Workbook
Name ByCategoryChartCategoryName: _xlfn.ANCHORARRAY('Chart Data'!$F$5)
Name ByCategoryChartMargin: _xlfn.ANCHORARRAY('Chart Data'!$G$5)
Name ByFridgeChartFridgeName: _xlfn.ANCHORARRAY('Chart Data'!$C$5)
Name ByFridgeChartMargin: _xlfn.ANCHORARRAY('Chart Data'!$D$5)
Name FormatDateYear: _xlfn.LAMBDA(_xlpm.Dates, TEXT(_xlpm.Dates, "mmmm yyyy"))
Name FrigolocoDiscountProvider: Settings!$C$5
Name MonthAndYearList: _xlfn.ANCHORARRAY('DV List'!$C$3)
Name MonthWiseLogisticsCost: _xlfn.ANCHORARRAY('Weekly Data'!$AG$5)
Name POSAndSoftwarePercentage: Settings!$C$3
Name RFIDTagAndTransactionFee: Settings!$C$4
Name WeeklyViewCateringFoodCost: 'Weekly View'!$F$4
Name WeeklyViewCateringTurnover: 'Weekly View'!$D$4
Name WeeklyViewLogisticsCost: 'Weekly View'!$G$4
Name WeeklyViewNumberOfDrops: 'Weekly View'!$H$4
Name WeeklyViewRemarks: 'Weekly View'!$J$4
Name WeeklyViewShowProgressCell: 'Weekly View'!$C$1
Name WeeklyViewTGTGTurnover: 'Weekly View'!$E$4
Name WeeklyViewUnsoldItems: 'Weekly View'!$I$4
Name WeeklyViewWeekNo: 'Weekly View'!$C$4
Name WeeklyViewYear: 'Weekly View'!$B$4
Name WeekStartDate: _xlfn.LAMBDA(_xlpm.WeekNo,_xlpm.Year,_xlfn.LET(_xlpm.\\LambdaName, "WeekStartDate", DATE(_xlpm.Year, 1, 1) - WEEKDAY(DATE(_xlpm.Year, 1, 1), 2) + 1 + (_xlpm.WeekNo - 1) * 7))

Sheet Settings
B2: Key | C2: Value | D2: Unit | E2: Comment
B3: POS & Software Percentage | C3: 0.09 | E3: Husky Fee on Sales
B4: RFID Tag & Transaction Fee | C4: 0.1 | D4: Per Item Sold | E4: We have RFID Tag on each product
B5: Frigoloco Discount Provider | C5: Frigo Loco Depot, Discount General | E5: Provider name in the discount part.
B9: TODO
B11: Take VAT off the turnover | C11: 0.06
B12: Create Monthly for 2026

Sheet Weekly View
C1: Tables updated successfully.
B3: Year | C3: Week No | D3: Busines Lunch CA | E3: TGTG CA | F3: Business Lunch Food Cost | G3: Logistics Cost | H3: # Of Drops | I3: Unsold Items | J3: Remarks
B4: 2026 | C4: 26 | E4: 55 | H4: 120 | I4: 0
C6: Start Date | D6: End Date | E6: In History?
C7: {=WeekStartDate(WeeklyViewWeekNo,WeeklyViewYear)} -> 46195 | D7: =C7+6 -> 46201 | E7: =NOT(ISNA(MATCH(C4,WeeklySummaryDataTable[Week No],0))) -> TRUE
B20: ="W" & C23&"-"&"W"&C31& " sales turnover, food margin and logistics" -> W18-W26 sales turnover, food margin and logistics | I20: ="Week " & WeeklyViewWeekNo & " Food Margin By Fridge" -> Week 26 Food Margin By Fridge | P20: ="Week " & WeeklyViewWeekNo & " Food Margin By Category" -> Week 26 Food Margin By Category
B22: Year | C22: Week No | D22: Logistics Cost | E22: Added Food Cost | F22: Sales Turnover | G22: Margin post logistics % | I22: Fridge Name | J22: Net Sale | K22: Food Cost | L22: Margin | M22: Margin% | P22: Category Name | Q22: Net Sale | R22: Food Cost | S22: Margin | T22: Margin %
B23: {=_xlfn.LET(_xlpm.WeekStartDate, C7, _xlpm.WeekOffsets, _xlfn.SEQUENCE(9, 1, -8, 1), _xlpm.TargetDates, _xlpm.WeekStartDate + _xlpm.WeekOffsets * 7, _xlfn.HSTACK(YEAR(_xlpm.TargetDates), _xlfn.ISOWEEKNUM(_xlpm.TargetDates)))} -> 2026 | C23: 18 | D23: {=_xlfn.MAP(_xlfn.CHOOSECOLS(_xlfn.ANCHORARRAY(B23), 1), _xlfn.CHOOSECOLS(_xlfn.ANCHORARRAY(B23), 2), _xlfn.LAMBDA(_xlpm.Year,_xlpm.WeekNo, _xlfn.XLOOKUP(1, (WeeklySummaryDataTable[Week No] = _xlpm.WeekNo) * (YEAR(WeeklySummaryDataTable[Start Date]) = _xlpm.Year), WeeklySummaryDataTable[Logistics Cost], 0)))} -> 1709 | E23: {=_xlfn.MAP(_xlfn.CHOOSECOLS(_xlfn.ANCHORARRAY(B23), 1), _xlfn.CHOOSECOLS(_xlfn.ANCHORARRAY(B23), 2), _xlfn.LAMBDA(_xlpm.Year,_xlpm.WeekNo, _xlfn.XLOOKUP(1, (WeeklySummaryDataTable[Week No] = _xlpm.WeekNo) * (YEAR(WeeklySummaryDataTable[Start Date]) = _xlpm.Year), WeeklySummaryDataTable[Added Food Cost], 0)))} -> 10551.3 | F23: {=_xlfn.MAP(_xlfn.CHOOSECOLS(_xlfn.ANCHORARRAY(B23), 1), _xlfn.CHOOSECOLS(_xlfn.ANCHORARRAY(B23), 2), _xlfn.LAMBDA(_xlpm.Year,_xlpm.WeekNo, _xlfn.XLOOKUP(1, (WeeklySummaryDataTable[Week No] = _xlpm.WeekNo) * (YEAR(WeeklySummaryDataTable[Start Date]) = _xlpm.Year), WeeklySummaryDataTable[Sales Turnover], 0)))} -> 13518.821 | G23: {=_xlfn.MAP(_xlfn.CHOOSECOLS(_xlfn.ANCHORARRAY(B23), 1), _xlfn.CHOOSECOLS(_xlfn.ANCHORARRAY(B23), 2), _xlfn.LAMBDA(_xlpm.Year,_xlpm.WeekNo, _xlfn.XLOOKUP(1, (WeeklySummaryDataTable[Week No] = _xlpm.WeekNo) * (YEAR(WeeklySummaryDataTable[Start Date]) = _xlpm.Year), WeeklySummaryDataTable[Net Margin %], 0)))} -> 0.0071988792 | I23: {=_xlfn.LET(_xlpm.SalesData, _xlfn._xlws.FILTER(_xlfn.HSTACK(ByFridgeWeeklySalesDataTable[Fridge Name], ByFridgeWeeklySalesDataTable[Net Sale]), (ByFridgeWeeklySalesDataTable[Week No] = WeeklyViewWeekNo) * (YEAR(ByFridgeWeeklySalesDataTable[Week Start Date]) = WeeklyViewYear)), _xlpm.FoodCostData, _xlfn._xlws.FILTER(_xlfn.HSTACK(ByFridgeWeeklyDispatchDataTable[Fridge Name], ByFridgeWeeklyDispatchDataTable[Foodcost Value]), (ByFridgeWeeklyDispatchDataTable[Week No] = WeeklyViewWeekNo) * (YEAR(ByFridgeWeeklyDispatchDataTable[Week Start Date]) = WeeklyViewYear)), _xlpm.StackedData, _xlfn.VSTACK(IFERROR(_xlpm.SalesData, ""), IFERROR(_xlpm.FoodCostData, "")), _xlpm.UniqueFridgeName, _xlfn.UNIQUE(_xlfn.CHOOSECOLS(_xlfn._xlws.FILTER(_xlpm.StackedData, _xlfn.CHOOSECOLS(_xlpm.StackedData, 1) <> ""), 1)), _xlpm.SalesByFridge, _xlfn.MAP(_xlpm.UniqueFridgeName, _xlfn.LAMBDA(_xlpm.FridgeName, IFERROR(_xlfn._xlws.FILTER(_xlfn.CHOOSECOLS(_xlpm.SalesData, 2), _xlfn.CHOOSECOLS(_xlpm.SalesData, 1) = _xlpm.FridgeName), 0))), _xlpm.FoodCost, _xlfn.MAP(_xlpm.UniqueFridgeName, _xlfn.LAMBDA(_xlpm.FridgeName, IFERROR(_xlfn.XLOOKUP(_xlpm.FridgeName, _xlfn.CHOOSECOLS(_xlpm.FoodCostData, 1), _xlfn.CHOOSECOLS(_xlpm.FoodCostData, 2), 0), 0))), _xlpm.Margin, _xlpm.SalesByFridge - _xlpm.FoodCost, _xlpm.MarginPercentage, IFERROR(_xlpm.Margin / _xlpm.SalesByFridge, 0), _xlpm.Sorted, _xlfn.SORTBY(_xlfn.HSTACK(_xlpm.UniqueFridgeName, _xlpm.SalesByFridge, _xlpm.FoodCost, _xlpm.Margin, _xlpm.MarginPercentage), _xlpm.Margin, 1), _xlpm.Result, _xlfn._xlws.FILTER(_xlpm.Sorted, _xlfn.CHOOSECOLS(_xlpm.Sorted, 1) <> 0), _xlpm.Result)} -> Allnex Freezer | J23: 283.88 | K23: 380.65 | L23: -96.77 | M23: -0.34088347 | P23: {=_xlfn.LET(_xlpm.SalesData, _xlfn._xlws.FILTER(_xlfn.HSTACK(ByCategoryWeeklySalesDataTable[Category Name], ByCategoryWeeklySalesDataTable[Net Sale]), (ByCategoryWeeklySalesDataTable[Week No] = WeeklyViewWeekNo) * (YEAR(ByCategoryWeeklySalesDataTable[Week Start Date]) = WeeklyViewYear)), _xlpm.FoodCostData, _xlfn._xlws.FILTER(_xlfn.HSTACK(ByCategoryWeeklyDispatchDataTable[Category Name], ByCategoryWeeklyDispatchDataTable[Foodcost Value]), (ByCategoryWeeklyDispatchDataTable[Week No] = WeeklyViewWeekNo) * (YEAR(ByCategoryWeeklyDispatchDataTable[Week Start Date]) = WeeklyViewYear)), _xlpm.StackedData, _xlfn.VSTACK(IFERROR(_xlpm.SalesData, ""), IFERROR(_xlpm.FoodCostData, "")), _xlpm.UniqueCategoryName, _xlfn.UNIQUE(_xlfn.CHOOSECOLS(_xlfn._xlws.FILTER(_xlpm.StackedData, NOT(ISNA(_xlfn.CHOOSECOLS(_xlpm.StackedData, 2)))), 1)), _xlpm.SalesByCategory, _xlfn.MAP(_xlpm.UniqueCategoryName, _xlfn.LAMBDA(_xlpm.CategoryName, IFERROR(_xlfn._xlws.FILTER(_xlfn.CHOOSECOLS(_xlpm.SalesData, 2), _xlfn.CHOOSECOLS(_xlpm.SalesData, 1) = _xlpm.CategoryName), 0))), _xlpm.FoodCost, _xlfn.MAP(_xlpm.UniqueCategoryName, _xlfn.LAMBDA(_xlpm.CategoryName, IFERROR(_xlfn.XLOOKUP(_xlpm.CategoryName, _xlfn.CHOOSECOLS(_xlpm.FoodCostData, 1), _xlfn.CHOOSECOLS(_xlpm.FoodCostData, 2), 0), 0))), _xlpm.Margin, _xlpm.SalesByCategory - _xlpm.FoodCost, _xlpm.MarginPercentage, IFERROR(_xlpm.Margin / _xlpm.SalesByCategory, 0), _xlpm.Sorted, _xlfn.SORTBY(_xlfn.HSTACK(_xlpm.UniqueCategoryName, _xlpm.SalesByCategory, _xlpm.FoodCost, _xlpm.Margin, _xlpm.MarginPercentage), _xlpm.Margin, 1), _xlpm.Sorted)} -> 10. Frozen Warm Dishes | Q23: 283.88 | R23: 380.65 | S23: -96.77 | T23: -0.34088347
B24: 2026 | C24: 19 | D24: 1728.72 | E24: 11043.59 | F24: 14729.009 | G24: 0.06280904 | I24: Spadel Brussels | J24: 125.58 | K24: 155.9 | L24: -30.32 | M24: -0.24143972 | P24: Unknown | Q24: 3.2 | R24: 0 | S24: 3.2 | T24: 1
B25: 2026 | C25: 20 | D25: 1514.2 | E25: 10473.69 | F25: 12398.028 | G25: -0.091487706 | I25: Lhoist Corbais | J25: 53.56 | K25: 81.67 | L25: -28.11 | M25: -0.52483196 | P25: 3. Warm Dishes Jar | Q25: 372.87 | R25: 227.3 | S25: 145.57 | T25: 0.39040416
B26: 2026 | C26: 21 | D26: 0 | E26: 0 | F26: 0 | G26: 0 | I26: Atelier rue du Cerf | J26: 117.48 | K26: 128.13 | L26: -10.65 | M26: -0.090653728 | P26: 4. Warm Dishes | Q26: 1938.6 | R26: 1602.13 | S26: 336.47 | T26: 0.1735634
B27: 2026 | C27: 22 | D27: 1583 | E27: 9993.46 | F27: 13073.66 | G27: 0.02766004 | I27: Velux | J27: 134.53 | K27: 141.01 | L27: -6.48 | M27: -0.048167695 | P27: 6. Snacks | Q27: 921.09 | R27: 534.78 | S27: 386.31 | T27: 0.41940527
B28: 2026 | C28: 23 | D28: 1983.33 | E28: 12099.23 | F28: 16621 | G28: 0.091500036 | I28: Brussels Airlines Vilvoorde | J28: 142.65 | K28: 143.2 | L28: -0.55 | M28: -0.0038555906 | P28: 8. Breakfast | Q28: 1442.95 | R28: 903 | S28: 539.95 | T28: 0.37419869
B29: 2026 | C29: 24 | D29: 1741 | E29: 12314.94 | F29: 16094.462 | G29: 0.032856516 | I29: Abbott Wavre | J29: 82.56 | K29: 71.24 | L29: 11.32 | M29: 0.1371124 | P29: 7. Drinks | Q29: 1155.95 | R29: 594.64 | S29: 561.31 | T29: 0.48558329
B30: 2026 | C30: 25 | D30: 1689 | E30: 0 | F30: 15332.038 | G30: 0.033876347 | I30: Brussels Airlines TFC | J30: 104.78 | K30: 88.52 | L30: 16.26 | M30: 0.15518229 | P30: 5. Desserts | Q30: 2801.86 | R30: 1922.15 | S30: 879.71 | T30: 0.31397357
B31: 2026 | C31: 26 | D31: 1711.6 | E31: 12267.45 | F31: 16903.538 | G31: 0.090223682 | I31: Brussels Airlines Airport | J31: 213.48 | K31: 196.76 | L31: 16.72 | M31: 0.078321154 | P31: 1. Cold Dishes | Q31: 3496.94 | R31: 2478.05 | S31: 1018.89 | T31: 0.29136617
I32: ABB Zaventem | J32: 177.09 | K32: 152.59 | L32: 24.5 | M32: 0.13834773 | P32: 2. Wraps & Sandwiches | Q32: 5500.41 | R32: 3596.64 | S32: 1903.77 | T32: 0.3461142
I33: Bank Degroof | J33: 130.52 | K33: 103.22 | L33: 27.3 | M33: 0.20916335 | P33: TOTAL | Q33: =SUM(Q23:Q32)/1.06 -> 16903.538 | R33: =SUM(R23:R32) -> 12239.34 | S33: =(SUM(S23:S32))-(SUM(Q23:Q32)*0.06) -> 4603.345 | T33: =S33/Q33 -> 0.27233027
I34: Engie Antwerpen | J34: 119.07 | K34: 78.36 | L34: 40.71 | M34: 0.34189972
I35: Lhoist Nivelles | J35: 171 | K35: 126.24 | L35: 44.76 | M35: 0.26175439
I36: PWC Ghent | J36: 167.81 | K36: 120.26 | L36: 47.55 | M36: 0.28335618
I37: Thermofisher Vilvoorde | J37: 118.05 | K37: 68.09 | L37: 49.96 | M37: 0.4232105
I38: Allianz Brussels | J38: 330.86 | K38: 253.37 | L38: 77.49 | M38: 0.23420782
I39: Engie Namur | J39: 295.12 | K39: 208.09 | L39: 87.03 | M39: 0.29489699
I40: Greenhouse Collection Links | J40: 338.56 | K40: 235.27 | L40: 103.29 | M40: 0.30508625
I41: Police Tubize | J41: 358.78 | K41: 255.49 | L41: 103.29 | M41: 0.2878923
I42: Interparking | J42: 289.1 | K42: 181.68 | L42: 107.42 | M42: 0.37156693
I43: Bia Group Overijse | J43: 347.05 | K43: 236.86 | L43: 110.19 | M43: 0.31750468
I44: Lhoist Limelette | J44: 257.57 | K44: 145.74 | L44: 111.83 | M44: 0.43417323
I45: GSV Huppertz Wilrijk | J45: 560.78 | K45: 410.42 | L45: 150.36 | M45: 0.26812654
... I63: RTBF Mediasquare 2e | J63: 1656.74 | K63: 1019.07 | L63: 637.67 | M63: 0.38489443
I66: TOTAL | J66: =SUM(J23:J64)/1.06 -> 16903.538 | K66: =SUM(K23:K64) -> 12239.34 | L66: =SUM(L23:L64)-(SUM(J23:J64)*0.06) -> 4603.345 | M66: =L66/J66 -> 0.27233027

Sheet Weekly Data
K1: =8869-M14 -> 8869
T2: MANUAL
E3: INCL VAT | H3: INCL VAT | I3: EX VAT | K3: From Wix/Manual Input | L3: Manual Input | M3: Comes from dispatch | N3: Manual/Wix | O3: Manual Input | P3: Manual Input | Q3: Manual Input | R3: Manual Input | S3: From Settings Sheet | U3: Calculated Fields | AF3: Month Wise Logistics Cost
B4: Week No | C4: Start Date | D4: End Date | E4: Total Sales | F4: Total Refund | G4: FrigoLoco Discount | H4: Customer Credit | I4: Sales Turnover | J4: # Of Fridge | K4: Catering Turnover | L4: TGTG Turnover | M4: Fridge Food Cost | N4: Added Food Cost | O4: Catering Food Cost | P4: Logistics Cost | Q4: # Of Drops | R4: Unsold Items | S4: Remarks | T4: POS & Software Percentage | U4: RFID Tags | V4: Per Fridge Turnover | W4: Food Margin In Euro | X4: Food Margin % | Y4: Food Margin for catering % | Z4: Logistic Cost Per Fridge | AA4: Logistic % | AB4: Unsold Item % | AC4: Net Margin | AD4: Net Margin % | AE4: Colonne1 | AG4: Month Name | AH4: Cost
B5: 34 | C5: 45887 | D5: 45893 | E5: 9171.81 | F5: 8.5 | G5: 144.22 | H5: 720.75 | I5: =(WeeklySummaryDataTable[[#This Row],[Total Sales]]+WeeklySummaryDataTable[[#This Row],[Customer Credit]]-WeeklySummaryDataTable[[#This Row],[Total Refund]])/1.06 -> 9324.5849 | J5: 31 | K5: 135 | L5: 55 | M5: =WeeklySummaryDataTable[[#This Row],[Added Food Cost]] -> 7090.91 | N5: {=IFERROR(SUM(_xlfn._xlws.FILTER(ByCategoryWeeklyAddedDataTable[Added Value],(ByCategoryWeeklyAddedDataTable[Week No]=WeeklySummaryDataTable[[#This Row],[Week No]])*(ByCategoryWeeklyAddedDataTable[Start Date]=WeeklySummaryDataTable[[#This Row],[Start Date]]))),0)} -> 7090.91 | O5: 100 | P5: 1572 | Q5: 120 | R5: 0 | T5: =WeeklySummaryDataTable[[#This Row],[Total Sales]]*Settings!$C$3 -> 825.4629 | U5: 0.1 | V5: =WeeklySummaryDataTable[[#This Row],[Sales Turnover]]/WeeklySummaryDataTable[[#This Row],['# Of Fridge]] -> 300.79306 | W5: =WeeklySummaryDataTable[[#This Row],[Sales Turnover]]-WeeklySummaryDataTable[[#This Row],[Fridge Food Cost]] -> 2233.6749 | X5: =WeeklySummaryDataTable[[#This Row],[Food Margin In Euro]]/WeeklySummaryDataTable[[#This Row],[Sales Turnover]] -> 0.23954685 | Y5: =IFERROR((WeeklySummaryDataTable[[#This Row],[Catering Turnover]]-WeeklySummaryDataTable[[#This Row],[Catering Food Cost]])/WeeklySummaryDataTable[[#This Row],[Catering Turnover]],0) -> 0.25925926 | Z5: =WeeklySummaryDataTable[[#This Row],[Logistics Cost]]/WeeklySummaryDataTable[[#This Row],['# Of Fridge]] -> 50.709677 | AA5: =IFERROR(WeeklySummaryDataTable[[#This Row],[Logistics Cost]]/WeeklySummaryDataTable[[#This Row],[Sales Turnover]],0) -> 0.16858659 | AB5: =IFERROR(WeeklySummaryDataTable[[#This Row],[Unsold Items]]/WeeklySummaryDataTable[[#This Row],[Sales Turnover]],0) -> 0 | AC5: =(WeeklySummaryDataTable[[#This Row],[Sales Turnover]]+WeeklySummaryDataTable[[#This Row],[Catering Turnover]]+WeeklySummaryDataTable[[#This Row],[TGTG Turnover]])-(WeeklySummaryDataTable[[#This Row],[Fridge Food Cost]]+WeeklySummaryDataTable[[#This Row],[Catering Food Cost]]+WeeklySummaryDataTable[[#This Row],[Logistics Cost]])-WeeklySummaryDataTable[[#This Row],[POS & Software Percentage]]-WeeklySummaryDataTable[[#This Row],[RFID Tags]] -> -73.887994 | AD5: =IFERROR(WeeklySummaryDataTable[[#This Row],[Net Margin]]/(WeeklySummaryDataTable[[#This Row],[Sales Turnover]]+WeeklySummaryDataTable[[#This Row],[Catering Turnover]]+WeeklySummaryDataTable[[#This Row],[TGTG Turnover]]),0) -> -0.0077657612 | AG5: {=_xlfn.LET( _xlpm.StartDates, WeeklySummaryDataTable[Start Date], _xlpm.LogisticsCost, WeeklySummaryDataTable[Logistics Cost], _xlpm.AllDates, _xlfn.DROP( _xlfn.REDUCE( "", _xlfn.SEQUENCE(ROWS(_xlpm.StartDates)), _xlfn.LAMBDA(_xlpm.a,_xlpm.c, _xlfn.LET( _xlpm.StartDate, INDEX(_xlpm.StartDates, _xlpm.c, 1), _xlpm.PerDayLogisticsCost, INDEX(_xlpm.LogisticsCost, _xlpm.c, 1) / 7, _xlpm.Curr, _xlfn.HSTACK(_xlfn.SEQUENCE(7, 1, _xlpm.StartDate), _xlfn.DROP(_xlfn.EXPAND("", 8, 1, _xlpm.PerDayLogisticsCost), 1)), _xlfn.VSTACK(_xlpm.a, _xlpm.Curr) ) ) ), 1 ), _xlpm.GroupedData, _xlfn.GROUPBY(FormatDateYear(_xlfn.CHOOSECOLS(_xlpm.AllDates, 1)), _xlfn.CHOOSECOLS(_xlpm.AllDates, 2), _xleta.SUM, 0, 0), _xlpm.GroupedData )} -> April 2026 | AH5: 7706.4657
B6: 35 | C6: 45894 | D6: 45900 | E6: 9401.42 | F6: 7.41 | G6: 135.24 | H6: 811.67 | I6: =(WeeklySummaryDataTable[[#This Row],[Total Sales]]+WeeklySummaryDataTable[[#This Row],[Customer Credit]]-WeeklySummaryDataTable[[#This Row],[Total Refund]])/1.06 -> 9628 | J6: 31 | L6: 0 | M6: =WeeklySummaryDataTable[[#This Row],[Added Food Cost]] -> 7621.21 | N6: {=IFERROR(SUM(_xlfn._xlws.FILTER(ByCategoryWeeklyAddedDataTable[Added Value],(ByCategoryWeeklyAddedDataTable[Week No]=WeeklySummaryDataTable[[#This Row],[Week No]])*(ByCategoryWeeklyAddedDataTable[Start Date]=WeeklySummaryDataTable[[#This Row],[Start Date]]))),0)} -> 7621.21 | P6: 1377 | Q6: 120 | R6: 0 | T6: =WeeklySummaryDataTable[[#This Row],[Total Sales]]*Settings!$C$3 -> 846.1278 | U6: 0.1 | V6: =WeeklySummaryDataTable[[#This Row],[Sales Turnover]]/WeeklySummaryDataTable[[#This Row],['# Of Fridge]] -> 310.58065 | W6: =WeeklySummaryDataTable[[#This Row],[Sales Turnover]]-WeeklySummaryDataTable[[#This Row],[Fridge Food Cost]] -> 2006.79 | X6: =WeeklySummaryDataTable[[#This Row],[Food Margin In Euro]]/WeeklySummaryDataTable[[#This Row],[Sales Turnover]] -> 0.2084327 | Y6: =IFERROR((WeeklySummaryDataTable[[#This Row],[Catering Turnover]]-WeeklySummaryDataTable[[#This Row],[Catering Food Cost]])/WeeklySummaryDataTable[[#This Row],[Catering Turnover]],0) -> 0 | Z6: =WeeklySummaryDataTable[[#This Row],[Logistics Cost]]/WeeklySummaryDataTable[[#This Row],['# Of Fridge]] -> 44.419355 | AA6: =IFERROR(WeeklySummaryDataTable[[#This Row],[Logistics Cost]]/WeeklySummaryDataTable[[#This Row],[Sales Turnover]],0) -> 0.14302036 | AB6: =IFERROR(WeeklySummaryDataTable[[#This Row],[Unsold Items]]/WeeklySummaryDataTable[[#This Row],[Sales Turnover]],0) -> 0 | AC6: =(WeeklySummaryDataTable[[#This Row],[Sales Turnover]]+WeeklySummaryDataTable[[#This Row],[Catering Turnover]]+WeeklySummaryDataTable[[#This Row],[TGTG Turnover]])-(WeeklySummaryDataTable[[#This Row],[Fridge Food Cost]]+WeeklySummaryDataTable[[#This Row],[Catering Food Cost]]+WeeklySummaryDataTable[[#This Row],[Logistics Cost]])-WeeklySummaryDataTable[[#This Row],[POS & Software Percentage]]-WeeklySummaryDataTable[[#This Row],[RFID Tags]] -> -216.4378 | AD6: =IFERROR(WeeklySummaryDataTable[[#This Row],[Net Margin]]/(WeeklySummaryDataTable[[#This Row],[Sales Turnover]]+WeeklySummaryDataTable[[#This Row],[Catering Turnover]]+WeeklySummaryDataTable[[#This Row],[TGTG Turnover]]),0) -> -0.022480037 | AG6: August 2025 | AH6: 2949
B7: 36 | C7: 45901 | D7: 45907 | E7: 10268.51 | F7: 31.74 | G7: 164.69 | H7: 810.23 | I7: =(WeeklySummaryDataTable[[#This Row],[Total Sales]]+WeeklySummaryDataTable[[#This Row],[Customer Credit]]-WeeklySummaryDataTable[[#This Row],[Total Refund]])/1.06 -> 10421.698 | J7: 32 | K7: 492 | L7: 0 | M7: =WeeklySummaryDataTable[[#This Row],[Added Food Cost]] -> 8024.38 | N7: {=IFERROR(SUM(_xlfn._xlws.FILTER(ByCategoryWeeklyAddedDataTable[Added Value],(ByCategoryWeeklyAddedDataTable[Week No]=WeeklySummaryDataTable[[#This Row],[Week No]])*(ByCategoryWeeklyAddedDataTable[Start Date]=WeeklySummaryDataTable[[#This Row],[Start Date]]))),0)} -> 8024.38 | O7: 298 | P7: 1598 | Q7: 120 | R7: 0 | T7: =WeeklySummaryDataTable[[#This Row],[Total Sales]]*Settings!$C$3 -> 924.1659 | U7: 0.1 | V7: =WeeklySummaryDataTable[[#This Row],[Sales Turnover]]/WeeklySummaryDataTable[[#This Row],['# Of Fridge]] -> 325.67807 | W7: =WeeklySummaryDataTable[[#This Row],[Sales Turnover]]-WeeklySummaryDataTable[[#This Row],[Fridge Food Cost]] -> 2397.3181 | X7: =WeeklySummaryDataTable[[#This Row],[Food Margin In Euro]]/WeeklySummaryDataTable[[#This Row],[Sales Turnover]] -> 0.23003143 | Y7: =IFERROR((WeeklySummaryDataTable[[#This Row],[Catering Turnover]]-WeeklySummaryDataTable[[#This Row],[Catering Food Cost]])/WeeklySummaryDataTable[[#This Row],[Catering Turnover]],0) -> 0.39430894 | Z7: =WeeklySummaryDataTable[[#This Row],[Logistics Cost]]/WeeklySummaryDataTable[[#This Row],['# Of Fridge]] -> 49.9375 | AA7: =IFERROR(WeeklySummaryDataTable[[#This Row],[Logistics Cost]]/WeeklySummaryDataTable[[#This Row],[Sales Turnover]],0) -> 0.15333394 | AB7: =IFERROR(WeeklySummaryDataTable[[#This Row],[Unsold Items]]/WeeklySummaryDataTable[[#This Row],[Sales Turnover]],0) -> 0 | AC7: =(WeeklySummaryDataTable[[#This Row],[Sales Turnover]]+WeeklySummaryDataTable[[#This Row],[Catering Turnover]]+WeeklySummaryDataTable[[#This Row],[TGTG Turnover]])-(WeeklySummaryDataTable[[#This Row],[Fridge Food Cost]]+WeeklySummaryDataTable[[#This Row],[Catering Food Cost]]+WeeklySummaryDataTable[[#This Row],[Logistics Cost]])-WeeklySummaryDataTable[[#This Row],[POS & Software Percentage]]-WeeklySummaryDataTable[[#This Row],[RFID Tags]] -> 69.052213 | AD7: =IFERROR(WeeklySummaryDataTable[[#This Row],[Net Margin]]/(WeeklySummaryDataTable[[#This Row],[Sales Turnover]]+WeeklySummaryDataTable[[#This Row],[Catering Turnover]]+WeeklySummaryDataTable[[#This Row],[TGTG Turnover]]),0) -> 0.0063271141 | AG7: December 2025 | AH7: 6201
B8: 37 | C8: 45908 | D8: 45914 | E8: 10672.49 | F8: 52.98 | G8: 192.55 | H8: 786.79 | I8: =(WeeklySummaryDataTable[[#This Row],[Total Sales]]+WeeklySummaryDataTable[[#This Row],[Customer Credit]]-WeeklySummaryDataTable[[#This Row],[Total Refund]])/1.06 -> 10760.66 | J8: 32 | K8: 378 | L8: 0 | M8: =WeeklySummaryDataTable[[#This Row],[Added Food Cost]] -> 8505.82 | N8: {=IFERROR(SUM(_xlfn._xlws.FILTER(ByCategoryWeeklyAddedDataTable[Added Value],(ByCategoryWeeklyAddedDataTable[Week No]=WeeklySummaryDataTable[[#This Row],[Week No]])*(ByCategoryWeeklyAddedDataTable[Start Date]=WeeklySummaryDataTable[[#This Row],[Start Date]]))),0)} -> 8505.82 | O8: 225 | P8: 1550 | Q8: 120 | R8: 0 | T8: =WeeklySummaryDataTable[[#This Row],[Total Sales]]*Settings!$C$3 -> 960.5241 | U8: 0.1 | V8: =WeeklySummaryDataTable[[#This Row],[Sales Turnover]]/WeeklySummaryDataTable[[#This Row],['# Of Fridge]] -> 336.27064 | W8: =WeeklySummaryDataTable[[#This Row],[Sales Turnover]]-WeeklySummaryDataTable[[#This Row],[Fridge Food Cost]] -> 2254.8404 | X8: =WeeklySummaryDataTable[[#This Row],[Food Margin In Euro]]/WeeklySummaryDataTable[[#This Row],[Sales Turnover]] -> 0.2095448 | Y8: =IFERROR((WeeklySummaryDataTable[[#This Row],[Catering Turnover]]-WeeklySummaryDataTable[[#This Row],[Catering Food Cost]])/WeeklySummaryDataTable[[#This Row],[Catering Turnover]],0) -> 0.4047619 | Z8: =WeeklySummaryDataTable[[#This Row],[Logistics Cost]]/WeeklySummaryDataTable[[#This Row],['# Of Fridge]] -> 48.4375 | AA8: =IFERROR(WeeklySummaryDataTable[[#This Row],[Logistics Cost]]/WeeklySummaryDataTable[[#This Row],[Sales Turnover]],0) -> 0.1440432 | AB8: =IFERROR(WeeklySummaryDataTable[[#This Row],[Unsold Items]]/WeeklySummaryDataTable[[#This Row],[Sales Turnover]],0) -> 0 | AC8: =(WeeklySummaryDataTable[[#This Row],[Sales Turnover]]+WeeklySummaryDataTable[[#This Row],[Catering Turnover]]+WeeklySummaryDataTable[[#This Row],[TGTG Turnover]])-(WeeklySummaryDataTable[[#This Row],[Fridge Food Cost]]+WeeklySummaryDataTable[[#This Row],[Catering Food Cost]]+WeeklySummaryDataTable[[#This Row],[Logistics Cost]])-WeeklySummaryDataTable[[#This Row],[POS & Software Percentage]]-WeeklySummaryDataTable[[#This Row],[RFID Tags]] -> -102.78372 | AD8: =IFERROR(WeeklySummaryDataTable[[#This Row],[Net Margin]]/(WeeklySummaryDataTable[[#This Row],[Sales Turnover]]+WeeklySummaryDataTable[[#This Row],[Catering Turnover]]+WeeklySummaryDataTable[[#This Row],[TGTG Turnover]]),0) -> -0.0092276557 | AG8: February 2026 | AH8: 6513.4514
B9: 38 | C9: 45915 | D9: 45921 | E9: 9878.48 | F9: 135.48 | G9: 170.42 | H9: 874.43 | I9: =(WeeklySummaryDataTable[[#This Row],[Total Sales]]+WeeklySummaryDataTable[[#This Row],[Customer Credit]]-WeeklySummaryDataTable[[#This Row],[Total Refund]])/1.06 -> 10016.443 | J9: 33 | K9: 575 | L9: 0 | M9: =WeeklySummaryDataTable[[#This Row],[Added Food Cost]] -> 8269.66 | N9: {=IFERROR(SUM(_xlfn._xlws.FILTER(ByCategoryWeeklyAddedDataTable[Added Value],(ByCategoryWeeklyAddedDataTable[Week No]=WeeklySummaryDataTable[[#This Row],[Week No]])*(ByCategoryWeeklyAddedDataTable[Start Date]=WeeklySummaryDataTable[[#This Row],[Start Date]]))),0)} -> 8269.66 | O9: 351 | P9: 1730 | Q9: 120 | R9: 0 | T9: =WeeklySummaryDataTable[[#This Row],[Total Sales]]*Settings!$C$3 -> 889.0632 | U9: 0.1 | V9: =WeeklySummaryDataTable[[#This Row],[Sales Turnover]]/WeeklySummaryDataTable[[#This Row],['# Of Fridge]] -> 303.52859 | W9: =WeeklySummaryDataTable[[#This Row],[Sales Turnover]]-WeeklySummaryDataTable[[#This Row],[Fridge Food Cost]] -> 1746.7834 | X9: =WeeklySummaryDataTable[[#This Row],[Food Margin In Euro]]/WeeklySummaryDataTable[[#This Row],[Sales Turnover]] -> 0.17439158 | Y9: =IFERROR((WeeklySummaryDataTable[[#This Row],[Catering Turnover]]-WeeklySummaryDataTable[[#This Row],[Catering Food Cost]])/WeeklySummaryDataTable[[#This Row],[Catering Turnover]],0) -> 0.38956522 | Z9: =WeeklySummaryDataTable[[#This Row],[Logistics Cost]]/WeeklySummaryDataTable[[#This Row],['# Of Fridge]] -> 52.424242 | AA9: =IFERROR(WeeklySummaryDataTable[[#This Row],[Logistics Cost]]/WeeklySummaryDataTable[[#This Row],[Sales Turnover]],0) -> 0.172716 | AB9: =IFERROR(WeeklySummaryDataTable[[#This Row],[Unsold Items]]/WeeklySummaryDataTable[[#This Row],[Sales Turnover]],0) -> 0 | AC9: =(WeeklySummaryDataTable[[#This Row],[Sales Turnover]]+WeeklySummaryDataTable[[#This Row],[Catering Turnover]]+WeeklySummaryDataTable[[#This Row],[TGTG Turnover]])-(WeeklySummaryDataTable[[#This Row],[Fridge Food Cost]]+WeeklySummaryDataTable[[#This Row],[Catering Food Cost]]+WeeklySummaryDataTable[[#This Row],[Logistics Cost]])-WeeklySummaryDataTable[[#This Row],[POS & Software Percentage]]-WeeklySummaryDataTable[[#This Row],[RFID Tags]] -> -648.3798 | AD9: =IFERROR(WeeklySummaryDataTable[[#This Row],[Net Margin]]/(WeeklySummaryDataTable[[#This Row],[Sales Turnover]]+WeeklySummaryDataTable[[#This Row],[Catering Turnover]]+WeeklySummaryDataTable[[#This Row],[TGTG Turnover]]),0) -> -0.061217322 | AG9: June 2026 | AH9: 7124.93
B10: 39 | C10: 45922 | D10: 45928 | E10: 10469.73 | F10: 19.39 | G10: 156.88 | H10: 698.13 | I10: =(WeeklySummaryDataTable[[#This Row],[Total Sales]]+WeeklySummaryDataTable[[#This Row],[Customer Credit]]-WeeklySummaryDataTable[[#This Row],[Total Refund]])/1.06 -> 10517.425 | J10: 33 | K10: 1043 | L10: 34 | M10: =WeeklySummaryDataTable[[#This Row],[Added Food Cost]] -> 8123.8 | N10: {=IFERROR(SUM(_xlfn._xlws.FILTER(ByCategoryWeeklyAddedDataTable[Added Value],(ByCategoryWeeklyAddedDataTable[Week No]=WeeklySummaryDataTable[[#This Row],[Week No]])*(ByCategoryWeeklyAddedDataTable[Start Date]=WeeklySummaryDataTable[[#This Row],[Start Date]]))),0)} -> 8123.8 | O10: =WeeklySummaryDataTable[[#This Row],[Catering Turnover]]-Q52 -> 1043 | P10: 1456 | Q10: 120 | R10: 0 | T10: =WeeklySummaryDataTable[[#This Row],[Total Sales]]*Settings!$C$3 -> 942.2757 | U10: 0.1 | V10: =WeeklySummaryDataTable[[#This Row],[Sales Turnover]]/WeeklySummaryDataTable[[#This Row],['# Of Fridge]] -> 318.70983 | W10: =WeeklySummaryDataTable[[#This Row],[Sales Turnover]]-WeeklySummaryDataTable[[#This Row],[Fridge Food Cost]] -> 2393.6245 | X10: =WeeklySummaryDataTable[[#This Row],[Food Margin In Euro]]/WeeklySummaryDataTable[[#This Row],[Sales Turnover]] -> 0.22758657 | Y10: =IFERROR((WeeklySummaryDataTable[[#This Row],[Catering Turnover]]-WeeklySummaryDataTable[[#This Row],[Catering Food Cost]])/WeeklySummaryDataTable[[#This Row],[Catering Turnover]],0) -> 0 | Z10: =WeeklySummaryDataTable[[#This Row],[Logistics Cost]]/WeeklySummaryDataTable[[#This Row],['# Of Fridge]] -> 44.121212 | AA10: =IFERROR(WeeklySummaryDataTable[[#This Row],[Logistics Cost]]/WeeklySummaryDataTable[[#This Row],[Sales Turnover]],0) -> 0.13843693 | AB10: =IFERROR(WeeklySummaryDataTable[[#This Row],[Unsold Items]]/WeeklySummaryDataTable[[#This Row],[Sales Turnover]],0) -> 0 | AC10: =(WeeklySummaryDataTable[[#This Row],[Sales Turnover]]+WeeklySummaryDataTable[[#This Row],[Catering Turnover]]+WeeklySummaryDataTable[[#This Row],[TGTG Turnover]])-(WeeklySummaryDataTable[[#This Row],[Fridge Food Cost]]+WeeklySummaryDataTable[[#This Row],[Catering Food Cost]]+WeeklySummaryDataTable[[#This Row],[Logistics Cost]])-WeeklySummaryDataTable[[#This Row],[POS & Software Percentage]]-WeeklySummaryDataTable[[#This Row],[RFID Tags]] -> 29.248828 | AD10: =IFERROR(WeeklySummaryDataTable[[#This Row],[Net Margin]]/(WeeklySummaryDataTable[[#This Row],[Sales Turnover]]+WeeklySummaryDataTable[[#This Row],[Catering Turnover]]+WeeklySummaryDataTable[[#This Row],[TGTG Turnover]]),0) -> 0.0025226632 | AG10: March 2026 | AH10: 7768.4943
B11: 40 | C11: 45929 | D11: 45935 | E11: 10458.71 | F11: 29.57 | G11: 158.94 | H11: 840.83 | I11: =(WeeklySummaryDataTable[[#This Row],[Total Sales]]+WeeklySummaryDataTable[[#This Row],[Customer Credit]]-WeeklySummaryDataTable[[#This Row],[Total Refund]])/1.06 -> 10632.047 | J11: 33 | K11: 441 | L11: 55 | M11: =WeeklySummaryDataTable[[#This Row],[Added Food Cost]] -> 8596.88 | N11: {=IFERROR(SUM(_xlfn._xlws.FILTER(ByCategoryWeeklyAddedDataTable[Added Value],(ByCategoryWeeklyAddedDataTable[Week No]=WeeklySummaryDataTable[[#This Row],[Week No]])*(ByCategoryWeeklyAddedDataTable[Start Date]=WeeklySummaryDataTable[[#This Row],[Start Date]]))),0)} -> 8596.88 | O11: =WeeklySummaryDataTable[[#This Row],[Catering Turnover]]-Q53 -> 283 | P11: 1527.56 | Q11: 120 | R11: 0 | S11: Friday Refill @Neuhaus | T11: =WeeklySummaryDataTable[[#This Row],[Total Sales]]*Settings!$C$3 -> 941.2839 | U11: 0.1 | V11: =WeeklySummaryDataTable[[#This Row],[Sales Turnover]]/WeeklySummaryDataTable[[#This Row],['# Of Fridge]] -> 322.18325 | W11: =WeeklySummaryDataTable[[#This Row],[Sales Turnover]]-WeeklySummaryDataTable[[#This Row],[Fridge Food Cost]] -> 2035.1672 | X11: =WeeklySummaryDataTable[[#This Row],[Food Margin In Euro]]/WeeklySummaryDataTable[[#This Row],[Sales Turnover]] -> 0.19141818 | Y11: =IFERROR((WeeklySummaryDataTable[[#This Row],[Catering Turnover]]-WeeklySummaryDataTable[[#This Row],[Catering Food Cost]])/WeeklySummaryDataTable[[#This Row],[Catering Turnover]],0) -> 0.35827664 | Z11: =WeeklySummaryDataTable[[#This Row],[Logistics Cost]]/WeeklySummaryDataTable[[#This Row],['# Of Fridge]] -> 46.289697 | AA11: =IFERROR(WeeklySummaryDataTable[[#This Row],[Logistics Cost]]/WeeklySummaryDataTable[[#This Row],[Sales Turnover]],0) -> 0.14367506 | AB11: =IFERROR(WeeklySummaryDataTable[[#This Row],[Unsold Items]]/WeeklySummaryDataTable[[#This Row],[Sales Turnover]],0) -> 0 | AC11: =(WeeklySummaryDataTable[[#This Row],[Sales Turnover]]+WeeklySummaryDataTable[[#This Row],[Catering Turnover]]+WeeklySummaryDataTable[[#This Row],[TGTG Turnover]])-(WeeklySummaryDataTable[[#This Row],[Fridge Food Cost]]+WeeklySummaryDataTable[[#This Row],[Catering Food Cost]]+WeeklySummaryDataTable[[#This Row],[Logistics Cost]])-WeeklySummaryDataTable[[#This Row],[POS & Software Percentage]]-WeeklySummaryDataTable[[#This Row],[RFID Tags]] -> -220.77673 | AD11: =IFERROR(WeeklySummaryDataTable[[#This Row],[Net Margin]]/(WeeklySummaryDataTable[[#This Row],[Sales Turnover]]+WeeklySummaryDataTable[[#This Row],[Catering Turnover]]+WeeklySummaryDataTable[[#This Row],[TGTG Turnover]]),0) -> -0.019839665 | AG11: May 2026 | AH11: 5558.3486
B12: 41 | C12: 45936 | D12: 45942 | E12: 10482.68 | F12: 18.12 | G12: 152.55 | H12: 776.65 | I12: =(WeeklySummaryDataTable[[#This Row],[Total Sales]]+WeeklySummaryDataTable[[#This Row],[Customer Credit]]-WeeklySummaryDataTable[[#This Row],[Total Refund]])/1.06 -> 10604.915 | J12: 34 | K12: 549 | L12: 55 | M12: =WeeklySummaryDataTable[[#This Row],[Added Food Cost]] -> 8385.28 | N12: {=IFERROR(SUM(_xlfn._xlws.FILTER(ByCategoryWeeklyAddedDataTable[Added Value],(ByCategoryWeeklyAddedDataTable[Week No]=WeeklySummaryDataTable[[#This Row],[Week No]])*(ByCategoryWeeklyAddedDataTable[Start Date]=WeeklySummaryDataTable[[#This Row],[Start Date]]))),0)} -> 8385.28 | O12: =WeeklySummaryDataTable[[#This Row],[Catering Turnover]]-Q54 -> 225 | P12: 1527.56 | Q12: 120 | R12: 0 | S12: Friday Refill @Neuhaus | T12: =WeeklySummaryDataTable[[#This Row],[Total Sales]]*Settings!$C$3 -> 943.4412 | U12: 0.1 | V12: =WeeklySummaryDataTable[[#This Row],[Sales Turnover]]/WeeklySummaryDataTable[[#This Row],['# Of Fridge]] -> 311.90927 | W12: =WeeklySummaryDataTable[[#This Row],[Sales Turnover]]-WeeklySummaryDataTable[[#This Row],[Fridge Food Cost]] -> 2219.6351 | X12: =WeeklySummaryDataTable[[#This Row],[Food Margin In Euro]]/WeeklySummaryDataTable[[#This Row],[Sales Turnover]] -> 0.20930249 | Y12: =IFERROR((WeeklySummaryDataTable[[#This Row],[Catering Turnover]]-WeeklySummaryDataTable[[#This Row],[Catering Food Cost]])/WeeklySummaryDataTable[[#This Row],[Catering Turnover]],0) -> 0.59016393 | Z12: =WeeklySummaryDataTable[[#This Row],[Logistics Cost]]/WeeklySummaryDataTable[[#This Row],['# Of Fridge]] -> 44.928235 | AA12: =IFERROR(WeeklySummaryDataTable[[#This Row],[Logistics Cost]]/WeeklySummaryDataTable[[#This Row],[Sales Turnover]],0) -> 0.14404264 | AB12: =IFERROR(WeeklySummaryDataTable[[#This Row],[Unsold Items]]/WeeklySummaryDataTable[[#This Row],[Sales Turnover]],0) -> 0 | AC12: =(WeeklySummaryDataTable[[#This Row],[Sales Turnover]]+WeeklySummaryDataTable[[#This Row],[Catering Turnover]]+WeeklySummaryDataTable[[#This Row],[TGTG Turnover]])-(WeeklySummaryDataTable[[#This Row],[Fridge Food Cost]]+WeeklySummaryDataTable[[#This Row],[Catering Food Cost]]+WeeklySummaryDataTable[[#This Row],[Logistics Cost]])-WeeklySummaryDataTable[[#This Row],[POS & Software Percentage]]-WeeklySummaryDataTable[[#This Row],[RFID Tags]] -> 127.53389 | AD12: =IFERROR(WeeklySummaryDataTable[[#This Row],[Net Margin]]/(WeeklySummaryDataTable[[#This Row],[Sales Turnover]]+WeeklySummaryDataTable[[#This Row],[Catering Turnover]]+WeeklySummaryDataTable[[#This Row],[TGTG Turnover]]),0) -> 0.011377898 | AG12: November 2025 | AH12: 6840.5714
B13: 42 | C13: 45943 | D13: 45949 | E13: 11672.22 | F13: 23.7 | G13: 284.18 | H13: 759.86 | I13: =(WeeklySummaryDataTable[[#This Row],[Total Sales]]+WeeklySummaryDataTable[[#This Row],[Customer Credit]]-WeeklySummaryDataTable[[#This Row],[Total Refund]])/1.06 -> 11706.019 | J13: 35 | K13: 668 | L13: 55 | M13: =WeeklySummaryDataTable[[#This Row],[Added Food Cost]] -> 9679.64 | N13: {=IFERROR(SUM(_xlfn._xlws.FILTER(ByCategoryWeeklyAddedDataTable[Added Value],(ByCategoryWeeklyAddedDataTable[Week No]=WeeklySummaryDataTable[[#This Row],[Week No]])*(ByCategoryWeeklyAddedDataTable[Start Date]=WeeklySummaryDataTable[[#This Row],[Start Date]]))),0)} -> 9679.64 | O13: =WeeklySummaryDataTable[[#This Row],[Catering Turnover]]-Q55 -> 429 | P13: 1768.75 | Q13: 120 | R13: 0 | T13: =WeeklySummaryDataTable[[#This Row],[Total Sales]]*Settings!$C$3 -> 1050.4998 | U13: 0.1 | V13: =WeeklySummaryDataTable[[#This Row],[Sales Turnover]]/WeeklySummaryDataTable[[#This Row],['# Of Fridge]] -> 334.45768 | W13: =WeeklySummaryDataTable[[#This Row],[Sales Turnover]]-WeeklySummaryDataTable[[#This Row],[Fridge Food Cost]] -> 2026.3789 | X13: =WeeklySummaryDataTable[[#This Row],[Food Margin In Euro]]/WeeklySummaryDataTable[[#This Row],[Sales Turnover]] -> 0.17310572 | Y13: =IFERROR((WeeklySummaryDataTable[[#This Row],[Catering Turnover]]-WeeklySummaryDataTable[[#This Row],[Catering Food Cost]])/WeeklySummaryDataTable[[#This Row],[Catering Turnover]],0) -> 0.35778443 | Z13: =WeeklySummaryDataTable[[#This Row],[Logistics Cost]]/WeeklySummaryDataTable[[#This Row],['# Of Fridge]] -> 50.535714 | AA13: =IFERROR(WeeklySummaryDataTable[[#This Row],[Logistics Cost]]/WeeklySummaryDataTable[[#This Row],[Sales Turnover]],0) -> 0.15109748 | AB13: =IFERROR(WeeklySummaryDataTable[[#This Row],[Unsold Items]]/WeeklySummaryDataTable[[#This Row],[Sales Turnover]],0) -> 0 | AC13: =(WeeklySummaryDataTable[[#This Row],[Sales Turnover]]+WeeklySummaryDataTable[[#This Row],[Catering Turnover]]+WeeklySummaryDataTable[[#This Row],[TGTG Turnover]])-(WeeklySummaryDataTable[[#This Row],[Fridge Food Cost]]+WeeklySummaryDataTable[[#This Row],[Catering Food Cost]]+WeeklySummaryDataTable[[#This Row],[Logistics Cost]])-WeeklySummaryDataTable[[#This Row],[POS & Software Percentage]]-WeeklySummaryDataTable[[#This Row],[RFID Tags]] -> -498.97093 | AD13: =IFERROR(WeeklySummaryDataTable[[#This Row],[Net Margin]]/(WeeklySummaryDataTable[[#This Row],[Sales Turnover]]+WeeklySummaryDataTable[[#This Row],[Catering Turnover]]+WeeklySummaryDataTable[[#This Row],[TGTG Turnover]]),0) -> -0.040145641 | AG13: October 2025 | AH13: 7362.6029
B14: 43 | C14: 45950 | D14: 45956 | E14: 12075.26 | F14: 16.59 | G14: 154.68 | H14: 731.63 | I14: =(WeeklySummaryDataTable[[#This Row],[Total Sales]]+WeeklySummaryDataTable[[#This Row],[Customer Credit]]-WeeklySummaryDataTable[[#This Row],[Total Refund]])/1.06 -> 12066.321 | J14: 35 | K14: 129 | L14: 55 | M14: {=IFERROR(SUM(_xlfn._xlws.FILTER(ByCategoryWeeklyDispatchDataTable[Foodcost Value],ByCategoryWeeklyDispatchDataTable[Week No]=WeeklySummaryDataTable[[#This Row],[Week No]])),0)} -> 0 | N14: {=IFERROR(SUM(_xlfn._xlws.FILTER(ByCategoryWeeklyAddedDataTable[Added Value],(ByCategoryWeeklyAddedDataTable[Week No]=WeeklySummaryDataTable[[#This Row],[Week No]])*(ByCategoryWeeklyAddedDataTable[Start Date]=WeeklySummaryDataTable[[#This Row],[Start Date]]))),0)} -> 9007.02 | O14: =129-48.3 -> 80.7 | P14: 1768.75 | Q14: 120 | R14: 0 | T14: =WeeklySummaryDataTable[[#This Row],[Total Sales]]*Settings!$C$3 -> 1086.7734 | U14: 0.1 | V14: =WeeklySummaryDataTable[[#This Row],[Sales Turnover]]/WeeklySummaryDataTable[[#This Row],['# Of Fridge]] -> 344.75202 | W14: =WeeklySummaryDataTable[[#This Row],[Sales Turnover]]-WeeklySummaryDataTable[[#This Row],[Fridge Food Cost]] -> 12066.321 | X14: =WeeklySummaryDataTable[[#This Row],[Food Margin In Euro]]/WeeklySummaryDataTable[[#This Row],[Sales Turnover]] -> 1 | Y14: =IFERROR((WeeklySummaryDataTable[[#This Row],[Catering Turnover]]-WeeklySummaryDataTable[[#This Row],[Catering Food Cost]])/WeeklySummaryDataTable[[#This Row],[Catering Turnover]],0) -> 0.3744186 | Z14: =WeeklySummaryDataTable[[#This Row],[Logistics Cost]]/WeeklySummaryDataTable[[#This Row],['# Of Fridge]] -> 50.535714 | AA14: =IFERROR(WeeklySummaryDataTable[[#This Row],[Logistics Cost]]/WeeklySummaryDataTable[[#This Row],[Sales Turnover]],0) -> 0.14658569 | AB14: =IFERROR(WeeklySummaryDataTable[[#This Row],[Unsold Items]]/WeeklySummaryDataTable[[#This Row],[Sales Turnover]],0) -> 0 | AC14: =(WeeklySummaryDataTable[[#This Row],[Sales Turnover]]+WeeklySummaryDataTable[[#This Row],[Catering Turnover]]+WeeklySummaryDataTable[[#This Row],[TGTG Turnover]])-(WeeklySummaryDataTable[[#This Row],[Fridge Food Cost]]+WeeklySummaryDataTable[[#This Row],[Catering Food Cost]]+WeeklySummaryDataTable[[#This Row],[Logistics Cost]])-WeeklySummaryDataTable[[#This Row],[POS & Software Percentage]]-WeeklySummaryDataTable[[#This Row],[RFID Tags]] -> 9313.9974 | AD14: =IFERROR(WeeklySummaryDataTable[[#This Row],[Net Margin]]/(WeeklySummaryDataTable[[#This Row],[Sales Turnover]]+WeeklySummaryDataTable[[#This Row],[Catering Turnover]]+WeeklySummaryDataTable[[#This Row],[TGTG Turnover]]),0) -> 0.76030641 | AG14: September 2025 | AH14: 6770.4457
B15: 44 | C15: 45957 | D15: 45963 | E15: 12093.57 | F15: 0 | G15: 203.7 | H15: 750.48 | I15: =(WeeklySummaryDataTable[[#This Row],[Total Sales]]+WeeklySummaryDataTable[[#This Row],[Customer Credit]]-WeeklySummaryDataTable[[#This Row],[Total Refund]])/1.06 -> 12117.028 | J15: 35 | K15: 288.4 | L15: 55 | M15: {=IFERROR(SUM(_xlfn._xlws.FILTER(ByCategoryWeeklyDispatchDataTable[Foodcost Value],ByCategoryWeeklyDispatchDataTable[Week No]=WeeklySummaryDataTable[[#This Row],[Week No]])),0)} -> 0 | N15: {=IFERROR(SUM(_xlfn._xlws.FILTER(ByCategoryWeeklyAddedDataTable[Added Value],(ByCategoryWeeklyAddedDataTable[Week No]=WeeklySummaryDataTable[[#This Row],[Week No]])*(ByCategoryWeeklyAddedDataTable[Start Date]=WeeklySummaryDataTable[[#This Row],[Start Date]]))),0)} -> 10395.01 | O15: 171.46 | P15: 1689 | Q15: 120 | R15: 0 | S15: Panne electricité chez Spadel - deucième semaine vacances toussaint | T15: =WeeklySummaryDataTable[[#This Row],[Total Sales]]*Settings!$C$3 -> 1088.4213 | U15: =U14 -> 0.1 | V15: =WeeklySummaryDataTable[[#This Row],[Sales Turnover]]/WeeklySummaryDataTable[[#This Row],['# Of Fridge]] -> 346.20081 | W15: =WeeklySummaryDataTable[[#This Row],[Sales Turnover]]-WeeklySummaryDataTable[[#This Row],[Fridge Food Cost]] -> 12117.028 | X15: =WeeklySummaryDataTable[[#This Row],[Food Margin In Euro]]/WeeklySummaryDataTable[[#This Row],[Sales Turnover]] -> 1 | Y15: =IFERROR((WeeklySummaryDataTable[[#This Row],[Catering Turnover]]-WeeklySummaryDataTable[[#This Row],[Catering Food Cost]])/WeeklySummaryDataTable[[#This Row],[Catering Turnover]],0) -> 0.4054785 | Z15: =WeeklySummaryDataTable[[#This Row],[Logistics Cost]]/WeeklySummaryDataTable[[#This Row],['# Of Fridge]] -> 48.257143 | AA15: =IFERROR(WeeklySummaryDataTable[[#This Row],[Logistics Cost]]/WeeklySummaryDataTable[[#This Row],[Sales Turnover]],0) -> 0.13939061 | AB15: =IFERROR(WeeklySummaryDataTable[[#This Row],[Unsold Items]]/WeeklySummaryDataTable[[#This Row],[Sales Turnover]],0) -> 0 | AC15: =(WeeklySummaryDataTable[[#This Row],[Sales Turnover]]+WeeklySummaryDataTable[[#This Row],[Catering Turnover]]+WeeklySummaryDataTable[[#This Row],[TGTG Turnover]])-(WeeklySummaryDataTable[[#This Row],[Fridge Food Cost]]+WeeklySummaryDataTable[[#This Row],[Catering Food Cost]]+WeeklySummaryDataTable[[#This Row],[Logistics Cost]])-WeeklySummaryDataTable[[#This Row],[POS & Software Percentage]]-WeeklySummaryDataTable[[#This Row],[RFID Tags]] -> 9511.447 | AD15: =IFERROR(WeeklySummaryDataTable[[#This Row],[Net Margin]]/(WeeklySummaryDataTable[[#This Row],[Sales Turnover]]+WeeklySummaryDataTable[[#This Row],[Catering Turnover]]+WeeklySummaryDataTable[[#This Row],[TGTG Turnover]]),0) -> 0.76333227
B16: 45 | C16: 45964 | D16: 45970 | E16: 13152.87 | F16: 44.64 | G16: 207.16 | H16: 812.08 | I16: =(WeeklySummaryDataTable[[#This Row],[Total Sales]]+WeeklySummaryDataTable[[#This Row],[Customer Credit]]-WeeklySummaryDataTable[[#This Row],[Total Refund]])/1.06 -> 13132.368 | J16: 35 | K16: 209 | L16: 55 | M16: {=IFERROR(SUM(_xlfn._xlws.FILTER(ByCategoryWeeklyDispatchDataTable[Foodcost Value],(ByCategoryWeeklyDispatchDataTable[Week No]=WeeklySummaryDataTable[[#This Row],[Week No]])*(ByCategoryWeeklyDispatchDataTable[Week Start Date]=WeeklySummaryDataTable[[#This Row],[Start Date]]))),0)} -> 0 | N16: {=IFERROR(SUM(_xlfn._xlws.FILTER(ByCategoryWeeklyAddedDataTable[Added Value],(ByCategoryWeeklyAddedDataTable[Week No]=WeeklySummaryDataTable[[#This Row],[Week No]])*(ByCategoryWeeklyAddedDataTable[Start Date]=WeeklySummaryDataTable[[#This Row],[Start Date]]))),0)} -> 10112.07 | O16: 137 | P16: 1811 | Q16: 120 | R16: 0 | T16: =WeeklySummaryDataTable[[#This Row],[Total Sales]]*Settings!$C$3 -> 1183.7583 | U16: 0.1 | V16: =WeeklySummaryDataTable[[#This Row],[Sales Turnover]]/WeeklySummaryDataTable[[#This Row],['# Of Fridge]] -> 375.21051 | W16: =WeeklySummaryDataTable[[#This Row],[Sales Turnover]]-WeeklySummaryDataTable[[#This Row],[Fridge Food Cost]] -> 13132.368 | X16: =WeeklySummaryDataTable[[#This Row],[Food Margin In Euro]]/WeeklySummaryDataTable[[#This Row],[Sales Turnover]] -> 1 | Y16: =IFERROR((WeeklySummaryDataTable[[#This Row],[Catering Turnover]]-WeeklySummaryDataTable[[#This Row],[Catering Food Cost]])/WeeklySummaryDataTable[[#This Row],[Catering Turnover]],0) -> 0.34449761 | Z16: =WeeklySummaryDataTable[[#This Row],[Logistics Cost]]/WeeklySummaryDataTable[[#This Row],['# Of Fridge]] -> 51.742857 | AA16: =IFERROR(WeeklySummaryDataTable[[#This Row],[Logistics Cost]]/WeeklySummaryDataTable[[#This Row],[Sales Turnover]],0) -> 0.13790354 | AB16: =IFERROR(WeeklySummaryDataTable[[#This Row],[Unsold Items]]/WeeklySummaryDataTable[[#This Row],[Sales Turnover]],0) -> 0 | AC16: =(WeeklySummaryDataTable[[#This Row],[Sales Turnover]]+WeeklySummaryDataTable[[#This Row],[Catering Turnover]]+WeeklySummaryDataTable[[#This Row],[TGTG Turnover]])-(WeeklySummaryDataTable[[#This Row],[Fridge Food Cost]]+WeeklySummaryDataTable[[#This Row],[Catering Food Cost]]+WeeklySummaryDataTable[[#This Row],[Logistics Cost]])-WeeklySummaryDataTable[[#This Row],[POS & Software Percentage]]-WeeklySummaryDataTable[[#This Row],[RFID Tags]] -> 10264.51 | AD16: =IFERROR(WeeklySummaryDataTable[[#This Row],[Net Margin]]/(WeeklySummaryDataTable[[#This Row],[Sales Turnover]]+WeeklySummaryDataTable[[#This Row],[Catering Turnover]]+WeeklySummaryDataTable[[#This Row],[TGTG Turnover]]),0) -> 0.76621586
B17: 46 | C17: 45971 | D17: 45977 | E17: 11038.47 | F17: 6.15 | G17: 187.55 | H17: 656.66 | I17: =(WeeklySummaryDataTable[[#This Row],[Total Sales]]+WeeklySummaryDataTable[[#This Row],[Customer Credit]]-WeeklySummaryDataTable[[#This Row],[Total Refund]])/1.06 -> 11027.34 | J17: 35 | K17: 570 | L17: 55 | M17: {=IFERROR(SUM(_xlfn._xlws.FILTER(ByCategoryWeeklyDispatchDataTable[Foodcost Value],(ByCategoryWeeklyDispatchDataTable[Week No]=WeeklySummaryDataTable[[#This Row],[Week No]])*(ByCategoryWeeklyDispatchDataTable[Week Start Date]=WeeklySummaryDataTable[[#This Row],[Start Date]]))),0)} -> 0 | N17: {=IFERROR(SUM(_xlfn._xlws.FILTER(ByCategoryWeeklyAddedDataTable[Added Value],(ByCategoryWeeklyAddedDataTable[Week No]=WeeklySummaryDataTable[[#This Row],[Week No]])*(ByCategoryWeeklyAddedDataTable[Start Date]=WeeklySummaryDataTable[[#This Row],[Start Date]]))),0)} -> 9032.725 | O17: 359 | P17: 1380 | Q17: 120 | R17: 0 | S17: Porte frigo RTBF Tombée 129€ à facturer | T17: =WeeklySummaryDataTable[[#This Row],[Total Sales]]*Settings!$C$3 -> 993.4623 | U17: 0.1 | V17: =WeeklySummaryDataTable[[#This Row],[Sales Turnover]]/WeeklySummaryDataTable[[#This Row],['# Of Fridge]] -> 315.06685 | W17: =WeeklySummaryDataTable[[#This Row],[Sales Turnover]]-WeeklySummaryDataTable[[#This Row],[Fridge Food Cost]] -> 11027.34 | X17: =WeeklySummaryDataTable[[#This Row],[Food Margin In Euro]]/WeeklySummaryDataTable[[#This Row],[Sales Turnover]] -> 1 | Y17: =IFERROR((WeeklySummaryDataTable[[#This Row],[Catering Turnover]]-WeeklySummaryDataTable[[#This Row],[Catering Food Cost]])/WeeklySummaryDataTable[[#This Row],[Catering Turnover]],0) -> 0.37017544 | Z17: =WeeklySummaryDataTable[[#This Row],[Logistics Cost]]/WeeklySummaryDataTable[[#This Row],['# Of Fridge]] -> 39.428571 | AA17: =IFERROR(WeeklySummaryDataTable[[#This Row],[Logistics Cost]]/WeeklySummaryDataTable[[#This Row],[Sales Turnover]],0) -> 0.12514351 | AB17: =IFERROR(WeeklySummaryDataTable[[#This Row],[Unsold Items]]/WeeklySummaryDataTable[[#This Row],[Sales Turnover]],0) -> 0 | AC17: =(WeeklySummaryDataTable[[#This Row],[Sales Turnover]]+WeeklySummaryDataTable[[#This Row],[Catering Turnover]]+WeeklySummaryDataTable[[#This Row],[TGTG Turnover]])-(WeeklySummaryDataTable[[#This Row],[Fridge Food Cost]]+WeeklySummaryDataTable[[#This Row],[Catering Food Cost]]+WeeklySummaryDataTable[[#This Row],[Logistics Cost]])-WeeklySummaryDataTable[[#This Row],[POS & Software Percentage]]-WeeklySummaryDataTable[[#This Row],[RFID Tags]] -> 8919.7773 | AD17: =IFERROR(WeeklySummaryDataTable[[#This Row],[Net Margin]]/(WeeklySummaryDataTable[[#This Row],[Sales Turnover]]+WeeklySummaryDataTable[[#This Row],[Catering Turnover]]+WeeklySummaryDataTable[[#This Row],[TGTG Turnover]]),0) -> 0.76549239
B18: 47 | C18: 45978 | D18: 45984 | E18: 14965.82 | F18: 44.07 | G18: 179.03 | H18: 904.3 | I18: =(WeeklySummaryDataTable[[#This Row],[Total Sales]]+WeeklySummaryDataTable[[#This Row],[Customer Credit]]-WeeklySummaryDataTable[[#This Row],[Total Refund]])/1.06 -> 14930.236 | J18: 37 | K18: 1304 | L18: 55 | M18: {=IFERROR(SUM(_xlfn._xlws.FILTER(ByCategoryWeeklyDispatchDataTable[Foodcost Value],(ByCategoryWeeklyDispatchDataTable[Week No]=WeeklySummaryDataTable[[#This Row],[Week No]])*(ByCategoryWeeklyDispatchDataTable[Week Start Date]=WeeklySummaryDataTable[[#This Row],[Start Date]]))),0)} -> 0 | N18: {=IFERROR(SUM(_xlfn._xlws.FILTER(ByCategoryWeeklyAddedDataTable[Added Value],(ByCategoryWeeklyAddedDataTable[Week No]=WeeklySummaryDataTable[[#This Row],[Week No]])*(ByCategoryWeeklyAddedDataTable[Start Date]=WeeklySummaryDataTable[[#This Row],[Start Date]]))),0)} -> 10837.072 | O18: 844 | P18: 1550 | Q18: 120 | R18: 0 | T18: =WeeklySummaryDataTable[[#This Row],[Total Sales]]*Settings!$C$3 -> 1346.9238 | U18: 0.1 | V18: =WeeklySummaryDataTable[[#This Row],[Sales Turnover]]/WeeklySummaryDataTable[[#This Row],['# Of Fridge]] -> 403.51989 | W18: =WeeklySummaryDataTable[[#This Row],[Sales Turnover]]-WeeklySummaryDataTable[[#This Row],[Fridge Food Cost]] -> 14930.236 | X18: =WeeklySummaryDataTable[[#This Row],[Food Margin In Euro]]/WeeklySummaryDataTable[[#This Row],[Sales Turnover]] -> 1 | Y18: =IFERROR((WeeklySummaryDataTable[[#This Row],[Catering Turnover]]-WeeklySummaryDataTable[[#This Row],[Catering Food Cost]])/WeeklySummaryDataTable[[#This Row],[Catering Turnover]],0) -> 0.35276074 | Z18: =WeeklySummaryDataTable[[#This Row],[Logistics Cost]]/WeeklySummaryDataTable[[#This Row],['# Of Fridge]] -> 41.891892 | AA18: =IFERROR(WeeklySummaryDataTable[[#This Row],[Logistics Cost]]/WeeklySummaryDataTable[[#This Row],[Sales Turnover]],0) -> 0.10381618 | AB18: =IFERROR(WeeklySummaryDataTable[[#This Row],[Unsold Items]]/WeeklySummaryDataTable[[#This Row],[Sales Turnover]],0) -> 0 | AC18: =(WeeklySummaryDataTable[[#This Row],[Sales Turnover]]+WeeklySummaryDataTable[[#This Row],[Catering Turnover]]+WeeklySummaryDataTable[[#This Row],[TGTG Turnover]])-(WeeklySummaryDataTable[[#This Row],[Fridge Food Cost]]+WeeklySummaryDataTable[[#This Row],[Catering Food Cost]]+WeeklySummaryDataTable[[#This Row],[Logistics Cost]])-WeeklySummaryDataTable[[#This Row],[POS & Software Percentage]]-WeeklySummaryDataTable[[#This Row],[RFID Tags]] -> 12548.212 | AD18: =IFERROR(WeeklySummaryDataTable[[#This Row],[Net Margin]]/(WeeklySummaryDataTable[[#This Row],[Sales Turnover]]+WeeklySummaryDataTable[[#This Row],[Catering Turnover]]+WeeklySummaryDataTable[[#This Row],[TGTG Turnover]]),0) -> 0.77033767
B19: 48 | C19: 45985 | D19: 45991 | E19: 13712.52 | F19: 37.88 | G19: 207.58 | H19: 859.54 | I19: =(WeeklySummaryDataTable[[#This Row],[Total Sales]]+WeeklySummaryDataTable[[#This Row],[Customer Credit]]-WeeklySummaryDataTable[[#This Row],[Total Refund]])/1.06 -> 13711.491 | J19: 37 | K19: 352 | L19: 55 | M19: {=IFERROR(SUM(_xlfn._xlws.FILTER(ByCategoryWeeklyDispatchDataTable[Foodcost Value],(ByCategoryWeeklyDispatchDataTable[Week No]=WeeklySummaryDataTable[[#This Row],[Week No]])*(ByCategoryWeeklyDispatchDataTable[Week Start Date]=WeeklySummaryDataTable[[#This Row],[Start Date]]))),0)} -> 0 | N19: {=IFERROR(SUM(_xlfn._xlws.FILTER(ByCategoryWeeklyAddedDataTable[Added Value],(ByCategoryWeeklyAddedDataTable[Week No]=WeeklySummaryDataTable[[#This Row],[Week No]])*(ByCategoryWeeklyAddedDataTable[Start Date]=WeeklySummaryDataTable[[#This Row],[Start Date]]))),0)} -> 10674.92 | O19: 212 | P19: 1617 | Q19: 120 | R19: 0 | T19: =WeeklySummaryDataTable[[#This Row],[Total Sales]]*Settings!$C$3 -> 1234.1268 | U19: 0.1 | V19: =WeeklySummaryDataTable[[#This Row],[Sales Turnover]]/WeeklySummaryDataTable[[#This Row],['# Of Fridge]] -> 370.58083 | W19: =WeeklySummaryDataTable[[#This Row],[Sales Turnover]]-WeeklySummaryDataTable[[#This Row],[Fridge Food Cost]] -> 13711.491 | X19: =WeeklySummaryDataTable[[#This Row],[Food Margin In Euro]]/WeeklySummaryDataTable[[#This Row],[Sales Turnover]] -> 1 | Y19: =IFERROR((WeeklySummaryDataTable[[#This Row],[Catering Turnover]]-WeeklySummaryDataTable[[#This Row],[Catering Food Cost]])/WeeklySummaryDataTable[[#This Row],[Catering Turnover]],0) -> 0.39772727 | Z19: =WeeklySummaryDataTable[[#This Row],[Logistics Cost]]/WeeklySummaryDataTable[[#This Row],['# Of Fridge]] -> 43.702703 | AA19: =IFERROR(WeeklySummaryDataTable[[#This Row],[Logistics Cost]]/WeeklySummaryDataTable[[#This Row],[Sales Turnover]],0) -> 0.11793029 | AB19: =IFERROR(WeeklySummaryDataTable[[#This Row],[Unsold Items]]/WeeklySummaryDataTable[[#This Row],[Sales Turnover]],0) -> 0 | AC19: =(WeeklySummaryDataTable[[#This Row],[Sales Turnover]]+WeeklySummaryDataTable[[#This Row],[Catering Turnover]]+WeeklySummaryDataTable[[#This Row],[TGTG Turnover]])-(WeeklySummaryDataTable[[#This Row],[Fridge Food Cost]]+WeeklySummaryDataTable[[#This Row],[Catering Food Cost]]+WeeklySummaryDataTable[[#This Row],[Logistics Cost]])-WeeklySummaryDataTable[[#This Row],[POS & Software Percentage]]-WeeklySummaryDataTable[[#This Row],[RFID Tags]] -> 11055.264 | AD19: =IFERROR(WeeklySummaryDataTable[[#This Row],[Net Margin]]/(WeeklySummaryDataTable[[#This Row],[Sales Turnover]]+WeeklySummaryDataTable[[#This Row],[Catering Turnover]]+WeeklySummaryDataTable[[#This Row],[TGTG Turnover]]),0) -> 0.7830344
B20: 49 | C20: 45992 | D20: 45998 | E20: 14803.99 | F20: 24.23 | G20: 262.56 | H20: 1017.83 | I20: =(WeeklySummaryDataTable[[#This Row],[Total Sales]]+WeeklySummaryDataTable[[#This Row],[Customer Credit]]-WeeklySummaryDataTable[[#This Row],[Total Refund]])/1.06 -> 14903.387 | J20: 37 | K20: 1008 | L20: 55 | M20: {=IFERROR(SUM(_xlfn._xlws.FILTER(ByCategoryWeeklyDispatchDataTable[Foodcost Value],(ByCategoryWeeklyDispatchDataTable[Week No]=WeeklySummaryDataTable[[#This Row],[Week No]])*(ByCategoryWeeklyDispatchDataTable[Week Start Date]=WeeklySummaryDataTable[[#This Row],[Start Date]]))),0)} -> 0 | N20: {=IFERROR(SUM(_xlfn._xlws.FILTER(ByCategoryWeeklyAddedDataTable[Added Value],(ByCategoryWeeklyAddedDataTable[Week No]=WeeklySummaryDataTable[[#This Row],[Week No]])*(ByCategoryWeeklyAddedDataTable[Start Date]=WeeklySummaryDataTable[[#This Row],[Start Date]]))),0)} -> 12033.34 | O20: 396.5 | P20: 1617 | Q20: 120 | R20: 0 | S20: 3 livreurs absent lundi, lancement 2 nouveau clients Zoetis et Thermo Vilvoorde | T20: =WeeklySummaryDataTable[[#This Row],[Total Sales]]*Settings!$C$3 -> 1332.3591 | U20: =WeeklySummaryDataTable[[#This Row],[Total Refund]]*Settings!$C$3 -> 2.1807 | V20: =WeeklySummaryDataTable[[#This Row],[Sales Turnover]]/WeeklySummaryDataTable[[#This Row],['# Of Fridge]] -> 402.79424 | W20: =WeeklySummaryDataTable[[#This Row],[Sales Turnover]]-WeeklySummaryDataTable[[#This Row],[Fridge Food Cost]] -> 14903.387 | X20: =WeeklySummaryDataTable[[#This Row],[Food Margin In Euro]]/WeeklySummaryDataTable[[#This Row],[Sales Turnover]] -> 1 | Y20: =IFERROR((WeeklySummaryDataTable[[#This Row],[Catering Turnover]]-WeeklySummaryDataTable[[#This Row],[Catering Food Cost]])/WeeklySummaryDataTable[[#This Row],[Catering Turnover]],0) -> 0.60664683 | Z20: =WeeklySummaryDataTable[[#This Row],[Logistics Cost]]/WeeklySummaryDataTable[[#This Row],['# Of Fridge]] -> 43.702703 | AA20: =IFERROR(WeeklySummaryDataTable[[#This Row],[Logistics Cost]]/WeeklySummaryDataTable[[#This Row],[Sales Turnover]],0) -> 0.10849883 | AB20: =IFERROR(WeeklySummaryDataTable[[#This Row],[Unsold Items]]/WeeklySummaryDataTable[[#This Row],[Sales Turnover]],0) -> 0 | AC20: =(WeeklySummaryDataTable[[#This Row],[Sales Turnover]]+WeeklySummaryDataTable[[#This Row],[Catering Turnover]]+WeeklySummaryDataTable[[#This Row],[TGTG Turnover]])-(WeeklySummaryDataTable[[#This Row],[Fridge Food Cost]]+WeeklySummaryDataTable[[#This Row],[Catering Food Cost]]+WeeklySummaryDataTable[[#This Row],[Logistics Cost]])-WeeklySummaryDataTable[[#This Row],[POS & Software Percentage]]-WeeklySummaryDataTable[[#This Row],[RFID Tags]] -> 12618.347 | AD20: =IFERROR(WeeklySummaryDataTable[[#This Row],[Net Margin]]/(WeeklySummaryDataTable[[#This Row],[Sales Turnover]]+WeeklySummaryDataTable[[#This Row],[Catering Turnover]]+WeeklySummaryDataTable[[#This Row],[TGTG Turnover]]),0) -> 0.79030698
B21: 50 | C21: 45999 | D21: 46005 | E21: 14189.5 | F21: 64.45 | G21: 302.1 | H21: 859.02 | I21: =(WeeklySummaryDataTable[[#This Row],[Total Sales]]+WeeklySummaryDataTable[[#This Row],[Customer Credit]]-WeeklySummaryDataTable[[#This Row],[Total Refund]])/1.06 -> 14135.915 | J21: 36 | K21: 375 | L21: 55 | M21: {=IFERROR(SUM(_xlfn._xlws.FILTER(ByCategoryWeeklyDispatchDataTable[Foodcost Value],(ByCategoryWeeklyDispatchDataTable[Week No]=WeeklySummaryDataTable[[#This Row],[Week No]])*(ByCategoryWeeklyDispatchDataTable[Week Start Date]=WeeklySummaryDataTable[[#This Row],[Start Date]]))),0)} -> 0 | N21: {=IFERROR(SUM(_xlfn._xlws.FILTER(ByCategoryWeeklyAddedDataTable[Added Value],(ByCategoryWeeklyAddedDataTable[Week No]=WeeklySummaryDataTable[[#This Row],[Week No]])*(ByCategoryWeeklyAddedDataTable[Start Date]=WeeklySummaryDataTable[[#This Row],[Start Date]]))),0)} -> 12059.72 | O21: 237 | P21: 1792 | Q21: 120 | R21: 0 | S21: Pas livraison Viangreo, remplacé par Colors Kitchen 2 proxideal, Livraison Zoetis apres midi et Namur pas livré | T21: =WeeklySummaryDataTable[[#This Row],[Total Sales]]*Settings!$C$3 -> 1277.055 | U21: 0.1 | V21: =WeeklySummaryDataTable[[#This Row],[Sales Turnover]]/WeeklySummaryDataTable[[#This Row],['# Of Fridge]] -> 392.66431 | W21: =WeeklySummaryDataTable[[#This Row],[Sales Turnover]]-WeeklySummaryDataTable[[#This Row],[Fridge Food Cost]] -> 14135.915 | X21: =WeeklySummaryDataTable[[#This Row],[Food Margin In Euro]]/WeeklySummaryDataTable[[#This Row],[Sales Turnover]] -> 1 | Y21: =IFERROR((WeeklySummaryDataTable[[#This Row],[Catering Turnover]]-WeeklySummaryDataTable[[#This Row],[Catering Food Cost]])/WeeklySummaryDataTable[[#This Row],[Catering Turnover]],0) -> 0.368 | Z21: =WeeklySummaryDataTable[[#This Row],[Logistics Cost]]/WeeklySummaryDataTable[[#This Row],['# Of Fridge]] -> 49.777778 | AA21: =IFERROR(WeeklySummaryDataTable[[#This Row],[Logistics Cost]]/WeeklySummaryDataTable[[#This Row],[Sales Turnover]],0) -> 0.1267693 | AB21: =IFERROR(WeeklySummaryDataTable[[#This Row],[Unsold Items]]/WeeklySummaryDataTable[[#This Row],[Sales Turnover]],0) -> 0 | AC21: =(WeeklySummaryDataTable[[#This Row],[Sales Turnover]]+WeeklySummaryDataTable[[#This Row],[Catering Turnover]]+WeeklySummaryDataTable[[#This Row],[TGTG Turnover]])-(WeeklySummaryDataTable[[#This Row],[Fridge Food Cost]]+WeeklySummaryDataTable[[#This Row],[Catering Food Cost]]+WeeklySummaryDataTable[[#This Row],[Logistics Cost]])-WeeklySummaryDataTable[[#This Row],[POS & Software Percentage]]-WeeklySummaryDataTable[[#This Row],[RFID Tags]] -> 11259.76 | AD21: =IFERROR(WeeklySummaryDataTable[[#This Row],[Net Margin]]/(WeeklySummaryDataTable[[#This Row],[Sales Turnover]]+WeeklySummaryDataTable[[#This Row],[Catering Turnover]]+WeeklySummaryDataTable[[#This Row],[TGTG Turnover]]),0) -> 0.77302113
B22: 51 | C22: 46006 | D22: 46012 | E22: 14072.71 | F22: 16.35 | G22: 262.53 | H22: 811.98 | I22: =(WeeklySummaryDataTable[[#This Row],[Total Sales]]+WeeklySummaryDataTable[[#This Row],[Customer Credit]]-WeeklySummaryDataTable[[#This Row],[Total Refund]])/1.06 -> 14026.736 | J22: 36 | K22: 456 | L22: 75 | M22: {=IFERROR(SUM(_xlfn._xlws.FILTER(ByCategoryWeeklyDispatchDataTable[Foodcost Value],(ByCategoryWeeklyDispatchDataTable[Week No]=WeeklySummaryDataTable[[#This Row],[Week No]])*(ByCategoryWeeklyDispatchDataTable[Week Start Date]=WeeklySummaryDataTable[[#This Row],[Start Date]]))),0)} -> 0 | N22: {=IFERROR(SUM(_xlfn._xlws.FILTER(ByCategoryWeeklyAddedDataTable[Added Value],(ByCategoryWeeklyAddedDataTable[Week No]=WeeklySummaryDataTable[[#This Row],[Week No]])*(ByCategoryWeeklyAddedDataTable[Start Date]=WeeklySummaryDataTable[[#This Row],[Start Date]]))),0)} -> 10217.06 | O22: 300 | P22: 1700 | Q22: 120 | R22: 0 | S22: Engie Namur fermé, Engie bxl et Abbot non livré le jeudi car grêve des tracteurs donc moins de conso. VDD départ en vacances | T22: =WeeklySummaryDataTable[[#This Row],[Total Sales]]*Settings!$C$3 -> 1266.5439 | U22: 0.1 | V22: =WeeklySummaryDataTable[[#This Row],[Sales Turnover]]/WeeklySummaryDataTable[[#This Row],['# Of Fridge]] -> 389.63155 | W22: =WeeklySummaryDataTable[[#This Row],[Sales Turnover]]-WeeklySummaryDataTable[[#This Row],[Fridge Food Cost]] -> 14026.736 | X22: =WeeklySummaryDataTable[[#This Row],[Food Margin In Euro]]/WeeklySummaryDataTable[[#This Row],[Sales Turnover]] -> 1 | Y22: =IFERROR((WeeklySummaryDataTable[[#This Row],[Catering Turnover]]-WeeklySummaryDataTable[[#This Row],[Catering Food Cost]])/WeeklySummaryDataTable[[#This Row],[Catering Turnover]],0) -> 0.34210526 | Z22: =WeeklySummaryDataTable[[#This Row],[Logistics Cost]]/WeeklySummaryDataTable[[#This Row],['# Of Fridge]] -> 47.222222 | AA22: =IFERROR(WeeklySummaryDataTable[[#This Row],[Logistics Cost]]/WeeklySummaryDataTable[[#This Row],[Sales Turnover]],0) -> 0.12119712 | AB22: =IFERROR(WeeklySummaryDataTable[[#This Row],[Unsold Items]]/WeeklySummaryDataTable[[#This Row],[Sales Turnover]],0) -> 0 | AC22: =(WeeklySummaryDataTable[[#This Row],[Sales Turnover]]+WeeklySummaryDataTable[[#This Row],[Catering Turnover]]+WeeklySummaryDataTable[[#This Row],[TGTG Turnover]])-(WeeklySummaryDataTable[[#This Row],[Fridge Food Cost]]+WeeklySummaryDataTable[[#This Row],[Catering Food Cost]]+WeeklySummaryDataTable[[#This Row],[Logistics Cost]])-WeeklySummaryDataTable[[#This Row],[POS & Software Percentage]]-WeeklySummaryDataTable[[#This Row],[RFID Tags]] -> 11291.092 | AD22: =IFERROR(WeeklySummaryDataTable[[#This Row],[Net Margin]]/(WeeklySummaryDataTable[[#This Row],[Sales Turnover]]+WeeklySummaryDataTable[[#This Row],[Catering Turnover]]+WeeklySummaryDataTable[[#This Row],[TGTG Turnover]]),0) -> 0.7756077
B23: 52 | C23: 46013 | D23: 46019 | E23: =5479.51999999998-165 -> 5314.52 | F23: 0 | G23: 132.47 | H23: 384.71 | I23: =(WeeklySummaryDataTable[[#This Row],[Total Sales]]+WeeklySummaryDataTable[[#This Row],[Customer Credit]]-WeeklySummaryDataTable[[#This Row],[Total Refund]])/1.06 -> 5376.6321 | J23: 35 | K23: 0 | L23: 55 | M23: {=IFERROR(SUM(_xlfn._xlws.FILTER(ByCategoryWeeklyDispatchDataTable[Foodcost Value],(ByCategoryWeeklyDispatchDataTable[Week No]=WeeklySummaryDataTable[[#This Row],[Week No]])*(ByCategoryWeeklyDispatchDataTable[Week Start Date]=WeeklySummaryDataTable[[#This Row],[Start Date]]))),0)} -> 0 | N23: {=IFERROR(SUM(_xlfn._xlws.FILTER(ByCategoryWeeklyAddedDataTable[Added Value],(ByCategoryWeeklyAddedDataTable[Week No]=WeeklySummaryDataTable[[#This Row],[Week No]])*(ByCategoryWeeklyAddedDataTable[Start Date]=WeeklySummaryDataTable[[#This Row],[Start Date]]))),0)} -> 4963.78 | O23: 0 | P23: 1092 | Q23: 120 | R23: 0 | S23: Semaine de congé scolaire + Noel. Engie Namur fermé | T23: =WeeklySummaryDataTable[[#This Row],[Total Sales]]*Settings!$C$3 -> 478.3068 | U23: 0.1 | V23: =WeeklySummaryDataTable[[#This Row],[Sales Turnover]]/WeeklySummaryDataTable[[#This Row],['# Of Fridge]] -> 153.61806 | W23: =WeeklySummaryDataTable[[#This Row],[Sales Turnover]]-WeeklySummaryDataTable[[#This Row],[Fridge Food Cost]] -> 5376.6321 | X23: =WeeklySummaryDataTable[[#This Row],[Food Margin In Euro]]/WeeklySummaryDataTable[[#This Row],[Sales Turnover]] -> 1 | Y23: =IFERROR((WeeklySummaryDataTable[[#This Row],[Catering Turnover]]-WeeklySummaryDataTable[[#This Row],[Catering Food Cost]])/WeeklySummaryDataTable[[#This Row],[Catering Turnover]],0) -> 0 | Z23: =WeeklySummaryDataTable[[#This Row],[Logistics Cost]]/WeeklySummaryDataTable[[#This Row],['# Of Fridge]] -> 31.2 | AA23: =IFERROR(WeeklySummaryDataTable[[#This Row],[Logistics Cost]]/WeeklySummaryDataTable[[#This Row],[Sales Turnover]],0) -> 0.20310112 | AB23: =IFERROR(WeeklySummaryDataTable[[#This Row],[Unsold Items]]/WeeklySummaryDataTable[[#This Row],[Sales Turnover]],0) -> 0 | AC23: =(WeeklySummaryDataTable[[#This Row],[Sales Turnover]]+WeeklySummaryDataTable[[#This Row],[Catering Turnover]]+WeeklySummaryDataTable[[#This Row],[TGTG Turnover]])-(WeeklySummaryDataTable[[#This Row],[Fridge Food Cost]]+WeeklySummaryDataTable[[#This Row],[Catering Food Cost]]+WeeklySummaryDataTable[[#This Row],[Logistics Cost]])-WeeklySummaryDataTable[[#This Row],[POS & Software Percentage]]-WeeklySummaryDataTable[[#This Row],[RFID Tags]] -> 3861.2253 | AD23: =IFERROR(WeeklySummaryDataTable[[#This Row],[Net Margin]]/(WeeklySummaryDataTable[[#This Row],[Sales Turnover]]+WeeklySummaryDataTable[[#This Row],[Catering Turnover]]+WeeklySummaryDataTable[[#This Row],[TGTG Turnover]]),0) -> 0.71087755
B24: 6 | C24: 46055 | D24: 46061 | E24: 16893.12 | F24: 59.65 | G24: 342.52 | H24: 831.22 | I24: =(WeeklySummaryDataTable[[#This Row],[Total Sales]]+WeeklySummaryDataTable[[#This Row],[Customer Credit]]-WeeklySummaryDataTable[[#This Row],[Total Refund]])/1.06 -> 16664.802 | J24: 39 | K24: 375 | L24: 55 | M24: {=IFERROR(SUM(_xlfn._xlws.FILTER(ByCategoryWeeklyDispatchDataTable[Foodcost Value],(ByCategoryWeeklyDispatchDataTable[Week No]=WeeklySummaryDataTable[[#This Row],[Week No]])*(ByCategoryWeeklyDispatchDataTable[Week Start Date]=WeeklySummaryDataTable[[#This Row],[Start Date]]))),0)} -> 0 | N24: {=IFERROR(SUM(_xlfn._xlws.FILTER(ByCategoryWeeklyAddedDataTable[Added Value],(ByCategoryWeeklyAddedDataTable[Week No]=WeeklySummaryDataTable[[#This Row],[Week No]])*(ByCategoryWeeklyAddedDataTable[Start Date]=WeeklySummaryDataTable[[#This Row],[Start Date]]))),0)} -> 13284.01 | O24: 250 | P24: 1792 | Q24: 120 | R24: 0 | T24: =WeeklySummaryDataTable[[#This Row],[Total Sales]]*Settings!$C$3 -> 1520.3808 | U24: 0.1 | V24: =WeeklySummaryDataTable[[#This Row],[Sales Turnover]]/WeeklySummaryDataTable[[#This Row],['# Of Fridge]] -> 427.30261 | W24: =WeeklySummaryDataTable[[#This Row],[Sales Turnover]]-WeeklySummaryDataTable[[#This Row],[Fridge Food Cost]] -> 16664.802 | X24: =WeeklySummaryDataTable[[#This Row],[Food Margin In Euro]]/WeeklySummaryDataTable[[#This Row],[Sales Turnover]] -> 1 | Y24: =IFERROR((WeeklySummaryDataTable[[#This Row],[Catering Turnover]]-WeeklySummaryDataTable[[#This Row],[Catering Food Cost]])/WeeklySummaryDataTable[[#This Row],[Catering Turnover]],0) -> 0.33333333 | Z24: =WeeklySummaryDataTable[[#This Row],[Logistics Cost]]/WeeklySummaryDataTable[[#This Row],['# Of Fridge]] -> 45.948718 | AA24: =IFERROR(WeeklySummaryDataTable[[#This Row],[Logistics Cost]]/WeeklySummaryDataTable[[#This Row],[Sales Turnover]],0) -> 0.10753203 | AB24: =IFERROR(WeeklySummaryDataTable[[#This Row],[Unsold Items]]/WeeklySummaryDataTable[[#This Row],[Sales Turnover]],0) -> 0 | AC24: =(WeeklySummaryDataTable[[#This Row],[Sales Turnover]]+WeeklySummaryDataTable[[#This Row],[Catering Turnover]]+WeeklySummaryDataTable[[#This Row],[TGTG Turnover]])-(WeeklySummaryDataTable[[#This Row],[Fridge Food Cost]]+WeeklySummaryDataTable[[#This Row],[Catering Food Cost]]+WeeklySummaryDataTable[[#This Row],[Logistics Cost]])-WeeklySummaryDataTable[[#This Row],[POS & Software Percentage]]-WeeklySummaryDataTable[[#This Row],[RFID Tags]] -> 13532.321 | AD24: =IFERROR(WeeklySummaryDataTable[[#This Row],[Net Margin]]/(WeeklySummaryDataTable[[#This Row],[Sales Turnover]]+WeeklySummaryDataTable[[#This Row],[Catering Turnover]]+WeeklySummaryDataTable[[#This Row],[TGTG Turnover]]),0) -> 0.79160444
B25: 7 | C25: 46062 | D25: 46068 | E25: 16370.25 | F25: 12.59 | G25: 590.35 | H25: 836.59 | I25: =(WeeklySummaryDataTable[[#This Row],[Total Sales]]+WeeklySummaryDataTable[[#This Row],[Customer Credit]]-WeeklySummaryDataTable[[#This Row],[Total Refund]])/1.06 -> 16220.991 | J25: 38 | K25: 375 | L25: 55 | M25: {=IFERROR(SUM(_xlfn._xlws.FILTER(ByCategoryWeeklyDispatchDataTable[Foodcost Value],(ByCategoryWeeklyDispatchDataTable[Week No]=WeeklySummaryDataTable[[#This Row],[Week No]])*(ByCategoryWeeklyDispatchDataTable[Week Start Date]=WeeklySummaryDataTable[[#This Row],[Start Date]]))),0)} -> 0 | N25: {=IFERROR(SUM(_xlfn._xlws.FILTER(ByCategoryWeeklyAddedDataTable[Added Value],(ByCategoryWeeklyAddedDataTable[Week No]=WeeklySummaryDataTable[[#This Row],[Week No]])*(ByCategoryWeeklyAddedDataTable[Start Date]=WeeklySummaryDataTable[[#This Row],[Start Date]]))),0)} -> 12288.3 | O25: 0 | P25: 1792 | Q25: 120 | R25: 0 | S25: Pas livraison Viangreo, remplacé par Colors Kitchen 2 proxideal, Livraison Zoetis apres midi et Namur pas livré | T25: =WeeklySummaryDataTable[[#This Row],[Total Sales]]*Settings!$C$3 -> 1473.3225 | U25: 0.1 | V25: =WeeklySummaryDataTable[[#This Row],[Sales Turnover]]/WeeklySummaryDataTable[[#This Row],['# Of Fridge]] -> 426.86817 | W25: =WeeklySummaryDataTable[[#This Row],[Sales Turnover]]-WeeklySummaryDataTable[[#This Row],[Fridge Food Cost]] -> 16220.991 | X25: =WeeklySummaryDataTable[[#This Row],[Food Margin In Euro]]/WeeklySummaryDataTable[[#This Row],[Sales Turnover]] -> 1 | Y25: =IFERROR((WeeklySummaryDataTable[[#This Row],[Catering Turnover]]-WeeklySummaryDataTable[[#This Row],[Catering Food Cost]])/WeeklySummaryDataTable[[#This Row],[Catering Turnover]],0) -> 1 | Z25: =WeeklySummaryDataTable[[#This Row],[Logistics Cost]]/WeeklySummaryDataTable[[#This Row],['# Of Fridge]] -> 47.157895 | AA25: =IFERROR(WeeklySummaryDataTable[[#This Row],[Logistics Cost]]/WeeklySummaryDataTable[[#This Row],[Sales Turnover]],0) -> 0.11047414 | AB25: =IFERROR(WeeklySummaryDataTable[[#This Row],[Unsold Items]]/WeeklySummaryDataTable[[#This Row],[Sales Turnover]],0) -> 0 | AC25: =(WeeklySummaryDataTable[[#This Row],[Sales Turnover]]+WeeklySummaryDataTable[[#This Row],[Catering Turnover]]+WeeklySummaryDataTable[[#This Row],[TGTG Turnover]])-(WeeklySummaryDataTable[[#This Row],[Fridge Food Cost]]+WeeklySummaryDataTable[[#This Row],[Catering Food Cost]]+WeeklySummaryDataTable[[#This Row],[Logistics Cost]])-WeeklySummaryDataTable[[#This Row],[POS & Software Percentage]]-WeeklySummaryDataTable[[#This Row],[RFID Tags]] -> 13385.568 | AD25: =IFERROR(WeeklySummaryDataTable[[#This Row],[Net Margin]]/(WeeklySummaryDataTable[[#This Row],[Sales Turnover]]+WeeklySummaryDataTable[[#This Row],[Catering Turnover]]+WeeklySummaryDataTable[[#This Row],[TGTG Turnover]]),0) -> 0.8038902
B26: 8 | C26: 46069 | D26: 46075 | E26: 13360.97 | F26: 6.74 | G26: 496.87 | H26: 732.18 | I26: =(WeeklySummaryDataTable[[#This Row],[Total Sales]]+WeeklySummaryDataTable[[#This Row],[Customer Credit]]-WeeklySummaryDataTable[[#This Row],[Total Refund]])/1.06 -> 13289.066 | J26: 38 | K26: 375 | L26: 55 | M26: {=IFERROR(SUM(_xlfn._xlws.FILTER(ByCategoryWeeklyDispatchDataTable[Foodcost Value],(ByCategoryWeeklyDispatchDataTable[Week No]=WeeklySummaryDataTable[[#This Row],[Week No]])*(ByCategoryWeeklyDispatchDataTable[Week Start Date]=WeeklySummaryDataTable[[#This Row],[Start Date]]))),0)} -> 0 | N26: {=IFERROR(SUM(_xlfn._xlws.FILTER(ByCategoryWeeklyAddedDataTable[Added Value],(ByCategoryWeeklyAddedDataTable[Week No]=WeeklySummaryDataTable[[#This Row],[Week No]])*(ByCategoryWeeklyAddedDataTable[Start Date]=WeeklySummaryDataTable[[#This Row],[Start Date]]))),0)} -> 10171.9 | O26: 250 | P26: 1667 | Q26: 120 | R26: 0 | S26: Congé scolaire Flandre + wallonie + Porte DPG Anvers Ouverte | T26: =WeeklySummaryDataTable[[#This Row],[Total Sales]]*Settings!$C$3 -> 1202.4873 | U26: 0.1 | V26: =WeeklySummaryDataTable[[#This Row],[Sales Turnover]]/WeeklySummaryDataTable[[#This Row],['# Of Fridge]] -> 349.71226 | W26: =WeeklySummaryDataTable[[#This Row],[Sales Turnover]]-WeeklySummaryDataTable[[#This Row],[Fridge Food Cost]] -> 13289.066 | X26: =WeeklySummaryDataTable[[#This Row],[Food Margin In Euro]]/WeeklySummaryDataTable[[#This Row],[Sales Turnover]] -> 1 | Y26: =IFERROR((WeeklySummaryDataTable[[#This Row],[Catering Turnover]]-WeeklySummaryDataTable[[#This Row],[Catering Food Cost]])/WeeklySummaryDataTable[[#This Row],[Catering Turnover]],0) -> 0.33333333 | Z26: =WeeklySummaryDataTable[[#This Row],[Logistics Cost]]/WeeklySummaryDataTable[[#This Row],['# Of Fridge]] -> 43.868421 | AA26: =IFERROR(WeeklySummaryDataTable[[#This Row],[Logistics Cost]]/WeeklySummaryDataTable[[#This Row],[Sales Turnover]],0) -> 0.12544147 | AB26: =IFERROR(WeeklySummaryDataTable[[#This Row],[Unsold Items]]/WeeklySummaryDataTable[[#This Row],[Sales Turnover]],0) -> 0 | AC26: =(WeeklySummaryDataTable[[#This Row],[Sales Turnover]]+WeeklySummaryDataTable[[#This Row],[Catering Turnover]]+WeeklySummaryDataTable[[#This Row],[TGTG Turnover]])-(WeeklySummaryDataTable[[#This Row],[Fridge Food Cost]]+WeeklySummaryDataTable[[#This Row],[Catering Food Cost]]+WeeklySummaryDataTable[[#This Row],[Logistics Cost]])-WeeklySummaryDataTable[[#This Row],[POS & Software Percentage]]-WeeklySummaryDataTable[[#This Row],[RFID Tags]] -> 10599.479 | AD26: =IFERROR(WeeklySummaryDataTable[[#This Row],[Net Margin]]/(WeeklySummaryDataTable[[#This Row],[Sales Turnover]]+WeeklySummaryDataTable[[#This Row],[Catering Turnover]]+WeeklySummaryDataTable[[#This Row],[TGTG Turnover]]),0) -> 0.77260935
B27: 9 | C27: 46076 | D27: 46082 | E27: 14369.53 | F27: 11.58 | G27: 508.47 | H27: 839.81 | I27: =(WeeklySummaryDataTable[[#This Row],[Total Sales]]+WeeklySummaryDataTable[[#This Row],[Customer Credit]]-WeeklySummaryDataTable[[#This Row],[Total Refund]])/1.06 -> 14337.509 | J27: 38 | K27: 134.6 | L27: 55 | M27: {=IFERROR(SUM(_xlfn._xlws.FILTER(ByCategoryWeeklyDispatchDataTable[Foodcost Value],ByCategoryWeeklyDispatchDataTable[Week No]=WeeklySummaryDataTable[[#This Row],[Week No]])),0)} -> 0 | N27: {=IFERROR(SUM(_xlfn._xlws.FILTER(ByCategoryWeeklyAddedDataTable[Added Value],(ByCategoryWeeklyAddedDataTable[Week No]=WeeklySummaryDataTable[[#This Row],[Week No]])*(ByCategoryWeeklyAddedDataTable[Start Date]=WeeklySummaryDataTable[[#This Row],[Start Date]]))),0)} -> 10872.12 | O27: 83.72 | P27: 1472.86 | Q27: 120 | R27: 0 | S27: Congé scolaire + Engie Namur off 3 jours + RTBF Ecran cassé | T27: =WeeklySummaryDataTable[[#This Row],[Total Sales]]*Settings!$C$3 -> 1293.2577 | U27: 0.1 | V27: =WeeklySummaryDataTable[[#This Row],[Sales Turnover]]/WeeklySummaryDataTable[[#This Row],['# Of Fridge]] -> 377.30288 | W27: =WeeklySummaryDataTable[[#This Row],[Sales Turnover]]-WeeklySummaryDataTable[[#This Row],[Fridge Food Cost]] -> 14337.509 | X27: =WeeklySummaryDataTable[[#This Row],[Food Margin In Euro]]/WeeklySummaryDataTable[[#This Row],[Sales Turnover]] -> 1 | Y27: =IFERROR((WeeklySummaryDataTable[[#This Row],[Catering Turnover]]-WeeklySummaryDataTable[[#This Row],[Catering Food Cost]])/WeeklySummaryDataTable[[#This Row],[Catering Turnover]],0) -> 0.37800892 | Z27: =WeeklySummaryDataTable[[#This Row],[Logistics Cost]]/WeeklySummaryDataTable[[#This Row],['# Of Fridge]] -> 38.759474 | AA27: =IFERROR(WeeklySummaryDataTable[[#This Row],[Logistics Cost]]/WeeklySummaryDataTable[[#This Row],[Sales Turnover]],0) -> 0.10272774 | AB27: =IFERROR(WeeklySummaryDataTable[[#This Row],[Unsold Items]]/WeeklySummaryDataTable[[#This Row],[Sales Turnover]],0) -> 0 | AC27: =(WeeklySummaryDataTable[[#This Row],[Sales Turnover]]+WeeklySummaryDataTable[[#This Row],[Catering Turnover]]+WeeklySummaryDataTable[[#This Row],[TGTG Turnover]])-(WeeklySummaryDataTable[[#This Row],[Fridge Food Cost]]+WeeklySummaryDataTable[[#This Row],[Catering Food Cost]]+WeeklySummaryDataTable[[#This Row],[Logistics Cost]])-WeeklySummaryDataTable[[#This Row],[POS & Software Percentage]]-WeeklySummaryDataTable[[#This Row],[RFID Tags]] -> 11677.172 | AD27: =IFERROR(WeeklySummaryDataTable[[#This Row],[Net Margin]]/(WeeklySummaryDataTable[[#This Row],[Sales Turnover]]+WeeklySummaryDataTable[[#This Row],[Catering Turnover]]+WeeklySummaryDataTable[[#This Row],[TGTG Turnover]]),0) -> 0.80381935
B28: 10 | C28: 46083 | D28: 46089 | E28: 15774.67 | F28: 19.05 | G28: 522.38 | H28: 845.58 | I28: =(WeeklySummaryDataTable[[#This Row],[Total Sales]]+WeeklySummaryDataTable[[#This Row],[Customer Credit]]-WeeklySummaryDataTable[[#This Row],[Total Refund]])/1.06 -> 15661.509 | J28: 38 | K28: 139.8 | L28: 55 | M28: {=IFERROR(SUM(_xlfn._xlws.FILTER(ByCategoryWeeklyDispatchDataTable[Foodcost Value],ByCategoryWeeklyDispatchDataTable[Week No]=WeeklySummaryDataTable[[#This Row],[Week No]])),0)} -> 0 | N28: {=IFERROR(SUM(_xlfn._xlws.FILTER(ByCategoryWeeklyAddedDataTable[Added Value],(ByCategoryWeeklyAddedDataTable[Week No]=WeeklySummaryDataTable[[#This Row],[Week No]])*(ByCategoryWeeklyAddedDataTable[Start Date]=WeeklySummaryDataTable[[#This Row],[Start Date]]))),0)} -> 12112.4 | O28: 87.36 | P28: 1797.68 | Q28: 120 | R28: 0 | S28: Porte DPG cassée perte produits+ Belle météo+ ramadan | T28: =WeeklySummaryDataTable[[#This Row],[Total Sales]]*Settings!$C$3 -> 1419.7203 | U28: 0.1 | V28: =WeeklySummaryDataTable[[#This Row],[Sales Turnover]]/WeeklySummaryDataTable[[#This Row],['# Of Fridge]] -> 412.14499 | W28: =WeeklySummaryDataTable[[#This Row],[Sales Turnover]]-WeeklySummaryDataTable[[#This Row],[Fridge Food Cost]] -> 15661.509 | X28: =WeeklySummaryDataTable[[#This Row],[Food Margin In Euro]]/WeeklySummaryDataTable[[#This Row],[Sales Turnover]] -> 1 | Y28: =IFERROR((WeeklySummaryDataTable[[#This Row],[Catering Turnover]]-WeeklySummaryDataTable[[#This Row],[Catering Food Cost]])/WeeklySummaryDataTable[[#This Row],[Catering Turnover]],0) -> 0.3751073 | Z28: =WeeklySummaryDataTable[[#This Row],[Logistics Cost]]/WeeklySummaryDataTable[[#This Row],['# Of Fridge]] -> 47.307368 | AA28: =IFERROR(WeeklySummaryDataTable[[#This Row],[Logistics Cost]]/WeeklySummaryDataTable[[#This Row],[Sales Turnover]],0) -> 0.11478332 | AB28: =IFERROR(WeeklySummaryDataTable[[#This Row],[Unsold Items]]/WeeklySummaryDataTable[[#This Row],[Sales Turnover]],0) -> 0 | AC28: =(WeeklySummaryDataTable[[#This Row],[Sales Turnover]]+WeeklySummaryDataTable[[#This Row],[Catering Turnover]]+WeeklySummaryDataTable[[#This Row],[TGTG Turnover]])-(WeeklySummaryDataTable[[#This Row],[Fridge Food Cost]]+WeeklySummaryDataTable[[#This Row],[Catering Food Cost]]+WeeklySummaryDataTable[[#This Row],[Logistics Cost]])-WeeklySummaryDataTable[[#This Row],[POS & Software Percentage]]-WeeklySummaryDataTable[[#This Row],[RFID Tags]] -> 12551.449 | AD28: =IFERROR(WeeklySummaryDataTable[[#This Row],[Net Margin]]/(WeeklySummaryDataTable[[#This Row],[Sales Turnover]]+WeeklySummaryDataTable[[#This Row],[Catering Turnover]]+WeeklySummaryDataTable[[#This Row],[TGTG Turnover]]),0) -> 0.79157443
B29: 11 | C29: 46090 | D29: 46096 | E29: 15379 | F29: 1.5 | G29: 601.78 | H29: 740.67 | I29: =(WeeklySummaryDataTable[[#This Row],[Total Sales]]+WeeklySummaryDataTable[[#This Row],[Customer Credit]]-WeeklySummaryDataTable[[#This Row],[Total Refund]])/1.06 -> 15205.821 | J29: 38 | K29: 560 | L29: 55 | M29: {=IFERROR(SUM(_xlfn._xlws.FILTER(ByCategoryWeeklyDispatchDataTable[Foodcost Value],ByCategoryWeeklyDispatchDataTable[Week No]=WeeklySummaryDataTable[[#This Row],[Week No]])),0)} -> 0 | N29: {=IFERROR(SUM(_xlfn._xlws.FILTER(ByCategoryWeeklyAddedDataTable[Added Value],(ByCategoryWeeklyAddedDataTable[Week No]=WeeklySummaryDataTable[[#This Row],[Week No]])*(ByCategoryWeeklyAddedDataTable[Start Date]=WeeklySummaryDataTable[[#This Row],[Start Date]]))),0)} -> 11722.1 | O29: 374 | P29: 1656.38 | Q29: 120 | R29: 0 | S29: Grêve 4 jours transport + centre Bruxelles | T29: =WeeklySummaryDataTable[[#This Row],[Total Sales]]*Settings!$C$3 -> 1384.11 | U29: 0.1 | V29: =WeeklySummaryDataTable[[#This Row],[Sales Turnover]]/WeeklySummaryDataTable[[#This Row],['# Of Fridge]] -> 400.15318 | W29: =WeeklySummaryDataTable[[#This Row],[Sales Turnover]]-WeeklySummaryDataTable[[#This Row],[Fridge Food Cost]] -> 15205.821 | X29: =WeeklySummaryDataTable[[#This Row],[Food Margin In Euro]]/WeeklySummaryDataTable[[#This Row],[Sales Turnover]] -> 1 | Y29: =IFERROR((WeeklySummaryDataTable[[#This Row],[Catering Turnover]]-WeeklySummaryDataTable[[#This Row],[Catering Food Cost]])/WeeklySummaryDataTable[[#This Row],[Catering Turnover]],0) -> 0.33214286 | Z29: =WeeklySummaryDataTable[[#This Row],[Logistics Cost]]/WeeklySummaryDataTable[[#This Row],['# Of Fridge]] -> 43.588947 | AA29: =IFERROR(WeeklySummaryDataTable[[#This Row],[Logistics Cost]]/WeeklySummaryDataTable[[#This Row],[Sales Turnover]],0) -> 0.10893065 | AB29: =IFERROR(WeeklySummaryDataTable[[#This Row],[Unsold Items]]/WeeklySummaryDataTable[[#This Row],[Sales Turnover]],0) -> 0 | AC29: =(WeeklySummaryDataTable[[#This Row],[Sales Turnover]]+WeeklySummaryDataTable[[#This Row],[Catering Turnover]]+WeeklySummaryDataTable[[#This Row],[TGTG Turnover]])-(WeeklySummaryDataTable[[#This Row],[Fridge Food Cost]]+WeeklySummaryDataTable[[#This Row],[Catering Food Cost]]+WeeklySummaryDataTable[[#This Row],[Logistics Cost]])-WeeklySummaryDataTable[[#This Row],[POS & Software Percentage]]-WeeklySummaryDataTable[[#This Row],[RFID Tags]] -> 12406.231 | AD29: =IFERROR(WeeklySummaryDataTable[[#This Row],[Net Margin]]/(WeeklySummaryDataTable[[#This Row],[Sales Turnover]]+WeeklySummaryDataTable[[#This Row],[Catering Turnover]]+WeeklySummaryDataTable[[#This Row],[TGTG Turnover]]),0) -> 0.78417112
B30: 12 | C30: 46097 | D30: 46103 | E30: 16374.2 | F30: 6.49 | G30: 405.74 | H30: 822.32 | I30: =(WeeklySummaryDataTable[[#This Row],[Total Sales]]+WeeklySummaryDataTable[[#This Row],[Customer Credit]]-WeeklySummaryDataTable[[#This Row],[Total Refund]])/1.06 -> 16217.009 | J30: 38 | K30: 1985 | L30: 55 | M30: {=IFERROR(SUM(_xlfn._xlws.FILTER(ByCategoryWeeklyDispatchDataTable[Foodcost Value],ByCategoryWeeklyDispatchDataTable[Week No]=WeeklySummaryDataTable[[#This Row],[Week No]])),0)} -> 0 | N30: {=IFERROR(SUM(_xlfn._xlws.FILTER(ByCategoryWeeklyAddedDataTable[Added Value],(ByCategoryWeeklyAddedDataTable[Week No]=WeeklySummaryDataTable[[#This Row],[Week No]])*(ByCategoryWeeklyAddedDataTable[Start Date]=WeeklySummaryDataTable[[#This Row],[Start Date]]))),0)} -> 12435.21 | O30: 1343 | P30: 1885.77 | Q30: 120 | R30: 0 | S30: Livraison Patisserie Ramadan dans toute la Belgique | T30: =WeeklySummaryDataTable[[#This Row],[Total Sales]]*Settings!$C$3 -> 1473.678 | U30: 0.1 | V30: =WeeklySummaryDataTable[[#This Row],[Sales Turnover]]/WeeklySummaryDataTable[[#This Row],['# Of Fridge]] -> 426.76341 | W30: =WeeklySummaryDataTable[[#This Row],[Sales Turnover]]-WeeklySummaryDataTable[[#This Row],[Fridge Food Cost]] -> 16217.009 | X30: =WeeklySummaryDataTable[[#This Row],[Food Margin In Euro]]/WeeklySummaryDataTable[[#This Row],[Sales Turnover]] -> 1 | Y30: =IFERROR((WeeklySummaryDataTable[[#This Row],[Catering Turnover]]-WeeklySummaryDataTable[[#This Row],[Catering Food Cost]])/WeeklySummaryDataTable[[#This Row],[Catering Turnover]],0) -> 0.32342569 | Z30: =WeeklySummaryDataTable[[#This Row],[Logistics Cost]]/WeeklySummaryDataTable[[#This Row],['# Of Fridge]] -> 49.625526 | AA30: =IFERROR(WeeklySummaryDataTable[[#This Row],[Logistics Cost]]/WeeklySummaryDataTable[[#This Row],[Sales Turnover]],0) -> 0.11628346 | AB30: =IFERROR(WeeklySummaryDataTable[[#This Row],[Unsold Items]]/WeeklySummaryDataTable[[#This Row],[Sales Turnover]],0) -> 0 | AC30: =(WeeklySummaryDataTable[[#This Row],[Sales Turnover]]+WeeklySummaryDataTable[[#This Row],[Catering Turnover]]+WeeklySummaryDataTable[[#This Row],[TGTG Turnover]])-(WeeklySummaryDataTable[[#This Row],[Fridge Food Cost]]+WeeklySummaryDataTable[[#This Row],[Catering Food Cost]]+WeeklySummaryDataTable[[#This Row],[Logistics Cost]])-WeeklySummaryDataTable[[#This Row],[POS & Software Percentage]]-WeeklySummaryDataTable[[#This Row],[RFID Tags]] -> 13554.461 | AD30: =IFERROR(WeeklySummaryDataTable[[#This Row],[Net Margin]]/(WeeklySummaryDataTable[[#This Row],[Sales Turnover]]+WeeklySummaryDataTable[[#This Row],[Catering Turnover]]+WeeklySummaryDataTable[[#This Row],[TGTG Turnover]]),0) -> 0.74242507
B31: 13 | C31: 46104 | D31: 46110 | E31: 17002.59 | F31: 21.65 | G31: 434.49 | H31: 872.05 | I31: =(WeeklySummaryDataTable[[#This Row],[Total Sales]]+WeeklySummaryDataTable[[#This Row],[Customer Credit]]-WeeklySummaryDataTable[[#This Row],[Total Refund]])/1.06 -> 16842.443 | J31: 38 | K31: 378 | L31: 55 | M31: {=IFERROR(SUM(_xlfn._xlws.FILTER(ByCategoryWeeklyDispatchDataTable[Foodcost Value],ByCategoryWeeklyDispatchDataTable[Week No]=WeeklySummaryDataTable[[#This Row],[Week No]])),0)} -> 2368.41 | N31: {=IFERROR(SUM(_xlfn._xlws.FILTER(ByCategoryWeeklyAddedDataTable[Added Value],(ByCategoryWeeklyAddedDataTable[Week No]=WeeklySummaryDataTable[[#This Row],[Week No]])*(ByCategoryWeeklyAddedDataTable[Start Date]=WeeklySummaryDataTable[[#This Row],[Start Date]]))),0)} -> 11922.83 | O31: 237 | P31: 1725.31 | Q31: 120 | R31: 0 | T31: =WeeklySummaryDataTable[[#This Row],[Total Sales]]*Settings!$C$3 -> 1530.2331 | U31: 0.1 | V31: =WeeklySummaryDataTable[[#This Row],[Sales Turnover]]/WeeklySummaryDataTable[[#This Row],['# Of Fridge]] -> 443.22219 | W31: =WeeklySummaryDataTable[[#This Row],[Sales Turnover]]-WeeklySummaryDataTable[[#This Row],[Fridge Food Cost]] -> 14474.033 | X31: =WeeklySummaryDataTable[[#This Row],[Food Margin In Euro]]/WeeklySummaryDataTable[[#This Row],[Sales Turnover]] -> 0.85937848 | Y31: =IFERROR((WeeklySummaryDataTable[[#This Row],[Catering Turnover]]-WeeklySummaryDataTable[[#This Row],[Catering Food Cost]])/WeeklySummaryDataTable[[#This Row],[Catering Turnover]],0) -> 0.37301587 | Z31: =WeeklySummaryDataTable[[#This Row],[Logistics Cost]]/WeeklySummaryDataTable[[#This Row],['# Of Fridge]] -> 45.402895 | AA31: =IFERROR(WeeklySummaryDataTable[[#This Row],[Logistics Cost]]/WeeklySummaryDataTable[[#This Row],[Sales Turnover]],0) -> 0.10243822 | AB31: =IFERROR(WeeklySummaryDataTable[[#This Row],[Unsold Items]]/WeeklySummaryDataTable[[#This Row],[Sales Turnover]],0) -> 0 | AC31: =(WeeklySummaryDataTable[[#This Row],[Sales Turnover]]+WeeklySummaryDataTable[[#This Row],[Catering Turnover]]+WeeklySummaryDataTable[[#This Row],[TGTG Turnover]])-(WeeklySummaryDataTable[[#This Row],[Fridge Food Cost]]+WeeklySummaryDataTable[[#This Row],[Catering Food Cost]]+WeeklySummaryDataTable[[#This Row],[Logistics Cost]])-WeeklySummaryDataTable[[#This Row],[POS & Software Percentage]]-WeeklySummaryDataTable[[#This Row],[RFID Tags]] -> 11414.39 | AD31: =IFERROR(WeeklySummaryDataTable[[#This Row],[Net Margin]]/(WeeklySummaryDataTable[[#This Row],[Sales Turnover]]+WeeklySummaryDataTable[[#This Row],[Catering Turnover]]+WeeklySummaryDataTable[[#This Row],[TGTG Turnover]]),0) -> 0.66072922
B32: 14 | C32: 46111 | D32: 46117 | E32: 17259.55 | F32: 7.89 | G32: 276.29 | H32: 924.87 | I32: =(WeeklySummaryDataTable[[#This Row],[Total Sales]]+WeeklySummaryDataTable[[#This Row],[Customer Credit]]-WeeklySummaryDataTable[[#This Row],[Total Refund]])/1.06 -> 17147.67 | J32: 39 | K32: 0 | L32: 55 | M32: {=IFERROR(SUM(_xlfn._xlws.FILTER(ByCategoryWeeklyDispatchDataTable[Foodcost Value],ByCategoryWeeklyDispatchDataTable[Week No]=WeeklySummaryDataTable[[#This Row],[Week No]])),0)} -> 11485.49 | N32: {=IFERROR(SUM(_xlfn._xlws.FILTER(ByCategoryWeeklyAddedDataTable[Added Value],(ByCategoryWeeklyAddedDataTable[Week No]=WeeklySummaryDataTable[[#This Row],[Week No]])*(ByCategoryWeeklyAddedDataTable[Start Date]=WeeklySummaryDataTable[[#This Row],[Start Date]]))),0)} -> 12897.74 | O32: 0 | P32: 1725.31 | Q32: 120 | R32: 0 | S32: Formation 3 students et + de produit pour couvrir le lundi férié | T32: =WeeklySummaryDataTable[[#This Row],[Total Sales]]*Settings!$C$3 -> 1553.3595 | U32: 0.1 | V32: =WeeklySummaryDataTable[[#This Row],[Sales Turnover]]/WeeklySummaryDataTable[[#This Row],['# Of Fridge]] -> 439.68384 | W32: =WeeklySummaryDataTable[[#This Row],[Sales Turnover]]-WeeklySummaryDataTable[[#This Row],[Fridge Food Cost]] -> 5662.1798 | X32: =WeeklySummaryDataTable[[#This Row],[Food Margin In Euro]]/WeeklySummaryDataTable[[#This Row],[Sales Turnover]] -> 0.33020112 | Y32: =IFERROR((WeeklySummaryDataTable[[#This Row],[Catering Turnover]]-WeeklySummaryDataTable[[#This Row],[Catering Food Cost]])/WeeklySummaryDataTable[[#This Row],[Catering Turnover]],0) -> 0 | Z32: =WeeklySummaryDataTable[[#This Row],[Logistics Cost]]/WeeklySummaryDataTable[[#This Row],['# Of Fridge]] -> 44.238718 | AA32: =IFERROR(WeeklySummaryDataTable[[#This Row],[Logistics Cost]]/WeeklySummaryDataTable[[#This Row],[Sales Turnover]],0) -> 0.10061484 | AB32: =IFERROR(WeeklySummaryDataTable[[#This Row],[Unsold Items]]/WeeklySummaryDataTable[[#This Row],[Sales Turnover]],0) -> 0 | AC32: =(WeeklySummaryDataTable[[#This Row],[Sales Turnover]]+WeeklySummaryDataTable[[#This Row],[Catering Turnover]]+WeeklySummaryDataTable[[#This Row],[TGTG Turnover]])-(WeeklySummaryDataTable[[#This Row],[Fridge Food Cost]]+WeeklySummaryDataTable[[#This Row],[Catering Food Cost]]+WeeklySummaryDataTable[[#This Row],[Logistics Cost]])-WeeklySummaryDataTable[[#This Row],[POS & Software Percentage]]-WeeklySummaryDataTable[[#This Row],[RFID Tags]] -> 2438.4103 | AD32: =IFERROR(WeeklySummaryDataTable[[#This Row],[Net Margin]]/(WeeklySummaryDataTable[[#This Row],[Sales Turnover]]+WeeklySummaryDataTable[[#This Row],[Catering Turnover]]+WeeklySummaryDataTable[[#This Row],[TGTG Turnover]]),0) -> 0.14174604
B33: 15 | C33: 46118 | D33: 46124 | E33: 12500.89 | F33: 0 | G33: 405.54 | H33: 706.22 | I33: =(WeeklySummaryDataTable[[#This Row],[Total Sales]]+WeeklySummaryDataTable[[#This Row],[Customer Credit]]-WeeklySummaryDataTable[[#This Row],[Total Refund]])/1.06 -> 12459.538 | J33: 39 | K33: 0 | L33: 55 | M33: {=IFERROR(SUM(_xlfn._xlws.FILTER(ByCategoryWeeklyDispatchDataTable[Foodcost Value],ByCategoryWeeklyDispatchDataTable[Week No]=WeeklySummaryDataTable[[#This Row],[Week No]])),0)} -> 8855.77 | N33: {=IFERROR(SUM(_xlfn._xlws.FILTER(ByCategoryWeeklyAddedDataTable[Added Value],(ByCategoryWeeklyAddedDataTable[Week No]=WeeklySummaryDataTable[[#This Row],[Week No]])*(ByCategoryWeeklyAddedDataTable[Start Date]=WeeklySummaryDataTable[[#This Row],[Start Date]]))),0)} -> 9322.84 | O33: 0 | P33: 1654.36 | Q33: 120 | R33: 0 | S33: Congé Flandre + semaine 4 jours +Proxideal | T33: =WeeklySummaryDataTable[[#This Row],[Total Sales]]*Settings!$C$3 -> 1125.0801 | U33: 0.1 | V33: =WeeklySummaryDataTable[[#This Row],[Sales Turnover]]/WeeklySummaryDataTable[[#This Row],['# Of Fridge]] -> 319.47533 | W33: =WeeklySummaryDataTable[[#This Row],[Sales Turnover]]-WeeklySummaryDataTable[[#This Row],[Fridge Food Cost]] -> 3603.7677 | X33: =WeeklySummaryDataTable[[#This Row],[Food Margin In Euro]]/WeeklySummaryDataTable[[#This Row],[Sales Turnover]] -> 0.28923768 | Y33: =IFERROR((WeeklySummaryDataTable[[#This Row],[Catering Turnover]]-WeeklySummaryDataTable[[#This Row],[Catering Food Cost]])/WeeklySummaryDataTable[[#This Row],[Catering Turnover]],0) -> 0 | Z33: =WeeklySummaryDataTable[[#This Row],[Logistics Cost]]/WeeklySummaryDataTable[[#This Row],['# Of Fridge]] -> 42.419487 | AA33: =IFERROR(WeeklySummaryDataTable[[#This Row],[Logistics Cost]]/WeeklySummaryDataTable[[#This Row],[Sales Turnover]],0) -> 0.1327786 | AB33: =IFERROR(WeeklySummaryDataTable[[#This Row],[Unsold Items]]/WeeklySummaryDataTable[[#This Row],[Sales Turnover]],0) -> 0 | AC33: =(WeeklySummaryDataTable[[#This Row],[Sales Turnover]]+WeeklySummaryDataTable[[#This Row],[Catering Turnover]]+WeeklySummaryDataTable[[#This Row],[TGTG Turnover]])-(WeeklySummaryDataTable[[#This Row],[Fridge Food Cost]]+WeeklySummaryDataTable[[#This Row],[Catering Food Cost]]+WeeklySummaryDataTable[[#This Row],[Logistics Cost]])-WeeklySummaryDataTable[[#This Row],[POS & Software Percentage]]-WeeklySummaryDataTable[[#This Row],[RFID Tags]] -> 879.22764 | AD33: =IFERROR(WeeklySummaryDataTable[[#This Row],[Net Margin]]/(WeeklySummaryDataTable[[#This Row],[Sales Turnover]]+WeeklySummaryDataTable[[#This Row],[Catering Turnover]]+WeeklySummaryDataTable[[#This Row],[TGTG Turnover]]),0) -> 0.070256501
B34: 16 | C34: 46125 | D34: 46131 | E34: 14531.07 | F34: 18.59 | G34: 359.05 | H34: 771.95 | I34: =(WeeklySummaryDataTable[[#This Row],[Total Sales]]+WeeklySummaryDataTable[[#This Row],[Customer Credit]]-WeeklySummaryDataTable[[#This Row],[Total Refund]])/1.06 -> 14419.274 | J34: 40 | K34: 0 | L34: 55 | M34: {=IFERROR(SUM(_xlfn._xlws.FILTER(ByCategoryWeeklyDispatchDataTable[Foodcost Value],ByCategoryWeeklyDispatchDataTable[Week No]=WeeklySummaryDataTable[[#This Row],[Week No]])),0)} -> 10317.58 | N34: {=IFERROR(SUM(_xlfn._xlws.FILTER(ByCategoryWeeklyAddedDataTable[Added Value],(ByCategoryWeeklyAddedDataTable[Week No]=WeeklySummaryDataTable[[#This Row],[Week No]])*(ByCategoryWeeklyAddedDataTable[Start Date]=WeeklySummaryDataTable[[#This Row],[Start Date]]))),0)} -> 11353.2 | O34: 0 | P34: 1749.17 | Q34: 120 | R34: 0 | S34: Congé Flandre + Lancement Allnex Freezer + deplacement FRigo PWC A par Selen | T34: =WeeklySummaryDataTable[[#This Row],[Total Sales]]*Settings!$C$3 -> 1307.7963 | U34: 0.1 | V34: =WeeklySummaryDataTable[[#This Row],[Sales Turnover]]/WeeklySummaryDataTable[[#This Row],['# Of Fridge]] -> 360.48184 | W34: =WeeklySummaryDataTable[[#This Row],[Sales Turnover]]-WeeklySummaryDataTable[[#This Row],[Fridge Food Cost]] -> 4101.6936 | X34: =WeeklySummaryDataTable[[#This Row],[Food Margin In Euro]]/WeeklySummaryDataTable[[#This Row],[Sales Turnover]] -> 0.2844591 | Y34: =IFERROR((WeeklySummaryDataTable[[#This Row],[Catering Turnover]]-WeeklySummaryDataTable[[#This Row],[Catering Food Cost]])/WeeklySummaryDataTable[[#This Row],[Catering Turnover]],0) -> 0 | Z34: =WeeklySummaryDataTable[[#This Row],[Logistics Cost]]/WeeklySummaryDataTable[[#This Row],['# Of Fridge]] -> 43.72925 | AA34: =IFERROR(WeeklySummaryDataTable[[#This Row],[Logistics Cost]]/WeeklySummaryDataTable[[#This Row],[Sales Turnover]],0) -> 0.12130778 | AB34: =IFERROR(WeeklySummaryDataTable[[#This Row],[Unsold Items]]/WeeklySummaryDataTable[[#This Row],[Sales Turnover]],0) -> 0 | AC34: =(WeeklySummaryDataTable[[#This Row],[Sales Turnover]]+WeeklySummaryDataTable[[#This Row],[Catering Turnover]]+WeeklySummaryDataTable[[#This Row],[TGTG Turnover]])-(WeeklySummaryDataTable[[#This Row],[Fridge Food Cost]]+WeeklySummaryDataTable[[#This Row],[Catering Food Cost]]+WeeklySummaryDataTable[[#This Row],[Logistics Cost]])-WeeklySummaryDataTable[[#This Row],[POS & Software Percentage]]-WeeklySummaryDataTable[[#This Row],[RFID Tags]] -> 1099.6273 | AD34: =IFERROR(WeeklySummaryDataTable[[#This Row],[Net Margin]]/(WeeklySummaryDataTable[[#This Row],[Sales Turnover]]+WeeklySummaryDataTable[[#This Row],[Catering Turnover]]+WeeklySummaryDataTable[[#This Row],[TGTG Turnover]]),0) -> 0.075971155
B35: 17 | C35: 46132 | D35: 46138 | E35: 16963.13 | F35: 12.77 | G35: 502.4 | H35: 936.14 | I35: =(WeeklySummaryDataTable[[#This Row],[Total Sales]]+WeeklySummaryDataTable[[#This Row],[Customer Credit]]-WeeklySummaryDataTable[[#This Row],[Total Refund]])/1.06 -> 16874.057 | J35: 40 | K35: 0 | L35: 55 | M35: {=IFERROR(SUM(_xlfn._xlws.FILTER(ByCategoryWeeklyDispatchDataTable[Foodcost Value],ByCategoryWeeklyDispatchDataTable[Week No]=WeeklySummaryDataTable[[#This Row],[Week No]])),0)} -> 12316.47 | N35: {=IFERROR(SUM(_xlfn._xlws.FILTER(ByCategoryWeeklyAddedDataTable[Added Value],(ByCategoryWeeklyAddedDataTable[Week No]=WeeklySummaryDataTable[[#This Row],[Week No]])*(ByCategoryWeeklyAddedDataTable[Start Date]=WeeklySummaryDataTable[[#This Row],[Start Date]]))),0)} -> 12523.12 | O35: 0 | P35: 2094 | Q35: 120 | R35: 0 | T35: =WeeklySummaryDataTable[[#This Row],[Total Sales]]*Settings!$C$3 -> 1526.6817 | U35: 0.1 | V35: =WeeklySummaryDataTable[[#This Row],[Sales Turnover]]/WeeklySummaryDataTable[[#This Row],['# Of Fridge]] -> 421.85142 | W35: =WeeklySummaryDataTable[[#This Row],[Sales Turnover]]-WeeklySummaryDataTable[[#This Row],[Fridge Food Cost]] -> 4557.5866 | X35: =WeeklySummaryDataTable[[#This Row],[Food Margin In Euro]]/WeeklySummaryDataTable[[#This Row],[Sales Turnover]] -> 0.27009431 | Y35: =IFERROR((WeeklySummaryDataTable[[#This Row],[Catering Turnover]]-WeeklySummaryDataTable[[#This Row],[Catering Food Cost]])/WeeklySummaryDataTable[[#This Row],[Catering Turnover]],0) -> 0 | Z35: =WeeklySummaryDataTable[[#This Row],[Logistics Cost]]/WeeklySummaryDataTable[[#This Row],['# Of Fridge]] -> 52.35 | AA35: =IFERROR(WeeklySummaryDataTable[[#This Row],[Logistics Cost]]/WeeklySummaryDataTable[[#This Row],[Sales Turnover]],0) -> 0.12409583 | AB35: =IFERROR(WeeklySummaryDataTable[[#This Row],[Unsold Items]]/WeeklySummaryDataTable[[#This Row],[Sales Turnover]],0) -> 0 | AC35: =(WeeklySummaryDataTable[[#This Row],[Sales Turnover]]+WeeklySummaryDataTable[[#This Row],[Catering Turnover]]+WeeklySummaryDataTable[[#This Row],[TGTG Turnover]])-(WeeklySummaryDataTable[[#This Row],[Fridge Food Cost]]+WeeklySummaryDataTable[[#This Row],[Catering Food Cost]]+WeeklySummaryDataTable[[#This Row],[Logistics Cost]])-WeeklySummaryDataTable[[#This Row],[POS & Software Percentage]]-WeeklySummaryDataTable[[#This Row],[RFID Tags]] -> 991.8049 | AD35: =IFERROR(WeeklySummaryDataTable[[#This Row],[Net Margin]]/(WeeklySummaryDataTable[[#This Row],[Sales Turnover]]+WeeklySummaryDataTable[[#This Row],[Catering Turnover]]+WeeklySummaryDataTable[[#This Row],[TGTG Turnover]]),0) -> 0.058585952
B36: 18 | C36: 46139 | D36: 46145 | E36: 13501.4 | F36: 6.8 | G36: 60.6 | H36: 835.35 | I36: =(WeeklySummaryDataTable[[#This Row],[Total Sales]]+WeeklySummaryDataTable[[#This Row],[Customer Credit]]-WeeklySummaryDataTable[[#This Row],[Total Refund]])/1.06 -> 13518.821 | J36: 39 | K36: 661 | L36: 55 | M36: {=IFERROR(SUM(_xlfn._xlws.FILTER(ByCategoryWeeklyDispatchDataTable[Foodcost Value],ByCategoryWeeklyDispatchDataTable[Week No]=WeeklySummaryDataTable[[#This Row],[Week No]])),0)} -> 10748.12 | N36: {=IFERROR(SUM(_xlfn._xlws.FILTER(ByCategoryWeeklyAddedDataTable[Added Value],(ByCategoryWeeklyAddedDataTable[Week No]=WeeklySummaryDataTable[[#This Row],[Week No]])*(ByCategoryWeeklyAddedDataTable[Start Date]=WeeklySummaryDataTable[[#This Row],[Start Date]]))),0)} -> 10551.3 | O36: 460 | P36: 1709 | Q36: 120 | R36: 0 | S36: Semaine de pacques francophone, semaine de 4 jours, Sandra en vacances:surstock de snacks and drinks => outil mal calibré dû aux codes EAN) | T36: =WeeklySummaryDataTable[[#This Row],[Total Sales]]*Settings!$C$3 -> 1215.126 | U36: 0.1 | V36: =WeeklySummaryDataTable[[#This Row],[Sales Turnover]]/WeeklySummaryDataTable[[#This Row],['# Of Fridge]] -> 346.63643 | W36: =WeeklySummaryDataTable[[#This Row],[Sales Turnover]]-WeeklySummaryDataTable[[#This Row],[Fridge Food Cost]] -> 2770.7008 | X36: =WeeklySummaryDataTable[[#This Row],[Food Margin In Euro]]/WeeklySummaryDataTable[[#This Row],[Sales Turnover]] -> 0.20495136 | Y36: =IFERROR((WeeklySummaryDataTable[[#This Row],[Catering Turnover]]-WeeklySummaryDataTable[[#This Row],[Catering Food Cost]])/WeeklySummaryDataTable[[#This Row],[Catering Turnover]],0) -> 0.30408472 | Z36: =WeeklySummaryDataTable[[#This Row],[Logistics Cost]]/WeeklySummaryDataTable[[#This Row],['# Of Fridge]] -> 43.820513 | AA36: =IFERROR(WeeklySummaryDataTable[[#This Row],[Logistics Cost]]/WeeklySummaryDataTable[[#This Row],[Sales Turnover]],0) -> 0.12641635 | AB36: =IFERROR(WeeklySummaryDataTable[[#This Row],[Unsold Items]]/WeeklySummaryDataTable[[#This Row],[Sales Turnover]],0) -> 0 | AC36: =(WeeklySummaryDataTable[[#This Row],[Sales Turnover]]+WeeklySummaryDataTable[[#This Row],[Catering Turnover]]+WeeklySummaryDataTable[[#This Row],[TGTG Turnover]])-(WeeklySummaryDataTable[[#This Row],[Fridge Food Cost]]+WeeklySummaryDataTable[[#This Row],[Catering Food Cost]]+WeeklySummaryDataTable[[#This Row],[Logistics Cost]])-WeeklySummaryDataTable[[#This Row],[POS & Software Percentage]]-WeeklySummaryDataTable[[#This Row],[RFID Tags]] -> 102.47475 | AD36: =IFERROR(WeeklySummaryDataTable[[#This Row],[Net Margin]]/(WeeklySummaryDataTable[[#This Row],[Sales Turnover]]+WeeklySummaryDataTable[[#This Row],[Catering Turnover]]+WeeklySummaryDataTable[[#This Row],[TGTG Turnover]]),0) -> 0.0071988792
B37: 20 | C37: 46153 | D37: 46159 | E37: 12362.97 | F37: 6.3 | G37: 298.07 | H37: 785.24 | I37: =(WeeklySummaryDataTable[[#This Row],[Total Sales]]+WeeklySummaryDataTable[[#This Row],[Customer Credit]]-WeeklySummaryDataTable[[#This Row],[Total Refund]])/1.06 -> 12398.028 | J37: 40 | K37: 0 | L37: 55 | M37: {=IFERROR(SUM(_xlfn._xlws.FILTER(ByCategoryWeeklyDispatchDataTable[Foodcost Value],ByCategoryWeeklyDispatchDataTable[Week No]=WeeklySummaryDataTable[[#This Row],[Week No]])),0)} -> 10965.36 | N37: {=IFERROR(SUM(_xlfn._xlws.FILTER(ByCategoryWeeklyAddedDataTable[Added Value],(ByCategoryWeeklyAddedDataTable[Week No]=WeeklySummaryDataTable[[#This Row],[Week No]])*(ByCategoryWeeklyAddedDataTable[Start Date]=WeeklySummaryDataTable[[#This Row],[Start Date]]))),0)} -> 10473.69 | O37: 0 | P37: 1514.2 | Q37: 120 | R37: 0 | S37: DPG Vilvoorde lercteur RFID out(perdu toute la livraison), RTBF changement bâtiment donc nouvelle conso, grêve nationale mardi | T37: =WeeklySummaryDataTable[[#This Row],[Total Sales]]*Settings!$C$3 -> 1112.6673 | U37: 0.1 | V37: =WeeklySummaryDataTable[[#This Row],[Sales Turnover]]/WeeklySummaryDataTable[[#This Row],['# Of Fridge]] -> 309.95071 | W37: =WeeklySummaryDataTable[[#This Row],[Sales Turnover]]-WeeklySummaryDataTable[[#This Row],[Fridge Food Cost]] -> 1432.6683 | X37: =WeeklySummaryDataTable[[#This Row],[Food Margin In Euro]]/WeeklySummaryDataTable[[#This Row],[Sales Turnover]] -> 0.11555614 | Y37: =IFERROR((WeeklySummaryDataTable[[#This Row],[Catering Turnover]]-WeeklySummaryDataTable[[#This Row],[Catering Food Cost]])/WeeklySummaryDataTable[[#This Row],[Catering Turnover]],0) -> 0 | Z37: =WeeklySummaryDataTable[[#This Row],[Logistics Cost]]/WeeklySummaryDataTable[[#This Row],['# Of Fridge]] -> 37.855 | AA37: =IFERROR(WeeklySummaryDataTable[[#This Row],[Logistics Cost]]/WeeklySummaryDataTable[[#This Row],[Sales Turnover]],0) -> 0.12213232 | AB37: =IFERROR(WeeklySummaryDataTable[[#This Row],[Unsold Items]]/WeeklySummaryDataTable[[#This Row],[Sales Turnover]],0) -> 0 | AC37: =(WeeklySummaryDataTable[[#This Row],[Sales Turnover]]+WeeklySummaryDataTable[[#This Row],[Catering Turnover]]+WeeklySummaryDataTable[[#This Row],[TGTG Turnover]])-(WeeklySummaryDataTable[[#This Row],[Fridge Food Cost]]+WeeklySummaryDataTable[[#This Row],[Catering Food Cost]]+WeeklySummaryDataTable[[#This Row],[Logistics Cost]])-WeeklySummaryDataTable[[#This Row],[POS & Software Percentage]]-WeeklySummaryDataTable[[#This Row],[RFID Tags]] -> -1139.299 | AD37: =IFERROR(WeeklySummaryDataTable[[#This Row],[Net Margin]]/(WeeklySummaryDataTable[[#This Row],[Sales Turnover]]+WeeklySummaryDataTable[[#This Row],[Catering Turnover]]+WeeklySummaryDataTable[[#This Row],[TGTG Turnover]]),0) -> -0.091487706
B38: 19 | C38: 46146 | D38: 46152 | E38: 14806 | F38: 29.1 | G38: 435.75 | H38: 835.85 | I38: =(WeeklySummaryDataTable[[#This Row],[Total Sales]]+WeeklySummaryDataTable[[#This Row],[Customer Credit]]-WeeklySummaryDataTable[[#This Row],[Total Refund]])/1.06 -> 14729.009 | J38: 40 | K38: 0 | L38: 55 | M38: {=IFERROR(SUM(_xlfn._xlws.FILTER(ByCategoryWeeklyDispatchDataTable[Foodcost Value],ByCategoryWeeklyDispatchDataTable[Week No]=WeeklySummaryDataTable[[#This Row],[Week No]])),0)} -> 10794.08 | N38: {=IFERROR(SUM(_xlfn._xlws.FILTER(ByCategoryWeeklyAddedDataTable[Added Value],(ByCategoryWeeklyAddedDataTable[Week No]=WeeklySummaryDataTable[[#This Row],[Week No]])*(ByCategoryWeeklyAddedDataTable[Start Date]=WeeklySummaryDataTable[[#This Row],[Start Date]]))),0)} -> 11043.59 | O38: 0 | P38: 1728.72 | Q38: 120 | R38: 0 | S38: DPG Vilvoorde lercteur RFID out(perdu toute la livraison), RTBF changement bâtiment donc nouvelle conso, grêve nationale mardi | T38: =WeeklySummaryDataTable[[#This Row],[Total Sales]]*Settings!$C$3 -> 1332.54 | U38: 0.1 | V38: =WeeklySummaryDataTable[[#This Row],[Sales Turnover]]/WeeklySummaryDataTable[[#This Row],['# Of Fridge]] -> 368.22524 | W38: =WeeklySummaryDataTable[[#This Row],[Sales Turnover]]-WeeklySummaryDataTable[[#This Row],[Fridge Food Cost]] -> 3934.9294 | X38: =WeeklySummaryDataTable[[#This Row],[Food Margin In Euro]]/WeeklySummaryDataTable[[#This Row],[Sales Turnover]] -> 0.26715506 | Y38: =IFERROR((WeeklySummaryDataTable[[#This Row],[Catering Turnover]]-WeeklySummaryDataTable[[#This Row],[Catering Food Cost]])/WeeklySummaryDataTable[[#This Row],[Catering Turnover]],0) -> 0 | Z38: =WeeklySummaryDataTable[[#This Row],[Logistics Cost]]/WeeklySummaryDataTable[[#This Row],['# Of Fridge]] -> 43.218 | AA38: =IFERROR(WeeklySummaryDataTable[[#This Row],[Logistics Cost]]/WeeklySummaryDataTable[[#This Row],[Sales Turnover]],0) -> 0.11736838 | AB38: =IFERROR(WeeklySummaryDataTable[[#This Row],[Unsold Items]]/WeeklySummaryDataTable[[#This Row],[Sales Turnover]],0) -> 0 | AC38: =(WeeklySummaryDataTable[[#This Row],[Sales Turnover]]+WeeklySummaryDataTable[[#This Row],[Catering Turnover]]+WeeklySummaryDataTable[[#This Row],[TGTG Turnover]])-(WeeklySummaryDataTable[[#This Row],[Fridge Food Cost]]+WeeklySummaryDataTable[[#This Row],[Catering Food Cost]]+WeeklySummaryDataTable[[#This Row],[Logistics Cost]])-WeeklySummaryDataTable[[#This Row],[POS & Software Percentage]]-WeeklySummaryDataTable[[#This Row],[RFID Tags]] -> 928.56943 | AD38: =IFERROR(WeeklySummaryDataTable[[#This Row],[Net Margin]]/(WeeklySummaryDataTable[[#This Row],[Sales Turnover]]+WeeklySummaryDataTable[[#This Row],[Catering Turnover]]+WeeklySummaryDataTable[[#This Row],[TGTG Turnover]]),0) -> 0.06280904
B39: 22 | C39: 46167 | D39: 46173 | E39: 13215.79 | F39: 9.04 | G39: 379.66 | H39: 651.33 | I39: =(WeeklySummaryDataTable[[#This Row],[Total Sales]]+WeeklySummaryDataTable[[#This Row],[Customer Credit]]-WeeklySummaryDataTable[[#This Row],[Total Refund]])/1.06 -> 13073.66 | J39: 40 | K39: 0 | L39: 55 | M39: 9993 | N39: {=IFERROR(SUM(_xlfn._xlws.FILTER(ByCategoryWeeklyAddedDataTable[Added Value],(ByCategoryWeeklyAddedDataTable[Week No]=WeeklySummaryDataTable[[#This Row],[Week No]])*(ByCategoryWeeklyAddedDataTable[Start Date]=WeeklySummaryDataTable[[#This Row],[Start Date]]))),0)} -> 9993.46 | O39: 0 | P39: 1583 | Q39: 120 | R39: 0 | S39: Semaine de 4 jours + 30 degrés+ Soucis Dispatch bug doc de commande + Sandra absence + Frigo DPG out connexion | T39: =WeeklySummaryDataTable[[#This Row],[Total Sales]]*Settings!$C$3 -> 1189.4211 | U39: 0.1 | V39: =WeeklySummaryDataTable[[#This Row],[Sales Turnover]]/WeeklySummaryDataTable[[#This Row],['# Of Fridge]] -> 326.84151 | W39: =WeeklySummaryDataTable[[#This Row],[Sales Turnover]]-WeeklySummaryDataTable[[#This Row],[Fridge Food Cost]] -> 3080.6604 | X39: =WeeklySummaryDataTable[[#This Row],[Food Margin In Euro]]/WeeklySummaryDataTable[[#This Row],[Sales Turnover]] -> 0.2356387 | Y39: =IFERROR((WeeklySummaryDataTable[[#This Row],[Catering Turnover]]-WeeklySummaryDataTable[[#This Row],[Catering Food Cost]])/WeeklySummaryDataTable[[#This Row],[Catering Turnover]],0) -> 0 | Z39: =WeeklySummaryDataTable[[#This Row],[Logistics Cost]]/WeeklySummaryDataTable[[#This Row],['# Of Fridge]] -> 39.575 | AA39: =IFERROR(WeeklySummaryDataTable[[#This Row],[Logistics Cost]]/WeeklySummaryDataTable[[#This Row],[Sales Turnover]],0) -> 0.12108315 | AB39: =IFERROR(WeeklySummaryDataTable[[#This Row],[Unsold Items]]/WeeklySummaryDataTable[[#This Row],[Sales Turnover]],0) -> 0 | AC39: =(WeeklySummaryDataTable[[#This Row],[Sales Turnover]]+WeeklySummaryDataTable[[#This Row],[Catering Turnover]]+WeeklySummaryDataTable[[#This Row],[TGTG Turnover]])-(WeeklySummaryDataTable[[#This Row],[Fridge Food Cost]]+WeeklySummaryDataTable[[#This Row],[Catering Food Cost]]+WeeklySummaryDataTable[[#This Row],[Logistics Cost]])-WeeklySummaryDataTable[[#This Row],[POS & Software Percentage]]-WeeklySummaryDataTable[[#This Row],[RFID Tags]] -> 363.13928 | AD39: =IFERROR(WeeklySummaryDataTable[[#This Row],[Net Margin]]/(WeeklySummaryDataTable[[#This Row],[Sales Turnover]]+WeeklySummaryDataTable[[#This Row],[Catering Turnover]]+WeeklySummaryDataTable[[#This Row],[TGTG Turnover]]),0) -> 0.02766004
B40: 23 | C40: 46174 | D40: 46180 | E40: 16913.06 | F40: 29.82 | G40: 367.16 | H40: 735.02 | I40: =(WeeklySummaryDataTable[[#This Row],[Total Sales]]+WeeklySummaryDataTable[[#This Row],[Customer Credit]]-WeeklySummaryDataTable[[#This Row],[Total Refund]])/1.06 -> 16621 | J40: 40 | K40: 0 | L40: 55 | M40: {=IFERROR(SUM(_xlfn._xlws.FILTER(ByCategoryWeeklyDispatchDataTable[Foodcost Value],ByCategoryWeeklyDispatchDataTable[Week No]=WeeklySummaryDataTable[[#This Row],[Week No]])),0)} -> 11644.54 | N40: {=IFERROR(SUM(_xlfn._xlws.FILTER(ByCategoryWeeklyAddedDataTable[Added Value],(ByCategoryWeeklyAddedDataTable[Week No]=WeeklySummaryDataTable[[#This Row],[Week No]])*(ByCategoryWeeklyAddedDataTable[Start Date]=WeeklySummaryDataTable[[#This Row],[Start Date]]))),0)} -> 12099.23 | O40: 0 | P40: 1983.33 | Q40: 120 | R40: 0 | S40: DHL Caisse recup + Fluxys 2X | T40: =WeeklySummaryDataTable[[#This Row],[Total Sales]]*Settings!$C$3 -> 1522.1754 | U40: 0.1 | V40: =WeeklySummaryDataTable[[#This Row],[Sales Turnover]]/WeeklySummaryDataTable[[#This Row],['# Of Fridge]] -> 415.525 | W40: =WeeklySummaryDataTable[[#This Row],[Sales Turnover]]-WeeklySummaryDataTable[[#This Row],[Fridge Food Cost]] -> 4976.46 | X40: =WeeklySummaryDataTable[[#This Row],[Food Margin In Euro]]/WeeklySummaryDataTable[[#This Row],[Sales Turnover]] -> 0.29940798 | Y40: =IFERROR((WeeklySummaryDataTable[[#This Row],[Catering Turnover]]-WeeklySummaryDataTable[[#This Row],[Catering Food Cost]])/WeeklySummaryDataTable[[#This Row],[Catering Turnover]],0) -> 0 | Z40: =WeeklySummaryDataTable[[#This Row],[Logistics Cost]]/WeeklySummaryDataTable[[#This Row],['# Of Fridge]] -> 49.58325 | AA40: =IFERROR(WeeklySummaryDataTable[[#This Row],[Logistics Cost]]/WeeklySummaryDataTable[[#This Row],[Sales Turnover]],0) -> 0.11932676 | AB40: =IFERROR(WeeklySummaryDataTable[[#This Row],[Unsold Items]]/WeeklySummaryDataTable[[#This Row],[Sales Turnover]],0) -> 0 | AC40: =(WeeklySummaryDataTable[[#This Row],[Sales Turnover]]+WeeklySummaryDataTable[[#This Row],[Catering Turnover]]+WeeklySummaryDataTable[[#This Row],[TGTG Turnover]])-(WeeklySummaryDataTable[[#This Row],[Fridge Food Cost]]+WeeklySummaryDataTable[[#This Row],[Catering Food Cost]]+WeeklySummaryDataTable[[#This Row],[Logistics Cost]])-WeeklySummaryDataTable[[#This Row],[POS & Software Percentage]]-WeeklySummaryDataTable[[#This Row],[RFID Tags]] -> 1525.8546 | AD40: =IFERROR(WeeklySummaryDataTable[[#This Row],[Net Margin]]/(WeeklySummaryDataTable[[#This Row],[Sales Turnover]]+WeeklySummaryDataTable[[#This Row],[Catering Turnover]]+WeeklySummaryDataTable[[#This Row],[TGTG Turnover]]),0) -> 0.091500036
B41: 24 | C41: 46181 | D41: 46187 | E41: 16234.08 | F41: 9.94 | G41: 788.69 | H41: 835.99 | I41: =(WeeklySummaryDataTable[[#This Row],[Total Sales]]+WeeklySummaryDataTable[[#This Row],[Customer Credit]]-WeeklySummaryDataTable[[#This Row],[Total Refund]])/1.06 -> 16094.462 | J41: 41 | K41: 0 | L41: 55 | M41: {=IFERROR(SUM(_xlfn._xlws.FILTER(ByCategoryWeeklyDispatchDataTable[Foodcost Value],ByCategoryWeeklyDispatchDataTable[Week No]=WeeklySummaryDataTable[[#This Row],[Week No]])),0)} -> 12416.68 | N41: {=IFERROR(SUM(_xlfn._xlws.FILTER(ByCategoryWeeklyAddedDataTable[Added Value],(ByCategoryWeeklyAddedDataTable[Week No]=WeeklySummaryDataTable[[#This Row],[Week No]])*(ByCategoryWeeklyAddedDataTable[Start Date]=WeeklySummaryDataTable[[#This Row],[Start Date]]))),0)} -> 12314.94 | O41: 0 | P41: 1741 | Q41: 120 | R41: 0 | S41: RTBF Déménagement final ancien bâtiment +200 euro frigo voisins + DPG Connection | T41: =WeeklySummaryDataTable[[#This Row],[Total Sales]]*Settings!$C$3 -> 1461.0672 | U41: 0.1 | V41: =WeeklySummaryDataTable[[#This Row],[Sales Turnover]]/WeeklySummaryDataTable[[#This Row],['# Of Fridge]] -> 392.54786 | W41: =WeeklySummaryDataTable[[#This Row],[Sales Turnover]]-WeeklySummaryDataTable[[#This Row],[Fridge Food Cost]] -> 3677.7823 | X41: =WeeklySummaryDataTable[[#This Row],[Food Margin In Euro]]/WeeklySummaryDataTable[[#This Row],[Sales Turnover]] -> 0.22851228 | Y41: =IFERROR((WeeklySummaryDataTable[[#This Row],[Catering Turnover]]-WeeklySummaryDataTable[[#This Row],[Catering Food Cost]])/WeeklySummaryDataTable[[#This Row],[Catering Turnover]],0) -> 0 | Z41: =WeeklySummaryDataTable[[#This Row],[Logistics Cost]]/WeeklySummaryDataTable[[#This Row],['# Of Fridge]] -> 42.463415 | AA41: =IFERROR(WeeklySummaryDataTable[[#This Row],[Logistics Cost]]/WeeklySummaryDataTable[[#This Row],[Sales Turnover]],0) -> 0.10817385 | AB41: =IFERROR(WeeklySummaryDataTable[[#This Row],[Unsold Items]]/WeeklySummaryDataTable[[#This Row],[Sales Turnover]],0) -> 0 | AC41: =(WeeklySummaryDataTable[[#This Row],[Sales Turnover]]+WeeklySummaryDataTable[[#This Row],[Catering Turnover]]+WeeklySummaryDataTable[[#This Row],[TGTG Turnover]])-(WeeklySummaryDataTable[[#This Row],[Fridge Food Cost]]+WeeklySummaryDataTable[[#This Row],[Catering Food Cost]]+WeeklySummaryDataTable[[#This Row],[Logistics Cost]])-WeeklySummaryDataTable[[#This Row],[POS & Software Percentage]]-WeeklySummaryDataTable[[#This Row],[RFID Tags]] -> 530.61506 | AD41: =IFERROR(WeeklySummaryDataTable[[#This Row],[Net Margin]]/(WeeklySummaryDataTable[[#This Row],[Sales Turnover]]+WeeklySummaryDataTable[[#This Row],[Catering Turnover]]+WeeklySummaryDataTable[[#This Row],[TGTG Turnover]]),0) -> 0.032856516
B42: 25 | C42: 46188 | D42: 46194 | E42: 15584.79 | F42: 62.25 | G42: 301.84 | H42: 729.42 | I42: =(WeeklySummaryDataTable[[#This Row],[Total Sales]]+WeeklySummaryDataTable[[#This Row],[Customer Credit]]-WeeklySummaryDataTable[[#This Row],[Total Refund]])/1.06 -> 15332.038 | J42: 41 | K42: 0 | L42: 55 | M42: {=IFERROR(SUM(_xlfn._xlws.FILTER(ByCategoryWeeklyDispatchDataTable[Foodcost Value],ByCategoryWeeklyDispatchDataTable[Week No]=WeeklySummaryDataTable[[#This Row],[Week No]])),0)} -> 11774.05 | N42: {=IFERROR(SUM(_xlfn._xlws.FILTER(ByCategoryWeeklyAddedDataTable[Added Value],(ByCategoryWeeklyAddedDataTable[Week No]=WeeklySummaryDataTable[[#This Row],[Week No]])*(ByCategoryWeeklyAddedDataTable[Start Date]=WeeklySummaryDataTable[[#This Row],[Start Date]]))),0)} -> 0 | O42: 0 | P42: 1689 | Q42: 120 | R42: 0 | S42: 1 frigo granola + 3 congelo delimeal out car bloc prise défectueux.+ Relivraison ABB + thermo Vilvoorde jeudi car mail client+ Glitch chez Husky mercredi et jeudi + RTBF roi et reine moins de conso | T42: =WeeklySummaryDataTable[[#This Row],[Total Sales]]*Settings!$C$3 -> 1402.6311 | U42: 0.1 | V42: =WeeklySummaryDataTable[[#This Row],[Sales Turnover]]/WeeklySummaryDataTable[[#This Row],['# Of Fridge]] -> 373.95214 | W42: =WeeklySummaryDataTable[[#This Row],[Sales Turnover]]-WeeklySummaryDataTable[[#This Row],[Fridge Food Cost]] -> 3557.9877 | X42: =WeeklySummaryDataTable[[#This Row],[Food Margin In Euro]]/WeeklySummaryDataTable[[#This Row],[Sales Turnover]] -> 0.23206229 | Y42: =IFERROR((WeeklySummaryDataTable[[#This Row],[Catering Turnover]]-WeeklySummaryDataTable[[#This Row],[Catering Food Cost]])/WeeklySummaryDataTable[[#This Row],[Catering Turnover]],0) -> 0 | Z42: =WeeklySummaryDataTable[[#This Row],[Logistics Cost]]/WeeklySummaryDataTable[[#This Row],['# Of Fridge]] -> 41.195122 | AA42: =IFERROR(WeeklySummaryDataTable[[#This Row],[Logistics Cost]]/WeeklySummaryDataTable[[#This Row],[Sales Turnover]],0) -> 0.11016148 | AB42: =IFERROR(WeeklySummaryDataTable[[#This Row],[Unsold Items]]/WeeklySummaryDataTable[[#This Row],[Sales Turnover]],0) -> 0 | AC42: =(WeeklySummaryDataTable[[#This Row],[Sales Turnover]]+WeeklySummaryDataTable[[#This Row],[Catering Turnover]]+WeeklySummaryDataTable[[#This Row],[TGTG Turnover]])-(WeeklySummaryDataTable[[#This Row],[Fridge Food Cost]]+WeeklySummaryDataTable[[#This Row],[Catering Food Cost]]+WeeklySummaryDataTable[[#This Row],[Logistics Cost]])-WeeklySummaryDataTable[[#This Row],[POS & Software Percentage]]-WeeklySummaryDataTable[[#This Row],[RFID Tags]] -> 521.25664 | AD42: =IFERROR(WeeklySummaryDataTable[[#This Row],[Net Margin]]/(WeeklySummaryDataTable[[#This Row],[Sales Turnover]]+WeeklySummaryDataTable[[#This Row],[Catering Turnover]]+WeeklySummaryDataTable[[#This Row],[TGTG Turnover]]),0) -> 0.033876347
B43: 26 | C43: 46195 | D43: 46201 | E43: 17030.08 | F43: 8.3 | G43: 471.77 | H43: 895.97 | I43: =(WeeklySummaryDataTable[[#This Row],[Total Sales]]+WeeklySummaryDataTable[[#This Row],[Customer Credit]]-WeeklySummaryDataTable[[#This Row],[Total Refund]])/1.06 -> 16903.538 | J43: 41 | K43: 263 | L43: 55 | M43: {=IFERROR(SUM(_xlfn._xlws.FILTER(ByCategoryWeeklyDispatchDataTable[Foodcost Value],ByCategoryWeeklyDispatchDataTable[Week No]=WeeklySummaryDataTable[[#This Row],[Week No]])),0)} -> 12239.34 | N43: {=IFERROR(SUM(_xlfn._xlws.FILTER(ByCategoryWeeklyAddedDataTable[Added Value],(ByCategoryWeeklyAddedDataTable[Week No]=WeeklySummaryDataTable[[#This Row],[Week No]])*(ByCategoryWeeklyAddedDataTable[Start Date]=WeeklySummaryDataTable[[#This Row],[Start Date]]))),0)} -> 12267.45 | O43: 184 | P43: 1711.6 | Q43: 67 | R43: 0 | S43: Nouvelles tournées via APP + Van+ Repasser chez plusieurs clients car grosses conso avec les 38°C + Hadrien bloqué Van déchargé | T43: =WeeklySummaryDataTable[[#This Row],[Total Sales]]*Settings!$C$3 -> 1532.7072 | U43: 0.1 | V43: =WeeklySummaryDataTable[[#This Row],[Sales Turnover]]/WeeklySummaryDataTable[[#This Row],['# Of Fridge]] -> 412.28141 | W43: =WeeklySummaryDataTable[[#This Row],[Sales Turnover]]-WeeklySummaryDataTable[[#This Row],[Fridge Food Cost]] -> 4664.1977 | X43: =WeeklySummaryDataTable[[#This Row],[Food Margin In Euro]]/WeeklySummaryDataTable[[#This Row],[Sales Turnover]] -> 0.27593027 | Y43: =IFERROR((WeeklySummaryDataTable[[#This Row],[Catering Turnover]]-WeeklySummaryDataTable[[#This Row],[Catering Food Cost]])/WeeklySummaryDataTable[[#This Row],[Catering Turnover]],0) -> 0.30038023 | Z43: =WeeklySummaryDataTable[[#This Row],[Logistics Cost]]/WeeklySummaryDataTable[[#This Row],['# Of Fridge]] -> 41.746341 | AA43: =IFERROR(WeeklySummaryDataTable[[#This Row],[Logistics Cost]]/WeeklySummaryDataTable[[#This Row],[Sales Turnover]],0) -> 0.10125691 | AB43: =IFERROR(WeeklySummaryDataTable[[#This Row],[Unsold Items]]/WeeklySummaryDataTable[[#This Row],[Sales Turnover]],0) -> 0 | AC43: =(WeeklySummaryDataTable[[#This Row],[Sales Turnover]]+WeeklySummaryDataTable[[#This Row],[Catering Turnover]]+WeeklySummaryDataTable[[#This Row],[TGTG Turnover]])-(WeeklySummaryDataTable[[#This Row],[Fridge Food Cost]]+WeeklySummaryDataTable[[#This Row],[Catering Food Cost]]+WeeklySummaryDataTable[[#This Row],[Logistics Cost]])-WeeklySummaryDataTable[[#This Row],[POS & Software Percentage]]-WeeklySummaryDataTable[[#This Row],[RFID Tags]] -> 1553.7905 | AD43: =IFERROR(WeeklySummaryDataTable[[#This Row],[Net Margin]]/(WeeklySummaryDataTable[[#This Row],[Sales Turnover]]+WeeklySummaryDataTable[[#This Row],[Catering Turnover]]+WeeklySummaryDataTable[[#This Row],[TGTG Turnover]]),0) -> 0.090223682
M46: based on ADDED
L47: 1 | M47: Fill in historical data
L48: 2 | M48: Compare real data (ADDED) vs Dispatch Data
L49: 3 | M49: Huppertz | N49: charge them ADDED | P49: Specific data
Q53: 158
Q54: 324
Q55: 239

Sheet DV List
C3: {=FormatDateYear(_xlfn.DROP(_xlfn.REDUCE("",_xlfn.SEQUENCE(5,1,2025),_xlfn.LAMBDA(_xlpm.a,_xlpm.c,_xlfn.VSTACK(_xlpm.a,DATE(_xlpm.c,_xlfn.SEQUENCE(12),1)))),1))} -> January 2025
C4: February 2025
C5: March 2025
C6: April 2025
C7: May 2025
C8: June 2025
C9: July 2025
C10: August 2025
C11: September 2025
C12: October 2025
C13: November 2025
C14: December 2025
C15: January 2026
... C62: December 2029

Sheet Monthly Client Analysis
D1: Can we go YoY? | F1: COPY PASTE FOR AN EXTRA MONTH
D2: How do we add exta months
D3: March 2026 | N3: November 2025 | X3: March 2026 | AH3: April 2026
C4: Fridge Name | D4: Food Cost | E4: Sales Turnover | F4: Food Margin | G4: % Food Margin | H4: Service Additional | I4: Fraction | J4: Logistics Cost | K4: POS & Software | L4: Client Fee | M4: Net Margin | N4: Food Cost | O4: Sales Turnover | P4: Food Margin | Q4: % Food Margin | R4: Service Additional | S4: Fraction | T4: Logistics Cost | U4: POS & Software | V4: Client Fee | W4: Net Margin | X4: Food Cost | Y4: Sales Turnover | Z4: Food Margin | AA4: % Food Margin | AB4: Service Additional | AC4: Fraction | AD4: Logistics Cost | AE4: POS & Software | AF4: Client Fee | AG4: Net Margin | AH4: Food Cost | AI4: Sales Turnover | AJ4: Food Margin | AK4: % Food Margin | AL4: Service Additional | AM4: Fraction | AN4: Logistics Cost | AO4: POS & Software | AP4: Client Fee | AQ4: Net Margin
C5: ABB Zaventem | D5: {=MonthlyByFridgeAnalysis($C$5:$C$45,D3)} -> 74.68 | E5: 1247.63 | F5: 1172.95 | G5: 0.94014251 | H5: 0 | I5: 0.027027027 | J5: 209.95931 | K5: 112.2867 | L5: 648.91667 | M5: 1499.6207 | N5: {=MonthlyByFridgeAnalysis($C$5:$C$45, N3)} -> 0 | O5: 1199.05 | P5: 1199.05 | Q5: 1 | R5: 0 | S5: 0.027027027 | T5: 184.88031 | U5: 107.9145 | V5: 648.91667 | W5: 1555.1719 | X5: {=MonthlyByFridgeAnalysis($C$5:$C$45, X3)} -> 74.68 | Y5: 1247.63 | Z5: 1172.95 | AA5: 0.94014251 | AB5: 0 | AC5: 0.027027027 | AD5: 209.95931 | AE5: 112.2867 | AF5: 648.91667 | AG5: 1499.6207 | AH5: {=MonthlyByFridgeAnalysis($C$5:$C$45, AH3)} -> 680.54 | AI5: 783.73 | AJ5: 103.19 | AK5: 0.13166524 | AL5: 0 | AM5: 0.027027027 | AN5: 208.28286 | AO5: 70.5357 | AP5: 648.91667 | AQ5: 473.28811
C6: Abbott Wavre | D6: 19.84 | E6: 290.41 | F6: 270.57 | G6: 0.93168279 | H6: 0 | I6: 0.027027027 | J6: 209.95931 | K6: 26.1369 | L6: 900 | M6: 934.47379 | N6: 0 | O6: 247.51 | P6: 247.51 | Q6: 1 | R6: 0 | S6: 0.027027027 | T6: 184.88031 | U6: 22.2759 | V6: 900 | W6: 940.35379 | X6: 19.84 | Y6: 290.41 | Z6: 270.57 | AA6: 0.93168279 | AB6: 0 | AC6: 0.027027027 | AD6: 209.95931 | AE6: 26.1369 | AF6: 900 | AG6: 934.47379 | AH6: 285.71 | AI6: 273.05 | AJ6: -12.66 | AK6: -0.046365135 | AL6: 0 | AM6: 0.027027027 | AN6: 208.28286 | AO6: 24.5745 | AP6: 900 | AQ6: 654.48264
C7: Allianz Brussels | D7: 128.22 | E7: 1188.67 | F7: 1060.45 | G7: 0.89213154 | H7: 0 | I7: 0.027027027 | J7: 209.95931 | K7: 106.9803 | L7: 900 | M7: 1643.5104 | N7: 0 | O7: 1180.47 | P7: 1180.47 | Q7: 1 | R7: 0 | S7: 0.027027027 | T7: 184.88031 | U7: 106.2423 | V7: 900 | W7: 1789.3474 | X7: 128.22 | Y7: 1188.67 | Z7: 1060.45 | AA7: 0.89213154 | AB7: 0 | AC7: 0.027027027 | AD7: 209.95931 | AE7: 106.9803 | AF7: 900 | AG7: 1643.5104 | AH7: 830.72 | AI7: 1260.12 | AJ7: 429.4 | AK7: 0.3407612 | AL7: 0 | AM7: 0.027027027 | AN7: 208.28286 | AO7: 113.4108 | AP7: 900 | AQ7: 1007.7063
C8: Allnex | D8: 109.46 | E8: 2042.58 | F8: 1933.12 | G8: 0.94641091 | H8: 0 | I8: 0.027027027 | J8: 209.95931 | K8: 183.8322 | L8: 684 | M8: 2223.3285 | N8: 0 | O8: 1449.5 | P8: 1449.5 | Q8: 1 | R8: 0 | S8: 0.027027027 | T8: 184.88031 | U8: 130.455 | V8: 684 | W8: 1818.1647 | X8: 109.46 | Y8: 2042.58 | Z8: 1933.12 | AA8: 0.94641091 | AB8: 0 | AC8: 0.027027027 | AD8: 209.95931 | AE8: 183.8322 | AF8: 684 | AG8: 2223.3285 | AH8: 1295.44 | AI8: 2048.29 | AJ8: 752.85 | AK8: 0.36755049 | AL8: 0 | AM8: 0.027027027 | AN8: 208.28286 | AO8: 184.3461 | AP8: 684 | AQ8: 1044.221
C9: Allnex Freezer | D9: 0 | E9: 0 | F9: 0 | G9: 0 | H9: 0 | I9: 0 | J9: 0 | K9: 0 | L9: 600 | M9: 600 | N9: 0 | O9: 0 | P9: 0 | Q9: 0 | R9: 0 | S9: 0 | T9: 0 | U9: 0 | V9: 600 | W9: 600 | X9: 0 | Y9: 0 | Z9: 0 | AA9: 0 | AB9: 0 | AC9: 0 | AD9: 0 | AE9: 0 | AF9: 600 | AG9: 600 | AH9: 186.52 | AI9: 591 | AJ9: 404.48 | AK9: 0.68439932 | AL9: 0 | AM9: 0 | AN9: 0 | AO9: 53.19 | AP9: 600 | AQ9: 951.29
C10: Bank Degroof | D10: 28.63 | E10: 553.26 | F10: 524.63 | G10: 0.94825218 | H10: 0 | I10: 0.027027027 | J10: 209.95931 | K10: 49.7934 | L10: 888 | M10: 1152.8773 | N10: 0 | O10: 506.95 | P10: 506.95 | Q10: 1 | R10: 0 | S10: 0.027027027 | T10: 184.88031 | U10: 45.6255 | V10: 888 | W10: 1164.4442 | X10: 28.63 | Y10: 553.26 | Z10: 524.63 | AA10: 0.94825218 | AB10: 0 | AC10: 0.027027027 | AD10: 209.95931 | AE10: 49.7934 | AF10: 888 | AG10: 1152.8773 | AH10: 415.11 | AI10: 472.74 | AJ10: 57.63 | AK10: 0.12190633 | AL10: 0 | AM10: 0.027027027 | AN10: 208.28286 | AO10: 42.5466 | AP10: 888 | AQ10: 694.80054
C11: Bia Group Overijse | D11: 110.76 | E11: 1615.31 | F11: 1504.55 | G11: 0.93143112 | H11: 0 | I11: 0.027027027 | J11: 209.95931 | K11: 145.3779 | L11: 824 | M11: 1973.2128 | N11: 0 | O11: 1246.46 | P11: 1246.46 | Q11: 1 | R11: 0 | S11: 0.027027027 | T11: 184.88031 | U11: 112.1814 | V11: 824 | W11: 1773.3983 | X11: 110.76 | Y11: 1615.31 | Z11: 1504.55 | AA11: 0.93143112 | AB11: 0 | AC11: 0.027027027 | AD11: 209.95931 | AE11: 145.3779 | AF11: 824 | AG11: 1973.2128 | AH11: 985.02 | AI11: 1308.51 | AJ11: 323.49 | AK11: 0.24722012 | AL11: 0 | AM11: 0.027027027 | AN11: 208.28286 | AO11: 117.7659 | AP11: 824 | AQ11: 821.44124
C12: Brussels Airlines Airport | D12: 106.85 | E12: 881.13 | F12: 774.28 | G12: 0.87873526 | H12: 0 | I12: 0.027027027 | J12: 209.95931 | K12: 79.3017 | L12: 814 | M12: 1299.019 | N12: 0 | O12: 862.67 | P12: 862.67 | Q12: 1 | R12: 0 | S12: 0.027027027 | T12: 184.88031 | U12: 77.6403 | V12: 814 | W12: 1414.1494 | X12: 106.85 | Y12: 881.13 | Z12: 774.28 | AA12: 0.87873526 | AB12: 0 | AC12: 0.027027027 | AD12: 209.95931 | AE12: 79.3017 | AF12: 814 | AG12: 1299.019 | AH12: 660.42 | AI12: 876.39 | AJ12: 215.97 | AK12: 0.24643138 | AL12: 0 | AM12: 0.027027027 | AN12: 208.28286 | AO12: 78.8751 | AP12: 814 | AQ12: 742.81204
C13: Brussels Airlines Be house | D13: 177.46 | E13: 2672.5 | F13: 2495.04 | G13: 0.93359775 | H13: 0 | I13: 0.027027027 | J13: 209.95931 | K13: 240.525 | L13: 814 | M13: 2858.5557 | N13: 0 | O13: 2294.72 | P13: 2294.72 | Q13: 1 | R13: 0 | S13: 0.027027027 | T13: 184.88031 | U13: 206.5248 | V13: 814 | W13: 2717.3149 | X13: 177.46 | Y13: 2672.5 | Z13: 2495.04 | AA13: 0.93359775 | AB13: 0 | AC13: 0.027027027 | AD13: 209.95931 | AE13: 240.525 | AF13: 814 | AG13: 2858.5557 | AH13: 1485.63 | AI13: 2180.47 | AJ13: 694.84 | AK13: 0.31866524 | AL13: 0 | AM13: 0.027027027 | AN13: 208.28286 | AO13: 196.2423 | AP13: 814 | AQ13: 1104.3148
C14: Brussels Airlines TFC | D14: 28.74 | E14: 607.43 | F14: 578.69 | G14: 0.95268591 | H14: 0 | I14: 0.027027027 | J14: 209.95931 | K14: 54.6687 | L14: 814 | M14: 1128.062 | N14: 0 | O14: 662.81 | P14: 662.81 | Q14: 1 | R14: 0 | S14: 0.027027027 | T14: 184.88031 | U14: 59.6529 | V14: 814 | W14: 1232.2768 | X14: 28.74 | Y14: 607.43 | Z14: 578.69 | AA14: 0.95268591 | AB14: 0 | AC14: 0.027027027 | AD14: 209.95931 | AE14: 54.6687 | AF14: 814 | AG14: 1128.062 | AH14: 370.95 | AI14: 355.9 | AJ14: -15.05 | AK14: -0.042287159 | AL14: 0 | AM14: 0.027027027 | AN14: 208.28286 | AO14: 32.031 | AP14: 814 | AQ14: 558.63614
C15: Brussels Airlines Vilvoorde | D15: 116.74 | E15: 1045.57 | F15: 928.83 | G15: 0.88834798 | H15: 0 | I15: 0.027027027 | J15: 209.95931 | K15: 94.1013 | L15: 814 | M15: 1438.7694 | N15: 0 | O15: 747.29 | P15: 747.29 | Q15: 1 | R15: 0 | S15: 0.027027027 | T15: 184.88031 | U15: 67.2561 | V15: 814 | W15: 1309.1536 | X15: 116.74 | Y15: 1045.57 | Z15: 928.83 | AA15: 0.88834798 | AB15: 0 | AC15: 0.027027027 | AD15: 209.95931 | AE15: 94.1013 | AF15: 814 | AG15: 1438.7694 | AH15: 750.06 | AI15: 1240.73 | AJ15: 490.67 | AK15: 0.3954688 | AL15: 0 | AM15: 0.027027027 | AN15: 208.28286 | AO15: 111.6657 | AP15: 814 | AQ15: 984.72144
C16: CBC | D16: 78.37 | E16: 1900.53 | F16: 1822.16 | G16: 0.95876413 | H16: 0 | I16: 0.027027027 | J16: 209.95931 | K16: 171.0477 | L16: 900 | M16: 2341.153 | N16: 0 | O16: 1501.13 | P16: 1501.13 | Q16: 1 | R16: 0 | S16: 0.027027027 | T16: 184.88031 | U16: 135.1017 | V16: 900 | W16: 2081.148 | X16: 78.37 | Y16: 1900.53 | Z16: 1822.16 | AA16: 0.95876413 | AB16: 0 | AC16: 0.027027027 | AD16: 209.95931 | AE16: 171.0477 | AF16: 900 | AG16: 2341.153 | AH16: 983.29 | AI16: 1513.54 | AJ16: 530.25 | AK16: 0.35033762 | AL16: 0 | AM16: 0.027027027 | AN16: 208.28286 | AO16: 136.2186 | AP16: 900 | AQ16: 1085.7485
C17: DPG Media Antwerpen | D17: 397.01 | E17: 2870.4 | F17: 2473.39 | G17: 0.86168827 | H17: 0 | I17: 0.027027027 | J17: 209.95931 | K17: 258.336 | L17: 824 | M17: 2829.0947 | N17: 0 | O17: 2987.42 | P17: 2987.42 | Q17: 1 | R17: 0 | S17: 0.027027027 | T17: 184.88031 | U17: 268.8678 | V17: 824 | W17: 3357.6719 | X17: 397.01 | Y17: 2870.4 | Z17: 2473.39 | AA17: 0.86168827 | AB17: 0 | AC17: 0.027027027 | AD17: 209.95931 | AE17: 258.336 | AF17: 824 | AG17: 2829.0947 | AH17: 1765.05 | AI17: 2707.4 | AJ17: 942.35 | AK17: 0.34806456 | AL17: 0 | AM17: 0.027027027 | AN17: 208.28286 | AO17: 243.666 | AP17: 824 | AQ17: 1314.4011
... C45: Zoetis LLN | D45: 256.08 | E45: 4767.81 | F45: 4511.73 | G45: 0.94628981 | H45: 0 | I45: 0.027027027 | J45: 209.95931 | K45: 429.1029 | L45: 925 | M45: 4797.6678 | N45: 0 | O45: 8.89 | P45: 8.89 | Q45: 1 | R45: 0 | S45: 0.027027027 | T45: 184.88031 | U45: 0.8001 | V45: 925 | W45: 748.20959 | X45: 256.08 | Y45: 4767.81 | Z45: 4511.73 | AA45: 0.94628981 | AB45: 0 | AC45: 0.027027027 | AD45: 209.95931 | AE45: 429.1029 | AF45: 925 | AG45: 4797.6678 | AH45: 2827.95 | AI45: 4383.44 | AJ45: 1555.49 | AK45: 0.354856 | AL45: 0 | AM45: 0.027027027 | AN45: 208.28286 | AO45: 394.5096 | AP45: 925 | AQ45: 1877.6975
C46: Total | D46: =SUM(D5:D45) -> 5649.96 | E46: =SUM(E5:E45) -> 78512.62 | F46: =E46-D46 -> 72862.66 | G46: =F46/E46 -> 0.92803756 | H46: =SUM(H5:H45) -> 0 | I46: =SUM(I5:I45) -> 1 | J46: =SUM(J5:J45) -> 7768.4943 | K46: =SUM(K5:K45) -> 7066.1358 | L46: =SUM(L5:L45) -> 30387.833 | M46: =SUM(M5:M45) -> 88415.863 | N46: =SUM(N5:N45) -> 0 | O46: =SUM(O5:O45) -> 57281.28 | P46: =O46-N46 -> 57281.28 | Q46: =P46/O46 -> 1 | R46: =SUM(R5:R45) -> 0 | S46: =SUM(S5:S45) -> 1 | T46: =SUM(T5:T45) -> 6840.5714 | U46: =SUM(U5:U45) -> 5155.3152 | V46: =SUM(V5:V45) -> 30387.833 | W46: =SUM(W5:W45) -> 75673.227 | X46: =SUM(X5:X45) -> 5649.96 | Y46: =SUM(Y5:Y45) -> 78512.62 | Z46: =Y46-X46 -> 72862.66 | AA46: =Z46/Y46 -> 0.92803756 | AB46: =SUM(AB5:AB45) -> 0 | AC46: =SUM(AC5:AC45) -> 1 | AD46: =SUM(AD5:AD45) -> 7768.4943 | AE46: =SUM(AE5:AE45) -> 7066.1358 | AF46: =SUM(AF5:AF45) -> 30387.833 | AG46: =SUM(AG5:AG45) -> 88415.863 | AH46: =SUM(AH5:AH45) -> 45721.15 | AI46: =SUM(AI5:AI45) -> 70600.69 | AJ46: =AI46-AH46 -> 24879.54 | AK46: =AJ46/AI46 -> 0.35239797 | AL46: =SUM(AL5:AL45) -> 0 | AM46: =SUM(AM5:AM45) -> 1 | AN46: =SUM(AN5:AN45) -> 7706.4657 | AO46: =SUM(AO5:AO45) -> 6354.0621 | AP46: =SUM(AP5:AP45) -> 30387.833 | AQ46: =SUM(AQ5:AQ45) -> 41206.846
W47: =W46/37 -> 2045.2223 | AD47: =AD46/Y46 -> 0.098945804 | AG47: =AG46/37 -> 2389.6179 | AN47: =AN46/AI46 -> 0.10915567 | AQ47: =AQ46/37 -> 1113.6985
B49: Documentation des calculs
B51: 1 | C51: Quand commence et quand termine le mois?

Sheet Monthly Supplier Analysis
D3: May 2026 | J3: April 2026 | P3: April 2026 | V3: February 2026 | AB3: March 2026 | AH3: April 2026
C4: Supplier Name | D4: Food Cost | E4: Sales Turnover | F4: Food Margin | G4: % Food Margin | H4: RFID Tag & Transaction Fee | I4: Net Margin | J4: Food Cost | K4: Sales Turnover | L4: Food Margin | M4: % Food Margin | N4: RFID Tag & Transaction Fee | O4: Net Margin | P4: Food Cost | Q4: Sales Turnover | R4: Food Margin | S4: % Food Margin | T4: RFID Tag & Transaction Fee | U4: Net Margin | V4: Food Cost | W4: Sales Turnover | X4: Food Margin | Y4: % Food Margin | Z4: RFID Tag & Transaction Fee | AA4: Net Margin | AB4: Food Cost | AC4: Sales Turnover | AD4: Food Margin | AE4: % Food Margin | AF4: RFID Tag & Transaction Fee | AG4: Net Margin | AH4: Food Cost | AI4: Sales Turnover | AJ4: Food Margin | AK4: % Food Margin | AL4: RFID Tag & Transaction Fee | AM4: Net Margin
C5: Bon - With Love | D5: {=MonthlyBySupplierAnalysis($C$5:$C$23, D3)} -> 1670.25 | E5: 1839.6 | F5: 169.35 | G5: 0.092058056 | H5: 29.3 | I5: 140.05 | J5: {=MonthlyBySupplierAnalysis($C$5:$C$23, J3)} -> 2793.95 | K5: 3994.2 | L5: 1200.25 | M5: 0.30049822 | N5: 63.6 | O5: 1136.65 | P5: {=MonthlyBySupplierAnalysis($C$5:$C$23, P3)} -> 2793.95 | Q5: 3994.2 | R5: 1200.25 | S5: 0.30049822 | T5: 63.6 | U5: 1136.65 | V5: {=MonthlyBySupplierAnalysis($C$5:$C$23, V3)} -> 0 | W5: 2847.6 | X5: 2847.6 | Y5: 1 | Z5: 45.2 | AA5: 2802.4 | AB5: {=MonthlyBySupplierAnalysis($C$5:$C$23, AB3)} -> 303 | AC5: 4378.5 | AD5: 4075.5 | AE5: 0.93079822 | AF5: 69.6 | AG5: 4005.9 | AH5: {=MonthlyBySupplierAnalysis($C$5:$C$23, AH3)} -> 2793.95 | AI5: 3994.2 | AJ5: 1200.25 | AK5: 0.30049822 | AL5: 63.6 | AM5: 1136.65
C6: Boulangerie Louise | D6: 0 | E6: 0 | F6: 0 | G6: 0 | H6: 0 | I6: 0 | J6: 0 | K6: 0 | L6: 0 | M6: 0 | N6: 0 | O6: 0 | P6: 0 | Q6: 0 | R6: 0 | S6: 0 | T6: 0 | U6: 0 | V6: 0 | W6: 29.7 | X6: 29.7 | Y6: 1 | Z6: 0.6 | AA6: 29.1 | AB6: 0 | AC6: 0 | AD6: 0 | AE6: 0 | AF6: 0 | AG6: 0 | AH6: 0 | AI6: 0 | AJ6: 0 | AK6: 0 | AL6: 0 | AM6: 0
C7: Croc&Go | D7: 21848.03 | E7: 27696.06 | F7: 5848.03 | G7: 0.21115025 | H7: 384.1 | I7: 5463.93 | J7: 18827.38 | K7: 27827.26 | L7: 8999.88 | M7: 0.32341955 | N7: 387.3 | O7: 8612.58 | P7: 18827.38 | Q7: 27827.26 | R7: 8999.88 | S7: 0.32341955 | T7: 387.3 | U7: 8612.58 | V7: 0 | W7: 27402.44 | X7: 27402.44 | Y7: 1 | Z7: 383.9 | AA7: 27018.54 | AB7: 2028.28 | AC7: 31415.46 | AD7: 29387.18 | AE7: 0.93543688 | AF7: 437 | AG7: 28950.18 | AH7: 18827.38 | AI7: 27827.26 | AJ7: 8999.88 | AK7: 0.32341955 | AL7: 387.3 | AM7: 8612.58
C8: Colors kitchen | D8: 2932.32 | E8: 3512.75 | F8: 580.43 | G8: 0.16523521 | H8: 37 | I8: 543.43 | J8: 1852.91 | K8: 2086.67 | L8: 233.76 | M8: 0.11202538 | N8: 21.9 | O8: 211.86 | P8: 1852.91 | Q8: 2086.67 | R8: 233.76 | S8: 0.11202538 | T8: 21.9 | U8: 211.86 | V8: 0 | W8: 1549.4 | X8: 1549.4 | Y8: 1 | Z8: 16.4 | AA8: 1533 | AB8: 139.67 | AC8: 2074.08 | AD8: 1934.41 | AE8: 0.9326593 | AF8: 21.9 | AG8: 1912.51 | AH8: 1852.91 | AI8: 2086.67 | AJ8: 233.76 | AK8: 0.11202538 | AL8: 21.9 | AM8: 211.86
C9: Full-iz | D9: 0 | E9: 0 | F9: 0 | G9: 0 | H9: 0 | I9: 0 | J9: 8.8 | K9: 0 | L9: -8.8 | M9: 0 | N9: 0 | O9: -8.8 | P9: 8.8 | Q9: 0 | R9: -8.8 | S9: 0 | T9: 0 | U9: -8.8 | V9: 0 | W9: 802.75 | X9: 802.75 | Y9: 1 | Z9: 17 | AA9: 785.75 | AB9: 25.08 | AC9: 589 | AD9: 563.92 | AE9: 0.95741935 | AF9: 12.4 | AG9: 551.52 | AH9: 8.8 | AI9: 0 | AJ9: -8.8 | AK9: 0 | AL9: 0 | AM9: -8.8
C10: Gaufrine | D10: 1258.12 | E10: 1805.1 | F10: 546.98 | G10: 0.30301922 | H10: 84.5 | I10: 462.48 | J10: 1234.9 | K10: 2237.4 | L10: 1002.5 | M10: 0.44806472 | N10: 105.1 | O10: 897.4 | P10: 1234.9 | Q10: 2237.4 | R10: 1002.5 | S10: 0.44806472 | T10: 105.1 | U10: 897.4 | V10: 0 | W10: 1555.5 | X10: 1555.5 | Y10: 1 | Z10: 77.2 | AA10: 1478.3 | AB10: 221.14 | AC10: 2100 | AD10: 1878.86 | AE10: 0.89469524 | AF10: 104.4 | AG10: 1774.46 | AH10: 1234.9 | AI10: 2237.4 | AJ10: 1002.5 | AK10: 0.44806472 | AL10: 105.1 | AM10: 897.4
C11: GENEROUS | D11: 0 | E11: 15 | F11: 15 | G11: 1 | H11: 0.4 | I11: 14.6 | J11: 0 | K11: 7.5 | L11: 7.5 | M11: 1 | N11: 0.2 | O11: 7.3 | P11: 0 | Q11: 7.5 | R11: 7.5 | S11: 1 | T11: 0.2 | U11: 7.3 | V11: 0 | W11: 75 | X11: 75 | Y11: 1 | Z11: 2 | AA11: 73 | AB11: 0 | AC11: 22.5 | AD11: 22.5 | AE11: 1 | AF11: 0.6 | AG11: 21.9 | AH11: 0 | AI11: 7.5 | AJ11: 7.5 | AK11: 1 | AL11: 0.2 | AM11: 7.3
C12: Gourmart | D12: 875.01 | E12: 1148.26 | F12: 273.25 | G12: 0.23796875 | H12: 12.8 | I12: 260.45 | J12: 686.01 | K12: 1250.3 | L12: 564.29 | M12: 0.45132368 | N12: 13.9 | O12: 550.39 | P12: 686.01 | Q12: 1250.3 | R12: 564.29 | S12: 0.45132368 | T12: 13.9 | U12: 550.39 | V12: 0 | W12: 1444.43 | X12: 1444.43 | Y12: 1 | Z12: 16 | AA12: 1428.43 | AB12: 73.03 | AC12: 1315.19 | AD12: 1242.16 | AE12: 0.9444719 | AF12: 14.6 | AG12: 1227.56 | AH12: 686.01 | AI12: 1250.3 | AJ12: 564.29 | AK12: 0.45132368 | AL12: 13.9 | AM12: 550.39
C13: Grains Noirs | D13: 0 | E13: 0 | F13: 0 | G13: 0 | H13: 0 | I13: 0 | J13: 0 | K13: 0 | L13: 0 | M13: 0 | N13: 0 | O13: 0 | P13: 0 | Q13: 0 | R13: 0 | S13: 0 | T13: 0 | U13: 0 | V13: 0 | W13: 0 | X13: 0 | Y13: 0 | Z13: 0 | AA13: 0 | AB13: 0 | AC13: 0 | AD13: 0 | AE13: 0 | AF13: 0 | AG13: 0 | AH13: 0 | AI13: 0 | AJ13: 0 | AK13: 0 | AL13: 0 | AM13: 0
C14: Greenz | D14: 561.2 | E14: 809 | F14: 247.8 | G14: 0.30630408 | H14: 8.3 | I14: 239.5 | J14: 0 | K14: 0 | L14: 0 | M14: 0 | N14: 0 | O14: 0 | P14: 0 | Q14: 0 | R14: 0 | S14: 0 | T14: 0 | U14: 0 | V14: 0 | W14: 0 | X14: 0 | Y14: 0 | Z14: 0 | AA14: 0 | AB14: 0 | AC14: 801.9 | AD14: 801.9 | AE14: 1 | AF14: 8.1 | AG14: 793.8 | AH14: 0 | AI14: 0 | AJ14: 0 | AK14: 0 | AL14: 0 | AM14: 0
C15: Interdrinks | D15: 361.01 | E15: 109.28 | F15: -251.73 | G15: -2.3035322 | H15: 5.2 | I15: -256.93 | J15: 2118.51 | K15: 3729.13 | L15: 1610.62 | M15: 0.43190235 | N15: 157.5 | O15: 1453.12 | P15: 2118.51 | Q15: 3729.13 | R15: 1610.62 | S15: 0.43190235 | T15: 157.5 | U15: 1453.12 | V15: 0 | W15: 2548.38 | X15: 2548.38 | Y15: 1 | Z15: 121.1 | AA15: 2427.28 | AB15: 340.09 | AC15: 3632.06 | AD15: 3291.97 | AE15: 0.90636443 | AF15: 160.6 | AG15: 3131.37 | AH15: 2118.51 | AI15: 3729.13 | AJ15: 1610.62 | AK15: 0.43190235 | AL15: 157.5 | AM15: 1453.12
C16: La Cantine de Géraldine | D16: 7183.45 | E16: 10890.87 | F16: 3707.42 | G16: 0.34041541 | H16: 422.2 | I16: 3285.22 | J16: 7668.27 | K16: 12732.77 | L16: 5064.5 | M16: 0.3977532 | N16: 489.4 | O16: 4575.1 | P16: 7668.27 | Q16: 12732.77 | R16: 5064.5 | S16: 0.3977532 | T16: 489.4 | U16: 4575.1 | V16: 0 | W16: 13704.67 | X16: 13704.67 | Y16: 1 | Z16: 486.7 | AA16: 13217.97 | AB16: 1296.02 | AC16: 15384.67 | AD16: 14088.65 | AE16: 0.915759 | AF16: 576.2 | AG16: 13512.45 | AH16: 7668.27 | AI16: 12732.77 | AJ16: 5064.5 | AK16: 0.3977532 | AL16: 489.4 | AM16: 4575.1
C17: MadLab | D17: 73.71 | E17: 104.4 | F17: 30.69 | G17: 0.29396552 | H17: 2.9 | I17: 27.79 | J17: 218.57 | K17: 504.9 | L17: 286.33 | M17: 0.5671024 | N17: 14 | O17: 272.33 | P17: 218.57 | Q17: 504.9 | R17: 286.33 | S17: 0.5671024 | T17: 14 | U17: 272.33 | V17: 0 | W17: 198 | X17: 198 | Y17: 1 | Z17: 5.6 | AA17: 192.4 | AB17: 39.71 | AC17: 688.5 | AD17: 648.79 | AE17: 0.94232389 | AF17: 19.1 | AG17: 629.69 | AH17: 218.57 | AI17: 504.9 | AJ17: 286.33 | AK17: 0.5671024 | AL17: 14 | AM17: 272.33
... C23: Tropbon | D23: 458.4 | E23: 785.64 | F23: 327.24 | G23: 0.41652665 | H23: 34.9 | I23: 292.34 | J23: 622.82 | K23: 1090.36 | L23: 467.54 | M23: 0.42879416 | N23: 48 | O23: 419.54 | P23: 622.82 | Q23: 1090.36 | R23: 467.54 | S23: 0.42879416 | T23: 48 | U23: 419.54 | V23: 0 | W23: 948.97 | X23: 948.97 | Y23: 1 | Z23: 42.3 | AA23: 906.67 | AB23: 53.98 | AC23: 937.43 | AD23: 883.45 | AE23: 0.94241703 | AF23: 41.8 | AG23: 841.65 | AH23: 622.82 | AI23: 1090.36 | AJ23: 467.54 | AK23: 0.42879416 | AL23: 48 | AM23: 419.54
C24: TOTAL | D24: =SUM(D5:D23) -> 43689.4 | E24: =SUM(E5:E23) -> 57016.61 | F24: =SUM(F5:F23) -> 13327.21 | G24: =IF(E24>0,(F24/E24),"") -> 0.23374259 | H24: =SUM(H5:H23) -> 1157.5 | I24: =SUM(I5:I23) -> 12169.71 | J24: =SUM(J5:J23) -> 45225.18 | K24: =SUM(K5:K23) -> 68931.79 | L24: =SUM(L5:L23) -> 23706.61 | M24: =IF(K24>0,(L24/K24),"") -> 0.34391403 | N24: =SUM(N5:N23) -> 1518.8 | O24: =SUM(O5:O23) -> 22187.81 | P24: =SUM(P5:P23) -> 45225.18 | Q24: =SUM(Q5:Q23) -> 68931.79 | R24: =SUM(R5:R23) -> 23706.61 | S24: =IF(Q24>0,(R24/Q24),"") -> 0.34391403 | T24: =SUM(T5:T23) -> 1518.8 | U24: =SUM(U5:U23) -> 22187.81 | V24: =SUM(V5:V23) -> 0 | W24: =SUM(W5:W23) -> 66218.98 | X24: =SUM(X5:X23) -> 66218.98 | Y24: =IF(W24>0,(X24/W24),"") -> 1 | Z24: =SUM(Z5:Z23) -> 1426.5 | AA24: =SUM(AA5:AA23) -> 64792.48 | AB24: =SUM(AB5:AB23) -> 5648.86 | AC24: =SUM(AC5:AC23) -> 78250.02 | AD24: =SUM(AD5:AD23) -> 72601.16 | AE24: =IF(AC24>0,(AD24/AC24),"") -> 0.92781011 | AF24: =SUM(AF5:AF23) -> 1708 | AG24: =SUM(AG5:AG23) -> 70893.16 | AH24: =SUM(AH5:AH23) -> 45225.18 | AI24: =SUM(AI5:AI23) -> 68931.79 | AJ24: =SUM(AJ5:AJ23) -> 23706.61 | AK24: =IF(AI24>0,(AJ24/AI24),"") -> 0.34391403 | AL24: =SUM(AL5:AL23) -> 1518.8 | AM24: =SUM(AM5:AM23) -> 22187.81
C27: Documentation des calculs

Sheet Monthly Category Analysis
D2: May 2026 | J2: April 2026 | P2: March 2026 | V2: April 2026
C3: Categories | D3: Food Cost | E3: Sales Turnover | F3: Food Margin | G3: % Food Margin | H3: RFID Tag & Transaction Fee | I3: Net Margin | J3: Food Cost | K3: Sales Turnover | L3: Food Margin | M3: % Food Margin | N3: RFID Tag & Transaction Fee | O3: Net Margin | P3: Food Cost | Q3: Sales Turnover | R3: Food Margin | S3: % Food Margin | T3: RFID Tag & Transaction Fee | U3: Net Margin | V3: Food Cost | W3: Sales Turnover | X3: Food Margin | Y3: % Food Margin | Z3: RFID Tag & Transaction Fee | AA3: Net Margin
C4: 1. Cold Dishes | D4: {=MonthlyByCategoryAnalysis($C$4:$C$12, D2)} -> 10112.5 | E4: 12081.64 | F4: 1969.14 | G4: 0.16298615 | H4: 122.2 | I4: 1846.94 | J4: {=MonthlyByCategoryAnalysis($C$4:$C$12, J2)} -> 8975.71 | K4: 13036.38 | L4: 4060.67 | M4: 0.31148754 | N4: 132.5 | O4: 3928.17 | P4: {=MonthlyByCategoryAnalysis($C$4:$C$12, P2)} -> 915.51 | Q4: 14441.92 | R4: 13526.41 | S4: 0.93660746 | T4: 147.5 | U4: 13378.91 | V4: {=MonthlyByCategoryAnalysis($C$4:$C$12, V2)} -> 8975.71 | W4: 13036.38 | X4: 4060.67 | Y4: 0.31148754 | Z4: 132.5 | AA4: 3928.17
C5: 2. Wraps & Sandwiches | D5: 13405.78 | E5: 17454.02 | F5: 4048.24 | G5: 0.2319374 | H5: 291.2 | I5: 3757.04 | J5: 13208.74 | K5: 19367.63 | L5: 6158.89 | M5: 0.31799916 | N5: 323.6 | O5: 5835.29 | P5: 1415.77 | Q5: 21601.94 | R5: 20186.17 | S5: 0.93446098 | T5: 361.2 | U5: 19824.97 | V5: 13208.74 | W5: 19367.63 | X5: 6158.89 | Y5: 0.31799916 | Z5: 323.6 | AA5: 5835.29
C6: 3. Warm Dishes Jar | D6: 875.01 | E6: 1148.26 | F6: 273.25 | G6: 0.23796875 | H6: 12.8 | I6: 260.45 | J6: 686.01 | K6: 1250.3 | L6: 564.29 | M6: 0.45132368 | N6: 13.9 | O6: 550.39 | P6: 73.03 | Q6: 1315.19 | R6: 1242.16 | S6: 0.9444719 | T6: 14.6 | U6: 1227.56 | V6: 686.01 | W6: 1250.3 | X6: 564.29 | Y6: 0.45132368 | Z6: 13.9 | AA6: 550.39
C7: 4. Warm Dishes | D7: 7101.41 | E7: 8486 | F7: 1384.59 | G7: 0.16316168 | H7: 99 | I7: 1285.59 | J7: 6971.35 | K7: 10012.69 | L7: 3041.34 | M7: 0.30374854 | N7: 128.2 | O7: 2913.14 | P7: 745.98 | Q7: 11622.35 | R7: 10876.37 | S7: 0.93581505 | T7: 147.3 | U7: 10729.07 | V7: 6971.35 | W7: 10012.69 | X7: 3041.34 | Y7: 0.30374854 | Z7: 128.2 | AA7: 2913.14
C8: 5. Desserts | D8: 7183.45 | E8: 10890.87 | F8: 3707.42 | G8: 0.34041541 | H8: 422.2 | I8: 3285.22 | J8: 7668.27 | K8: 12732.77 | L8: 5064.5 | M8: 0.3977532 | N8: 489.4 | O8: 4575.1 | P8: 1296.02 | Q8: 15384.67 | R8: 14088.65 | S8: 0.915759 | T8: 576.2 | U8: 13512.45 | V8: 7668.27 | W8: 12732.77 | X8: 5064.5 | Y8: 0.3977532 | Z8: 489.4 | AA8: 4575.1
C9: 6. Snacks | D9: 2140.92 | E9: 3262.63 | F9: 1121.71 | G9: 0.34380546 | H9: 147.8 | I9: 973.91 | J9: 2225.64 | K9: 3996.36 | L9: 1770.72 | M9: 0.44308321 | N9: 174.4 | O9: 1596.32 | P9: 314.84 | Q9: 3748.43 | R9: 3433.59 | S9: 0.9160075 | T9: 165.9 | U9: 3267.69 | V9: 2225.64 | W9: 3996.36 | X9: 1770.72 | Y9: 0.44308321 | Z9: 174.4 | AA9: 1596.32
C10: 7. Drinks | D10: 2737.93 | E10: 3530.85 | F10: 792.92 | G10: 0.22456915 | H10: 156.1 | I10: 636.82 | J10: 2274.44 | K10: 4067.53 | L10: 1793.09 | M10: 0.44083018 | N10: 169.6 | O10: 1623.49 | P10: 378.79 | Q10: 4542.46 | R10: 4163.67 | S10: 0.91661126 | T10: 184.4 | U10: 3979.27 | V10: 2274.44 | W10: 4067.53 | X10: 1793.09 | Y10: 0.44083018 | Z10: 169.6 | AA10: 1623.49
C11: 8. Breakfast | D11: 2774.44 | E11: 4102.9 | F11: 1328.46 | G11: 0.32378562 | H11: 81.2 | I11: 1247.26 | J11: 3641.31 | K11: 5506.58 | L11: 1865.27 | M11: 0.33873475 | N11: 108.6 | O11: 1756.67 | P11: 510.05 | Q11: 5861.96 | R11: 5351.91 | S11: 0.91298985 | T11: 115 | U11: 5236.91 | V11: 3641.31 | W11: 5506.58 | X11: 1865.27 | Y11: 0.33873475 | Z11: 108.6 | AA11: 1756.67
C12: 9. Soup | D12: 0 | E12: 0 | F12: 0 | G12: 0 | H12: 0 | I12: 0 | J12: 0 | K12: 0 | L12: 0 | M12: 0 | N12: 0 | O12: 0 | P12: 0 | Q12: 0 | R12: 0 | S12: 0 | T12: 0 | U12: 0 | V12: 0 | W12: 0 | X12: 0 | Y12: 0 | Z12: 0 | AA12: 0
C13: 10. Frozen warm meals
C14: TOTAL | D14: =SUM(D4:D12) -> 46331.44 | E14: =SUM(E4:E12) -> 60957.17 | F14: =SUM(F4:F12) -> 14625.73 | G14: =IF(E14>0,(F14/E14),"") -> 0.23993453 | H14: =SUM(H4:H12) -> 1332.5 | I14: =SUM(I4:I12) -> 13293.23 | J14: =SUM(J4:J12) -> 45651.47 | K14: =SUM(K4:K12) -> 69970.24 | L14: =SUM(L4:L12) -> 24318.77 | M14: =IF(K14>0,(L14/K14),"") -> 0.34755876 | N14: =SUM(N4:N12) -> 1540.2 | O14: =SUM(O4:O12) -> 22778.57 | P14: =SUM(P4:P12) -> 5649.99 | Q14: =SUM(Q4:Q12) -> 78518.92 | R14: =SUM(R4:R12) -> 72868.93 | S14: =IF(Q14>0,(R14/Q14),"") -> 0.92804295 | T14: =SUM(T4:T12) -> 1712.1 | U14: =SUM(U4:U12) -> 71156.83 | V14: =SUM(V4:V12) -> 45651.47 | W14: =SUM(W4:W12) -> 69970.24 | X14: =SUM(X4:X12) -> 24318.77 | Y14: =IF(W14>0,(X14/W14),"") -> 0.34755876 | Z14: =SUM(Z4:Z12) -> 1540.2 | AA14: =SUM(AA4:AA12) -> 22778.57
B18: Documentation des calculs

Sheet Dispatch Data
B2: Last Updated Time: | C2: Wed Jan 28 2026 03:30:06 GMT+0000 (Coordinated Universal Time) | D2: Mon Jun 29 2026 07:57:54 GMT+0000 (Coordinated Universal Time)
B4: Weekly Dispatch Data | Q4: Monthly Dispatch Data
B6: Week No | C6: Week Start Date | D6: Fridge Name | E6: Foodcost Value | G6: Week No | H6: Week Start Date | I6: Supplier Name Name | J6: Foodcost Value | L6: Week No | M6: Week Start Date | N6: Category Name | O6: Foodcost Value | Q6: Month Name | R6: Month Start Date | S6: Fridge Name | T6: Dispatched Value | V6: Month Name | W6: Month Start Date | X6: Supplier Name | Y6: Dispatched Value | AA6: Month Name | AB6: Month Start Date | AC6: Category Name | AD6: Dispatched Value
B7: 13 | C7: 46104 | D7: Zoetis LLN | E7: 97.27 | G7: 13 | H7: 46104 | I7: Colors Kitchen | J7: 17.76 | L7: 13 | M7: 46104 | N7: 4. Warm Dishes | O7: 295.49 | Q7: March | R7: 46082 | S7: Zoetis LLN | T7: 256.08 | V7: March | W7: 46082 | X7: Colors Kitchen | Y7: 139.67 | AA7: March | AB7: 46082 | AC7: 4. Warm Dishes | AD7: 745.98
B8: 13 | C8: 46104 | D8: Allnex | E8: 31.28 | G8: 13 | H8: 46104 | I8: Mister cook | J8: 156.48 | L8: 13 | M8: 46104 | N8: 5. Desserts | O8: 714.37 | Q8: March | R8: 46082 | S8: Allnex | T8: 109.46 | V8: March | W8: 46082 | X8: Mister cook | Y8: 364.27 | AA8: March | AB8: 46082 | AC8: 5. Desserts | AD8: 1296.02
B9: 13 | C9: 46104 | D9: GSV Huppertz Wilrijk | E9: 64.22 | G9: 13 | H9: 46104 | I9: Tastyfood | J9: 121.25 | L9: 13 | M9: 46104 | N9: 6. Snacks | O9: 156.4 | Q9: March | R9: 46082 | S9: GSV Huppertz Wilrijk | T9: 174.23 | V9: March | W9: 46082 | X9: Tastyfood | Y9: 242.03 | AA9: March | AB9: 46082 | AC9: 6. Snacks | AD9: 314.84
B10: 13 | C10: 46104 | D10: Kadans Droite | E10: 49.2 | G10: 13 | H10: 46104 | I10: La Cantine de Géraldine | J10: 714.37 | L10: 13 | M10: 46104 | N10: 7. Drinks | O10: 212.14 | Q10: March | R10: 46082 | S10: Kadans Droite | T10: 153.17 | V10: March | W10: 46082 | X10: La Cantine de Géraldine | Y10: 1296.02 | AA10: March | AB10: 46082 | AC10: 7. Drinks | AD10: 378.79
B11: 13 | C11: 46104 | D11: Kadans Gauche | E11: 47.18 | G11: 13 | H11: 46104 | I11: MadLab | J11: 22 | L11: 13 | M11: 46104 | N11: 8. Breakfast | O11: 288.35 | Q11: March | R11: 46082 | S11: Kadans Gauche | T11: 152.76 | V11: March | W11: 46082 | X11: MadLab | Y11: 39.71 | AA11: March | AB11: 46082 | AC11: 8. Breakfast | AD11: 510.05
B12: 13 | C12: 46104 | D12: RTBF | E12: 654.11 | G12: 13 | H12: 46104 | I12: Gaufrine | J12: 129 | L12: 14 | M12: 46111 | N12: 1. Cold Dishes | O12: 2475.4 | Q12: March | R12: 46082 | S12: RTBF | T12: 1144.66 | V12: March | W12: 46082 | X12: Gaufrine | Y12: 221.14 | AA12: March | AB12: 46082 | AC12: 1. Cold Dishes | AD12: 915.51
B13: 13 | C13: 46104 | D13: Spadel Brussels | E13: 27.67 | G13: 13 | H13: 46104 | I13: Interdrinks | J13: 189.65 | L13: 14 | M13: 46111 | N13: 2. Wraps & Sandwiches | O13: 3269.56 | Q13: March | R13: 46082 | S13: Spadel Brussels | T13: 98.59 | V13: March | W13: 46082 | X13: Interdrinks | Y13: 340.09 | AA13: April | AB13: 46113 | AC13: 1. Cold Dishes | AD13: 8975.71
B14: 13 | C14: 46104 | D14: The Woods | E14: 133.31 | G14: 13 | H14: 46104 | I14: Full-Iz | J14: 21.56 | L14: 14 | M14: 46111 | N14: 3. Warm Dishes Jar | O14: 214.3 | Q14: March | R14: 46082 | S14: The Woods | T14: 307.11 | V14: March | W14: 46082 | X14: Full-Iz | Y14: 25.08 | AA14: March | AB14: 46082 | AC14: 2. Wraps & Sandwiches | AD14: 1415.77
B15: 13 | C15: 46104 | D15: Bia Group Overijse | E15: 22.27 | G15: 13 | H15: 46104 | I15: Seppe's | J15: 288.35 | L15: 14 | M15: 46111 | N15: 4. Warm Dishes | O15: 1576.7 | Q15: March | R15: 46082 | S15: Bia Group Overijse | T15: 110.76 | V15: March | W15: 46082 | X15: Seppe's | Y15: 510.05 | AA15: April | AB15: 46113 | AC15: 2. Wraps & Sandwiches | AD15: 13208.74
B16: 13 | C16: 46104 | D16: PWC Diegem | E16: 128.37 | G16: 14 | H16: 46111 | I16: Croc&Go | J16: 5066.24 | L16: 14 | M16: 46111 | N16: 5. Desserts | O16: 2035.77 | Q16: March | R16: 46082 | S16: PWC Diegem | T16: 284.53 | V16: March | W16: 46082 | X16: Croc&Go | Y16: 2028.28 | AA16: March | AB16: 46082 | AC16: 3. Warm Dishes Jar | AD16: 73.03
B17: 13 | C17: 46104 | D17: Brussels Airlines Be house | E17: 53.17 | G17: 14 | H17: 46111 | I17: Bon - With Love | J17: 678.72 | L17: 14 | M17: 46111 | N17: 6. Snacks | O17: 554.54 | Q17: March | R17: 46082 | S17: Brussels Airlines Be house | T17: 177.46 | V17: April | W17: 46113 | X17: Croc&Go | Y17: 18827.38 | AA17: April | AB17: 46113 | AC17: 3. Warm Dishes Jar | AD17: 686.01
B18: 13 | C18: 46104 | D18: Greenhouse Collection Antwerpen | E18: 57.37 | G18: 14 | H18: 46111 | I18: Gourmart | J18: 214.3 | L18: 14 | M18: 46111 | N18: 7. Drinks | O18: 583.27 | Q18: March | R18: 46082 | S18: Greenhouse Collection Antwerpen | T18: 182.22 | V18: March | W18: 46082 | X18: Bon - With Love | Y18: 303 | AA18: April | AB18: 46113 | AC18: 4. Warm Dishes | AD18: 6971.35
... B189: 18 | C189: 46139 | D189: Lhoist Limelette | E189: 85.55 | G189: 26 | H189: 46195 | I189: Tropbon | J189: 112.92 | L189: 19 | M189: 46146 | N189: 8. Breakfast | O189: 615 | Q189: July | R189: 46204 | S189: Kadans Gauche | T189: 153.89 | V189: December | W189: 45992 | X189: Tastyfood | Y189: 836.21 | AA189: March | AB189: 46082 | AC189: 3. Warm Dishes Jar | AD189: 192.69
B190: 18 | C190: 46139 | D190: Neuhaus Sint-Pieters | E190: 395.41 | G190: 26 | H190: 46195 | I190: Gaufrine | J190: 322.5 | L190: 13 | M190: 46104 | N190: 1. Cold Dishes | O190: 208.25 | Q190: July | R190: 46204 | S190: Lhoist Corbais | T190: 56.46 | V190: December | W190: 45992 | X190: Bon - With Love | Y190: 4255.17
B191: 18 | C191: 46139 | D191: PWC Diegem | E191: 519.37 | G191: 26 | H191: 46195 | I191: Big Bag | J191: 594.64 | L191: 13 | M191: 46104 | N191: 2. Wraps & Sandwiches | O191: 481.61 | Q191: July | R191: 46204 | S191: Lhoist Limelette | T191: 108.25 | V191: January | W191: 45658 | X191: Bon - With Love | Y191: 3095.07
B192: 18 | C192: 46139 | D192: PWC Ghent | E192: 136.04 | G192: 26 | H192: 46195 | I192: Seppe's | J192: 903 | L192: 13 | M192: 46104 | N192: 3. Warm Dishes Jar | O192: 11.8 | Q192: July | R192: 46204 | S192: Lhoist Nivelles | T192: 79.56 | V192: January | W192: 45658 | X192: Gourmart | Y192: 531.79
B193: 18 | C193: 46139 | D193: Police Tubize | E193: 269.98 | G193: 26 | H193: 46195 | I193: Delimeal | J193: 380.65 | L193: 20 | M193: 46153 | N193: 1. Cold Dishes | O193: 2302.65 | Q193: July | R193: 46204 | S193: Neuhaus Sint-Pieters | T193: 222.39 | V193: January | W193: 45658 | X193: Mister cook | Y193: 2714.95
B194: 18 | C194: 46139 | D194: RTBF | E194: 1706.6 | G194: 27 | H194: 46202 | I194: Croc&Go | J194: 3652.07 | L194: 20 | M194: 46153 | N194: 2. Wraps & Sandwiches | O194: 2861.62 | Q194: July | R194: 46204 | S194: PWC Diegem | T194: 167.68 | V194: January | W194: 45658 | X194: La Cantine de Géraldine | Y194: 7300.67
B195: 18 | C195: 46139 | D195: RTBF Mediasquare 2e | E195: 216.2 | G195: 27 | H195: 46202 | I195: Gourmart | J195: 48.5 | L195: 20 | M195: 46153 | N195: 3. Warm Dishes Jar | O195: 263.2 | Q195: July | R195: 46204 | S195: PWC Ghent | T195: 111.01 | V195: January | W195: 45658 | X195: MadLab | Y195: 243.71
B196: 18 | C196: 46139 | D196: Spadel Brussels | E196: 153.72 | G196: 27 | H196: 46202 | I196: Tastyfood | J196: 515.91 | L196: 20 | M196: 46153 | N196: 4. Warm Dishes | O196: 1456.86 | Q196: July | R196: 46204 | S196: Police Tubize | T196: 126.68 | V196: January | W196: 45658 | X196: Tropbon | Y196: 286.54
B197: 18 | C197: 46139 | D197: The Woods | E197: 610.56 | G197: 27 | H197: 46202 | I197: Colors Kitchen | J197: 404.6 | L197: 20 | M197: 46153 | N197: 5. Desserts | O197: 1659.2 | Q197: July | R197: 46204 | S197: RTBF | T197: 187.95 | V197: January | W197: 45658 | X197: GENEROUS | Y197: 63.26
B198: 18 | C198: 46139 | D198: Thermofisher Vilvoorde | E198: 92.94 | G198: 27 | H198: 46202 | I198: Greenz | J198: 430.17 | L198: 20 | M198: 46153 | N198: 6. Snacks | O198: 445.26 | Q198: July | R198: 46204 | S198: RTBF Mediasquare 2e | T198: 258.83 | V198: January | W198: 45658 | X198: Gaufrine | Y198: 707.29
B199: 18 | C199: 46139 | D199: Thermofisher Zaventem | E199: 367.41 | G199: 27 | H199: 46202 | I199: La Cantine de Géraldine | J199: 1071.55 | L199: 20 | M199: 46153 | N199: 7. Drinks | O199: 509.22 | Q199: July | R199: 46204 | S199: RTBF Mediasquare 4e | T199: 186.12 | V199: January | W199: 45658 | X199: Interdrinks | Y199: 1305.79
B200: 18 | C200: 46139 | D200: Velux | E200: 67.2 | G200: 27 | H200: 46202 | I200: Betty&Albert | J200: 32.4 | L200: 20 | M200: 46153 | N200: 8. Breakfast | O200: 954.05 | Q200: July | R200: 46204 | S200: Spadel Brussels | T200: 98.34 | V200: January | W200: 45658 | X200: Seppe's | Y200: 1892.99
B201: 18 | C201: 46139 | D201: Zoetis LLN | E201: 577.31 | G201: 27 | H201: 46202 | I201: Tropbon | J201: 89.88 | L201: 20 | M201: 46153 | N201: 10. Frozen Warm Dishes | O201: 513.3 | Q201: July | R201: 46204 | S201: The Woods | T201: 229.54 | V201: January | W201: 45658 | X201: Croc&Go | Y201: 15707.22
... B333: 21 | C333: 46160 | D333: Engie Namur | E333: 145.19 | G333: 22 | H333: 46167 | I333: Tastyfood | J333: 529.45 | L333: 52 | M333: 46013 | N333: 9. Soup | O333: 206.8 | Q333: June | R333: 46174 | S333: CBC | T333: 823.43 | V333: March | W333: 46082 | X333: Big Bag | Y333: 0.62
B334: 21 | C334: 46160 | D334: GSV Huppertz Wilrijk | E334: 409.31 | G334: 22 | H334: 46167 | I334: Mister cook | J334: 345 | L334: 1 | M334: 46020 | N334: 1. Cold Dishes | O334: 749.7 | Q334: June | R334: 46174 | S334: DPG Media Antwerpen | T334: 1047.05
B335: 21 | C335: 46160 | D335: Lhoist Corbais | E335: 72.04 | G335: 22 | H335: 46167 | I335: Colors Kitchen | J335: 422.45 | L335: 1 | M335: 46020 | N335: 2. Wraps & Sandwiches | O335: 1199.82 | Q335: June | R335: 46174 | S335: DPG Media Vilvoorde | T335: 994.87
B336: 21 | C336: 46160 | D336: Lhoist Nivelles | E336: 103.93 | G336: 22 | H336: 46167 | I336: La Cantine de Géraldine | J336: 1580 | L336: 1 | M336: 46020 | N336: 3. Warm Dishes Jar | O336: 160.4 | Q336: June | R336: 46174 | S336: Engie Garden Café Heat and Eat | T336: 434.64
B337: 21 | C337: 46160 | D337: Engie Garden Café Wrap & Roll | E337: 182.85 | G337: 22 | H337: 46167 | I337: Betty&Albert | J337: 82.08 | L337: 1 | M337: 46020 | N337: 4. Warm Dishes | O337: 568.61 | Q337: June | R337: 46174 | S337: Engie Namur | T337: 591.95
B338: 21 | C338: 46160 | D338: Allnex Freezer | E338: 111.83 | G338: 22 | H338: 46167 | I338: Tropbon | J338: 139.2 | L338: 1 | M338: 46020 | N338: 5. Desserts | O338: 562.36 | Q338: June | R338: 46174 | S338: GSV Huppertz Wilrijk | T338: 888.96
B339: 21 | C339: 46160 | D339: DPG Media Vilvoorde | E339: 127.86 | G339: 22 | H339: 46167 | I339: Gaufrine | J339: 347.01 | L339: 1 | M339: 46020 | N339: 6. Snacks | O339: 158.16 | Q339: June | R339: 46174 | S339: Greenhouse Collection Antwerpen | T339: 839.91
B340: 22 | C340: 46167 | D340: Abbott Wavre | E340: 88.3 | G340: 22 | H340: 46167 | I340: Big Bag | J340: 870.9 | L340: 1 | M340: 46020 | N340: 7. Drinks | O340: 116.24 | Q340: June | R340: 46174 | S340: Greenhouse Collection Links | T340: 674.25
B341: 22 | C341: 46167 | D341: Allianz Brussels | E341: 215.55 | G341: 22 | H341: 46167 | I341: Seppe's | J341: 285 | L341: 1 | M341: 46020 | N341: 8. Breakfast | O341: 54.25 | Q341: June | R341: 46174 | S341: Interparking | T341: 633.11
B342: 22 | C342: 46167 | D342: Allnex | E342: 308.32 | G342: 22 | H342: 46167 | I342: Delimeal | J342: 285.6 | L342: 2 | M342: 46027 | N342: 1. Cold Dishes | O342: 1951.6 | Q342: June | R342: 46174 | S342: Kadans Droite | T342: 1071.85
B343: 22 | C343: 46167 | D343: Bank Degroof | E343: 75.12 | G343: 22 | H343: 46167 | I343: Greenz | J343: 12.2 | L343: 2 | M343: 46027 | N343: 2. Wraps & Sandwiches | O343: 2706.74 | Q343: June | R343: 46174 | S343: Kadans Gauche | T343: 1059.07
B344: 22 | C344: 46167 | D344: Bia Group Overijse | E344: 172.16 | G344: 23 | H344: 46174 | I344: Croc&Go | J344: 5843.43 | L344: 2 | M344: 46027 | N344: 4. Warm Dishes | O344: 1707.39 | Q344: June | R344: 46174 | S344: Lhoist Limelette | T344: 453.16
B345: 22 | C345: 46167 | D345: Brussels Airlines Airport | E345: 170.85 | G345: 23 | H345: 46174 | I345: Gourmart | J345: 141.85 | L345: 2 | M345: 46027 | N345: 5. Desserts | O345: 1733.76 | Q345: June | R345: 46174 | S345: Neuhaus Sint-Pieters | T345: 1242.17
... B818: 19 | C818: 46146 | D818: Police Tubize | E818: 232.58 | G818: 45 | H818: 45964 | I818: Croc&Go | J818: 3781.87 | L818: 7 | M818: 46062 | N818: 4. Warm Dishes | O818: 146 | Q818: March | R818: 46082 | S818: Van Mieghem Tubize | T818: 349.24
B819: 19 | C819: 46146 | D819: RTBF | E819: 1219.12 | G819: 45 | H819: 45964 | I819: Gourmart | J819: 210.9 | L819: 7 | M819: 46062 | N819: 5. Desserts | O819: 213.89
B820: 19 | C820: 46146 | D820: RTBF Mediasquare 2e | E820: 193.99 | G820: 45 | H820: 45964 | I820: La Cantine de Géraldine | J820: 1724.95 | L820: 7 | M820: 46062 | N820: 6. Snacks | O820: 1.2
B821: 19 | C821: 46146 | D821: Spadel Brussels | E821: 214.78 | G821: 45 | H821: 45964 | I821: MadLab | J821: 104 | L821: 7 | M821: 46062 | N821: 7. Drinks | O821: 85.73
B822: 19 | C822: 46146 | D822: The Woods | E822: 512.14 | G822: 45 | H822: 45964 | I822: Tropbon | J822: 227.88 | L822: 7 | M822: 46062 | N822: 8. Breakfast | O822: 80.85
B823: 19 | C823: 46146 | D823: Thermofisher Vilvoorde | E823: 156.13 | G823: 45 | H823: 45964 | I823: GENEROUS | J823: 9.6 | L823: 7 | M823: 46062 | N823: 9. Soup | O823: 9
B824: 19 | C824: 46146 | D824: Thermofisher Zaventem | E824: 354.58 | G824: 45 | H824: 45964 | I824: Gaufrine | J824: 369.92 | L824: 8 | M824: 46069 | N824: 1. Cold Dishes | O824: 1963.5
B825: 19 | C825: 46146 | D825: Velux | E825: 92.92 | G825: 45 | H825: 45964 | I825: Interdrinks | J825: 405.46 | L825: 8 | M825: 46069 | N825: 2. Wraps & Sandwiches | O825: 2904.26
B826: 19 | C826: 46146 | D826: Zoetis LLN | E826: 739.49 | G826: 45 | H826: 45964 | I826: RISH | J826: 95.52 | L826: 8 | M826: 46069 | N826: 3. Warm Dishes Jar | O826: 228.5
B827: 19 | C827: 46146 | D827: Engie Garden Café Wrap & Roll | E827: 258 | G827: 45 | H827: 45964 | I827: Seppe's | J827: 557.75 | L827: 8 | M827: 46069 | N827: 4. Warm Dishes | O827: 1387.37
B828: 13 | C828: 46104 | D828: DPG Media Antwerpen | E828: 258.14 | G828: 45 | H828: 45964 | I828: Colors Kitchen | J828: 1063.7 | L828: 8 | M828: 46069 | N828: 5. Desserts | O828: 2087.71
B829: 13 | C829: 46104 | D829: DPG Media Vilvoorde | E829: 170.74 | G829: 45 | H829: 45964 | I829: Bon - With Love | J829: 363.6 | L829: 8 | M829: 46069 | N829: 6. Snacks | O829: 432.21
B830: 13 | C830: 46104 | D830: Police Tubize | E830: 106.32 | G830: 45 | H830: 45964 | I830: Mister cook | J830: 719 | L830: 8 | M830: 46069 | N830: 7. Drinks | O830: 385.69
... B855: 20 | C855: 46153 | D855: Lhoist Nivelles | E855: 79.63 | G855: 47 | H855: 45978 | I855: Tropbon | J855: 158.56 | L855: 11 | M855: 46090 | N855: 8. Breakfast | O855: 531.15
B856: 20 | C856: 46153 | D856: Neuhaus Sint-Pieters | E856: 418.68 | G856: 47 | H856: 45978 | I856: GENEROUS | J856: 16.8
B857: 20 | C857: 46153 | D857: PWC Diegem | E857: 415.7 | G857: 47 | H857: 45978 | I857: Gaufrine | J857: 385.71
B858: 20 | C858: 46153 | D858: PWC Ghent | E858: 110.61 | G858: 47 | H858: 45978 | I858: Interdrinks | J858: 392.02
B859: 20 | C859: 46153 | D859: Police Tubize | E859: 259.09 | G859: 47 | H859: 45978 | I859: RISH | J859: 67.66
B860: 20 | C860: 46153 | D860: RTBF | E860: 1213.42 | G860: 47 | H860: 45978 | I860: Seppe's | J860: 742.15
B861: 20 | C861: 46153 | D861: RTBF Mediasquare 2e | E861: 531.84 | G861: 47 | H861: 45978 | I861: The Good Food | J861: 311.75
B862: 20 | C862: 46153 | D862: RTBF Mediasquare 4e | E862: 707.57 | G862: 47 | H862: 45978 | I862: Big Bag | J862: 24.95
B863: 20 | C863: 46153 | D863: Spadel Brussels | E863: 203.88 | G863: 48 | H863: 45985 | I863: Croc&Go | J863: 3767.28
B864: 20 | C864: 46153 | D864: The Woods | E864: 480.29 | G864: 48 | H864: 45985 | I864: Bon - With Love | J864: 307.04
B865: 20 | C865: 46153 | D865: Thermofisher Vilvoorde | E865: 74.87 | G865: 48 | H865: 45985 | I865: Gourmart | J865: 852.3
B866: 20 | C866: 46153 | D866: Thermofisher Zaventem | E866: 313.26 | G866: 48 | H866: 45985 | I866: Mister cook | J866: 694.62
B867: 20 | C867: 46153 | D867: Velux | E867: 69.39 | G867: 48 | H867: 45985 | I867: Tastyfood | J867: 309.32
... B1500: 2 | C1500: 46027 | D1500: Engie Antwerpen | E1500: 54.96 | G1500: 11 | H1500: 46090 | I1500: Seppe's | J1500: 531.15
B1501: 2 | C1501: 46027 | D1501: Lhoist Corbais | E1501: 62.68
B1502: 2 | C1502: 46027 | D1502: Lhoist Limelette | E1502: 66.17
B1503: 2 | C1503: 46027 | D1503: Lhoist Nivelles | E1503: 55.6
B1504: 2 | C1504: 46027 | D1504: Van Mieghem Tubize | E1504: 177.61
B1505: 2 | C1505: 46027 | D1505: Engie Garden Café Wrap & Roll | E1505: 158.39
B1506: 3 | C1506: 46034 | D1506: ABB Zaventem | E1506: 116.8
B1507: 3 | C1507: 46034 | D1507: Abbott Wavre | E1507: 71.42
B1508: 3 | C1508: 46034 | D1508: Allnex | E1508: 164.37
B1509: 3 | C1509: 46034 | D1509: Bank Degroof | E1509: 82.86
B1510: 3 | C1510: 46034 | D1510: Bia Group Overijse | E1510: 145.71
B1511: 3 | C1511: 46034 | D1511: Brussels Airlines Be house | E1511: 233.73
B1512: 3 | C1512: 46034 | D1512: Brussels Airlines TFC | E1512: 122.14
... B1609: 5 | C1609: 46048 | D1609: Brussels Airlines TFC | E1609: 138.13
B1610: 5 | C1610: 46048 | D1610: Lhoist Corbais | E1610: 71.74 | G1610: 50 | I1610: Gaufrine | J1610: 276.06
B1611: 5 | C1611: 46048 | D1611: Lhoist Nivelles | E1611: 59.3 | G1611: 50 | I1611: Interdrinks | J1611: 269.42
B1612: 5 | C1612: 46048 | D1612: Thermofisher Vilvoorde | E1612: 75.93 | G1612: 50 | I1612: RISH | J1612: 63.68
B1613: 5 | C1613: 46048 | D1613: Engie Garden Café Wrap & Roll | E1613: 305.63 | G1613: 50 | I1613: Seppe's | J1613: 666.4
B1614: 5 | C1614: 46048 | D1614: GSV Huppertz Wilrijk | E1614: 502.12 | G1614: 50 | I1614: The Good Food | J1614: 281.25
B1615: 5 | C1615: 46048 | D1615: Van Mieghem Tubize | E1615: 170 | G1615: 51 | I1615: Croc&Go | J1615: 2561.37
B1616: 5 | C1616: 46048 | D1616: Engie Namur | E1616: 189.23 | G1616: 51 | I1616: Bon - With Love | J1616: 395.92
B1617: 6 | C1617: 46055 | D1617: RTBF | E1617: 890.06 | G1617: 51 | I1617: Gourmart | J1617: 130.3
B1618: 6 | C1618: 46055 | D1618: Engie Garden Café Wrap & Roll | E1618: 158.37 | G1618: 51 | I1618: Colors Kitchen | J1618: 351.05
B1619: 6 | C1619: 46055 | D1619: Engie Garden Café Heat and Eat | E1619: 30.53 | G1619: 51 | I1619: Tastyfood | J1619: 210.7
B1620: 6 | C1620: 46055 | D1620: ABB Zaventem | E1620: 75.4 | G1620: 51 | I1620: Mister cook | J1620: 613.56
B1621: 6 | C1621: 46055 | D1621: Brussels Airlines Vilvoorde | E1621: 78.78 | G1621: 51 | I1621: La Cantine de Géraldine | J1621: 1253.93
... B1629: 6 | C1629: 46055 | D1629: The Woods | E1629: 255.19 | G1629: 51 | I1629: The Good Food | J1629: 238.5
B1630: 6 | C1630: 46055 | D1630: Zoetis LLN | E1630: 301.46
B1631: 6 | C1631: 46055 | D1631: Allnex | E1631: 85.92
B1632: 6 | C1632: 46055 | D1632: Bia Group Overijse | E1632: 127.35
B1633: 6 | C1633: 46055 | D1633: Brussels Airlines Be house | E1633: 143.08
B1634: 6 | C1634: 46055 | D1634: GSV Huppertz Wilrijk | E1634: 191.19
B1635: 6 | C1635: 46055 | D1635: Thermofisher Vilvoorde | E1635: 37.5
...

Sheet Added Data
C4: Weekly Added Data | R4: Monthly Added Data
C6: Week No | D6: Start Date | E6: Fridge Name | F6: Added Value | H6: Week No | I6: Start Date | J6: Supplier Name Name | K6: Added Value | M6: Week No | N6: Start Date | O6: Category Name | P6: Added Value | R6: Month Name | S6: Start Date | T6: Fridge Name | U6: Added Value | W6: Month Name | X6: Start Date | Y6: Supplier Name | Z6: Added Value | AB6: Month Name | AC6: Start Date | AD6: Category Name | AE6: Added Value
C7: 44 | D7: 45957 | E7: Velux | F7: 54.13 | H7: 44 | I7: 45957 | J7: La Cantine de Géraldine | K7: 1749.85 | M7: 44 | N7: 45957 | O7: 5. Desserts | P7: 1749.85 | R7: October | S7: 45931 | T7: Bia Group Overijse | U7: 1149.76 | W7: October | X7: 45931 | Y7: Croc&Go | Z7: 16007.51 | AB7: October | AC7: 45931 | AD7: 2. Wraps & Sandwiches | AE7: 11779.67
C8: 44 | D8: 45957 | E8: Bia Group Overijse | F8: 263.09 | H8: 44 | I8: 45957 | J8: Croc&Go | K8: 4585.32 | M8: 44 | N8: 45957 | O8: 2. Wraps & Sandwiches | P8: 3056.38 | R8: October | S8: 45931 | T8: Thermofisher | U8: 1391.91 | W8: October | X8: 45931 | Y8: Gaufrine | Z8: 1587.08 | AB8: October | AC8: 45931 | AD8: 6. Snacks | AE8: 2143.76
C9: 44 | D9: 45957 | E9: Lhoist Limelette | F9: 74.2 | H9: 44 | I9: 45957 | J9: Gaufrine | K9: 448.36 | M9: 44 | N9: 45957 | O9: 6. Snacks | P9: 541.16 | R9: October | S9: 45931 | T9: Kadans Droite | U9: 1435.75 | W9: October | X9: 45931 | Y9: La Cantine de Géraldine | Z9: 7042.65 | AB9: October | AC9: 45931 | AD9: 5. Desserts | AE9: 7042.65
C10: 44 | D10: 45957 | E10: Police Tubize | F10: 279.87 | H10: 44 | I10: 45957 | J10: Seppe's | K10: 679.4 | M10: 44 | N10: 45957 | O10: 8. Breakfast | P10: 679.4 | R10: October | S10: 45931 | T10: ABB Zaventem | U10: 1265.14 | W10: October | X10: 45931 | Y10: Interdrinks | Z10: 1834.2 | AB10: October | AC10: 45931 | AD10: 7. Drinks | AE10: 2181.23
C11: 44 | D11: 45957 | E11: Thermofisher | F11: 334.96 | H11: 44 | I11: 45957 | J11: Bon - With Love | K11: 339.36 | M11: 44 | N11: 45957 | O11: 4. Warm Dishes | P11: 1580.44 | R11: October | S11: 45931 | T11: Neuhaus Sint-Pieters | U11: 1863.77 | W11: October | X11: 45931 | Y11: MadLab | Z11: 152 | AB11: October | AC11: 45931 | AD11: 1. Cold Dishes | AE11: 7435
C12: 44 | D12: 45957 | E12: Abbott Wavre | F12: 82.42 | H12: 44 | I12: 45957 | J12: Mister cook | K12: 946.6 | M12: 44 | N12: 45957 | O12: 1. Cold Dishes | P12: 1868.3 | R12: October | S12: 45931 | T12: Kadans Gauche | U12: 1367.05 | W12: October | X12: 45931 | Y12: Mister cook | Z12: 2841.86 | AB12: October | AC12: 45931 | AD12: 4. Warm Dishes | AE12: 5959.22
C13: 44 | D13: 45957 | E13: Allnex | F13: 286.8 | H13: 44 | I13: 45957 | J13: Tastyfood | K13: 633.84 | M13: 44 | N13: 45957 | O13: 7. Drinks | P13: 422.23 | R13: October | S13: 45931 | T13: Allnex | U13: 1182 | W13: October | X13: 45931 | Y13: Tastyfood | Z13: 3117.36 | AB13: October | AC13: 45931 | AD13: 3. Warm Dishes Jar | AE13: 1157.25
C14: 44 | D14: 45957 | E14: GSV Huppertz Wilrijk | F14: 427.82 | H14: 44 | I14: 45957 | J14: Interdrinks | K14: 331.91 | M14: 44 | N14: 45957 | O14: 3. Warm Dishes Jar | P14: 497.25 | R14: October | S14: 45931 | T14: GSV Huppertz Wilrijk | U14: 1782.27 | W14: October | X14: 45931 | Y14: Gourmart | Z14: 1157.25 | AB14: October | AC14: 45931 | AD14: 8. Breakfast | AE14: 2355.35
C15: 44 | D15: 45957 | E15: The Woods | F15: 623.575 | H15: 44 | I15: 45957 | J15: GENEROUS | K15: 24 | M15: 43 | N15: 45950 | O15: 4. Warm Dishes | P15: 1232.97 | R15: October | S15: 45931 | T15: PWC Diegem | U15: 2812.79 | W15: October | X15: 45931 | Y15: Tropbon | Z15: 326.68 | AB15: October | AC15: 45931 | AD15: 9. Soup | AE15: 17.6
C16: 44 | D16: 45957 | E16: Van Mieghem Tubize | F16: 133.12 | H16: 44 | I16: 45957 | J16: MadLab | K16: 10 | M16: 43 | N16: 45950 | O16: 6. Snacks | P16: 464.92 | R16: October | S16: 45931 | T16: The Woods | U16: 2735.695 | W16: October | X16: 45931 | Y16: Seppe's | Z16: 2355.35 | AB16: September | AC16: 45901 | AD16: 1. Cold Dishes | AE16: 7080.5
C17: 44 | D17: 45957 | E17: Kadans Gauche | F17: 344.08 | H17: 44 | I17: 45957 | J17: Tropbon | K17: 58.8 | M17: 43 | N17: 45950 | O17: 2. Wraps & Sandwiches | P17: 2579.82 | R17: October | S17: 45931 | T17: Spadel Brussels | U17: 1520.29 | W17: October | X17: 45931 | Y17: RISH | Z17: 314.42 | AB17: September | AC17: 45901 | AD17: 2. Wraps & Sandwiches | AE17: 11219.47
C18: 44 | D18: 45957 | E18: Kadans Droite | F18: 338.67 | H18: 44 | I18: 45957 | J18: Gourmart | K18: 497.25 | M18: 43 | N18: 45950 | O18: 5. Desserts | P18: 1777.5 | R18: October | S18: 45931 | T18: Brussels Airlines Be house | U18: 1782.84 | W18: October | X18: 45931 | Y18: GENEROUS | Z18: 78 | AB18: September | AC18: 45901 | AD18: 8. Breakfast | AE18: 2796.75
... C35: 44 | D35: 45957 | E35: Engie Garden Café Wrap & Roll | F35: 262.61 | H35: 42 | I35: 45943 | J35: Croc&Go | K35: 2946.15 | M35: 41 | N35: 45936 | O35: 4. Warm Dishes | P35: 1474.81 | R35: October | S35: 45931 | T35: PWC Ghent | U35: 723.46 | W35: September | X35: 45901 | Y35: Greenz | Z35: 401.33 | AB35: November | AC35: 45962 | AD35: 5. Desserts | AE35: 7984.13
C36: 44 | D36: 45957 | E36: Brussels Airlines Vilvoorde | F36: 322.86 | H36: 42 | I36: 45943 | J36: Bon - With Love | K36: 1768.54 | M36: 41 | N36: 45936 | O36: 2. Wraps & Sandwiches | P36: 2379.1 | R36: October | S36: 45931 | T36: Bank Degroof | U36: 385.07 | W36: September | X36: 45901 | Y36: Unknown | AB36: November | AC36: 45962 | AD36: 1. Cold Dishes | AE36: 7412.17
C37: 44 | D37: 45957 | E37: Engie Garden Café Heat and Eat | F37: 105.03 | H37: 42 | I37: 45943 | J37: Seppe's | K37: 507 | M37: 41 | N37: 45936 | O37: 1. Cold Dishes | P37: 1404.2 | R37: October | S37: 45931 | T37: Engie Namur | U37: 714.23 | W37: August | X37: 45870 | Y37: Tastyfood | Z37: 2156.16 | AB37: November | AC37: 45962 | AD37: 8. Breakfast | AE37: 2225.25
C38: 44 | D38: 45957 | E38: Brussels Airlines TFC | F38: 237.2 | H38: 42 | I38: 45943 | J38: Gaufrine | K38: 420.5 | M38: 41 | N38: 45936 | O38: 6. Snacks | P38: 374.55 | R38: October | S38: 45931 | T38: Lhoist Corbais | U38: 210.48 | W38: August | X38: 45870 | Y38: Seppe's | Z38: 3137.65 | AB38: November | AC38: 45962 | AD38: 7. Drinks | AE38: 1884.6925
C39: 44 | D39: 45957 | E39: Interparking | F39: 304.63 | H39: 42 | I39: 45943 | J39: MadLab | K39: 26 | M39: 41 | N39: 45936 | O39: 3. Warm Dishes Jar | P39: 188.2 | R39: October | S39: 45931 | T39: Engie Antwerpen | U39: 224.6 | W39: August | X39: 45870 | Y39: Gourmart | Z39: 1820.9 | AB39: November | AC39: 45962 | AD39: 6. Snacks | AE39: 2365.78
C40: 44 | D40: 45957 | E40: Allianz Brussels | F40: 212.4 | H40: 42 | I40: 45943 | J40: Mister cook | K40: 325.8 | M40: 40 | N40: 45929 | O40: 7. Drinks | P40: 505.41 | R40: October | S40: 45931 | T40: Interparking | U40: 789.11 | W40: August | X40: 45870 | Y40: Mister cook | Z40: 1473.82 | AB40: November | AC40: 45962 | AD40: 3. Warm Dishes Jar | AE40: 1543.6
C41: 44 | D41: 45957 | E41: DPG Media Vilvoorde | F41: 456.86 | H41: 42 | I41: 45943 | J41: Tastyfood | K41: 1012.64 | M41: 40 | N41: 45929 | O41: 6. Snacks | P41: 592.75 | R41: October | S41: 45931 | T41: Brussels Airlines TFC | U41: 769.96 | W41: August | X41: 45870 | Y41: La Cantine de Géraldine | Z41: 2913.25 | AB41: November | AC41: 45962 | AD41: 9. Soup | AE41: 951.225
C42: 43 | D42: 45950 | E42: Velux | F42: 63.06 | H42: 42 | I42: 45943 | J42: Tropbon | K42: 118.44 | M42: 40 | N42: 45929 | O42: 2. Wraps & Sandwiches | P42: 2354.66 | R42: September | S42: 45901 | T42: Bia Group Overijse | U42: 1390.35 | W42: August | X42: 45870 | Y42: Interdrinks | Z42: 1287.55 | AB42: December | AC42: 45992 | AD42: 4. Warm Dishes | AE42: 6268.23
C43: 43 | D43: 45950 | E43: Police Tubize | F43: 223.13 | H43: 42 | I43: 45943 | J43: GENEROUS | K43: 28.8 | M43: 40 | N43: 45929 | O43: 5. Desserts | P43: 1494.1 | R43: September | S43: 45901 | T43: Velux | U43: 428.63 | W43: August | X43: 45870 | Y43: Gaufrine | Z43: 1231.65 | AB43: December | AC43: 45992 | AD43: 6. Snacks | AE43: 1776.53
C44: 43 | D44: 45950 | E44: Thermofisher | F44: 256.43 | H44: 42 | I44: 45943 | J44: Gourmart | K44: 253.85 | M44: 40 | N44: 45929 | O44: 4. Warm Dishes | P44: 1237.36 | R44: September | S44: 45901 | T44: GSV Huppertz Wilrijk | U44: 465.69 | W44: August | X44: 45870 | Y44: Croc&Go | Z44: 12017.52 | AB44: December | AC44: 45992 | AD44: 2. Wraps & Sandwiches | AE44: 10584.38
C45: 43 | D45: 45950 | E45: Lhoist Limelette | F45: 81.24 | H45: 42 | I45: 45943 | J45: Interdrinks | K45: 501.98 | M45: 40 | N45: 45929 | O45: 1. Cold Dishes | P45: 1529.15 | R45: September | S45: 45901 | T45: Brussels Airlines Airport | U45: 959.21 | W45: August | X45: 45870 | Y45: Bon - With Love | Z45: 1335.34 | AB45: December | AC45: 45992 | AD45: 5. Desserts | AE45: 6828.69
C46: 43 | D46: 45950 | E46: Bia Group Overijse | F46: 255.6 | H46: 42 | I46: 45943 | J46: RISH | K46: 111.44 | M46: 40 | N46: 45929 | O46: 8. Breakfast | P46: 658.55 | R46: September | S46: 45901 | T46: Bank Degroof | U46: 662.87 | W46: August | X46: 45870 | Y46: MadLab | Z46: 238 | AB46: December | AC46: 45992 | AD46: 1. Cold Dishes | AE46: 7187.01
C47: 43 | D47: 45950 | E47: ABB Zaventem | F47: 298.64 | H47: 41 | I47: 45936 | J47: Interdrinks | K47: 414.52 | M47: 40 | N47: 45929 | O47: 3. Warm Dishes Jar | P47: 222.7 | R47: September | S47: 45901 | T47: Lhoist Limelette | U47: 412.01 | W47: August | X47: 45870 | Y47: Tropbon | Z47: 256.6 | AB47: December | AC47: 45992 | AD47: 7. Drinks | AE47: 1629.51
C48: 43 | D48: 45950 | E48: Allnex | F48: 258.15 | H48: 41 | I48: 45936 | J48: Seppe's | K48: 588.25 | M48: 40 | N48: 45929 | O48: 9. Soup | P48: 2.2 | R48: September | S48: 45901 | T48: Thermofisher | U48: 1813.06 | W48: August | X48: 45870 | Y48: GENEROUS | Z48: 44.4 | AB48: December | AC48: 45992 | AD48: 8. Breakfast | AE48: 2697.55
... C57: 43 | D57: 45950 | E57: Kadans Droite | F57: 289.09 | H57: 41 | I57: 45936 | J57: Tropbon | K57: 73.32 | M57: 38 | N57: 45915 | O57: 7. Drinks | P57: 430.42 | R57: September | S57: 45901 | T57: ABB Zaventem | U57: 1343.57 | W57: November | X57: 45962 | Y57: Colors Kitchen | Z57: 3053.54 | AB57: February | AC57: 46054 | AD57: 8. Breakfast | AE57: 4625.95
C58: 43 | D58: 45950 | E58: PWC Diegem | F58: 601.45 | H58: 41 | I58: 45936 | J58: GENEROUS | K58: 4.8 | M58: 38 | N58: 45915 | O58: 8. Breakfast | P58: 598.45 | R58: September | S58: 45901 | T58: Engie Antwerpen | U58: 313.31 | W58: November | X58: 45962 | Y58: Bon - With Love | Z58: 2119.4 | AB58: February | AC58: 46054 | AD58: 9. Soup
C59: 43 | D59: 45950 | E59: Lhoist Nivelles | F59: 96.74 | H59: 41 | I59: 45936 | J59: RISH | K59: 49.75 | M59: 38 | N59: 45915 | O59: 5. Desserts | P59: 1402.15 | R59: September | S59: 45901 | T59: Kadans Droite | U59: 1588.8 | W59: November | X59: 45962 | Y59: Gaufrine | Z59: 1470.54 | AB59: February | AC59: 46054 | AD59: 3. Warm Dishes Jar | AE59: 16.9
C60: 43 | D60: 45950 | E60: Engie Namur | F60: 166.75 | H60: 40 | I60: 45929 | J60: Interdrinks | K60: 445.71 | M60: 38 | N60: 45915 | O60: 1. Cold Dishes | P60: 1386.35 | R60: September | S60: 45901 | T60: Van Mieghem Tubize | U60: 692.87 | W60: November | X60: 45962 | Y60: MadLab | Z60: 284 | AB60: March | AC60: 46082 | AD60: 5. Desserts | AE60: 9696.69
C61: 43 | D61: 45950 | E61: RTBF | F61: 1336.77 | H61: 40 | I61: 45929 | J61: MadLab | K61: 80 | M61: 38 | N61: 45915 | O61: 2. Wraps & Sandwiches | P61: 2433.45 | R61: September | S61: 45901 | T61: DPG Media Antwerpen | U61: 2078.77 | W61: November | X61: 45962 | Y61: Gourmart | Z61: 1543.6 | AB61: March | AC61: 46082 | AD61: 1. Cold Dishes | AE61: 11071.85
C62: 43 | D62: 45950 | E62: Lhoist Corbais | F62: 56.65 | H62: 40 | I62: 45929 | J62: Croc&Go | K62: 3570.89 | M62: 38 | N62: 45915 | O62: 4. Warm Dishes | P62: 1154.04 | R62: September | S62: 45901 | T62: Neuhaus Sint-Pieters | U62: 2292.22 | W62: November | X62: 45962 | Y62: RISH | Z62: 328.35 | AB62: March | AC62: 46082 | AD62: 2. Wraps & Sandwiches | AE62: 15960.7
C63: 43 | D63: 45950 | E63: PWC Antwerpen | F63: 62.93 | H63: 40 | I63: 45929 | J63: La Cantine de Géraldine | K63: 1494.1 | M63: 38 | N63: 45915 | O63: 6. Snacks | P63: 647.5 | R63: September | S63: 45901 | T63: Engie Garden Café Wrap & Roll | U63: 1297.84 | W63: November | X63: 45962 | Y63: GENEROUS | Z63: 82.8 | AB63: March | AC63: 46082 | AD63: 4. Warm Dishes | AE63: 8254.33
C64: 43 | D64: 45950 | E64: Brussels Airlines Vilvoorde | F64: 140.4 | H64: 40 | I64: 45929 | J64: Tastyfood | K64: 703.96 | M64: 38 | N64: 45915 | O64: 3. Warm Dishes Jar | P64: 217.3 | R64: September | S64: 45901 | T64: PWC Diegem | U64: 2382.21 | W64: November | X64: 45962 | Y64: Big Bag | Z64: 35.7625 | AB64: March | AC64: 46082 | AD64: 7. Drinks | AE64: 2592.34
C65: 43 | D65: 45950 | E65: Brussels Airlines Be house | F65: 378.36 | H65: 40 | I65: 45929 | J65: Bon - With Love | K65: 315.12 | M65: 37 | N65: 45908 | O65: 5. Desserts | P65: 1299.1 | R65: September | S65: 45901 | T65: Brussels Airlines Vilvoorde | U65: 427.82 | W65: November | X65: 45962 | Y65: The Good Food | Z65: 951.225 | AB65: March | AC65: 46082 | AD65: 6. Snacks | AE65: 2479.61
C66: 43 | D66: 45950 | E66: CBC | F66: 239.26 | H66: 40 | I66: 45929 | J66: GENEROUS | K66: 14.4 | M66: 37 | N66: 45908 | O66: 6. Snacks | P66: 789.71 | R66: September | S66: 45901 | T66: Engie Garden Café Heat and Eat | U66: 534.6 | W66: December | X66: 45992 | Y66: Tastyfood | Z66: 882.05 | AB66: March | AC66: 46082 | AD66: 8. Breakfast | AE66: 5288.7
C67: 43 | D67: 45950 | E67: Bank Degroof | F67: 87.08 | H67: 40 | I67: 45929 | J67: Seppe's | K67: 658.55 | M67: 37 | N67: 45908 | O67: 8. Breakfast | P67: 490.6 | R67: September | S67: 45901 | T67: Lhoist Corbais | U67: 346.55 | W67: December | X67: 45992 | Y67: Gaufrine | Z67: 1123.57 | AB67: March | AC67: 46082 | AD67: 3. Warm Dishes Jar | AE67: 647.5
C68: 43 | D68: 45950 | E68: Engie Antwerpen | F68: 48.86 | H68: 40 | I68: 45929 | J68: Mister cook | K68: 533.4 | M68: 37 | N68: 45908 | O68: 2. Wraps & Sandwiches | P68: 2695.32 | R68: September | S68: 45901 | T68: DPG Media Vilvoorde | U68: 2046.62 | W68: December | X68: 45992 | Y68: Bon - With Love | Z68: 3745.83 | AB68: April | AC68: 46113 | AD68: 1. Cold Dishes | AE68: 9752.2
C69: 43 | D69: 45950 | E69: PWC Ghent | F69: 125.76 | H69: 40 | I69: 45929 | J69: Tropbon | K69: 105.28 | M69: 37 | N69: 45908 | O69: 1. Cold Dishes | P69: 1683.85 | R69: September | S69: 45901 | T69: Spadel Brussels | U69: 1789.46 | W69: December | X69: 45992 | Y69: La Cantine de Géraldine | Z69: 6828.69 | AB69: April | AC69: 46113 | AD69: 4. Warm Dishes | AE69: 7010.27
C70: 43 | D70: 45950 | E70: Engie Garden Café Heat and Eat | F70: 182.7 | H70: 40 | I70: 45929 | J70: Gourmart | K70: 222.7 | M70: 37 | N70: 45908 | O70: 4. Warm Dishes | P70: 1085.21 | R70: September | S70: 45901 | T70: Lhoist Nivelles | U70: 382.74 | W70: December | X70: 45992 | Y70: GENEROUS | Z70: 128.4 | AB70: April | AC70: 46113 | AD70: 8. Breakfast | AE70: 3824.9
... C86: 42 | D86: 45943 | E86: Van Mieghem Tubize | F86: 106.76 | H86: 39 | I86: 45922 | J86: RISH | K86: 77.61 | M86: 35 | N86: 45894 | O86: 1. Cold Dishes | P86: 1445.85 | R86: August | S86: 45870 | T86: Allnex | U86: 1006.9 | W86: February | X86: 46054 | Y86: Interdrinks | Z86: 1632.07 | AB86: June | AC86: 46174 | AD86: 5. Desserts | AE86: 7847.8
C87: 42 | D87: 45943 | E87: ABB Zaventem | F87: 255.41 | H87: 39 | I87: 45922 | J87: Unknown | M87: 35 | N87: 45894 | O87: 6. Snacks | P87: 604.69 | R87: August | S87: 45870 | T87: Engie Namur | U87: 855.99 | W87: February | X87: 46054 | Y87: Tropbon | Z87: 607.8 | AB87: June | AC87: 46174 | AD87: 8. Breakfast | AE87: 3555.65
C88: 42 | D88: 45943 | E88: Brussels Airlines Be house | F88: 407.77 | H88: 38 | I88: 45915 | J88: Interdrinks | K88: 366.74 | M88: 35 | N88: 45894 | O88: 5. Desserts | P88: 921.2 | R88: August | S88: 45870 | T88: Van Mieghem Tubize | U88: 460.31 | W88: February | X88: 46054 | Y88: Colors Kitchen | Z88: 1211.16 | AB88: June | AC88: 46174 | AD88: 7. Drinks | AE88: 2185.01
C89: 42 | D89: 45943 | E89: Abbott Wavre | F89: 82.89 | H89: 38 | I89: 45915 | J89: Seppe's | K89: 598.45 | M89: 45 | N89: 45964 | O89: 4. Warm Dishes | P89: 1653.77 | R89: August | S89: 45870 | T89: Brussels Airlines Be house | U89: 1545.4 | W89: February | X89: 46054 | Y89: Tastyfood | Z89: 2098.39 | AB89: June | AC89: 46174 | AD89: 2. Wraps & Sandwiches | AE89: 13997.88
C90: 42 | D90: 45943 | E90: Neuhaus Sint-Pieters | F90: 427.26 | H90: 38 | I90: 45915 | J90: La Cantine de Géraldine | K90: 1402.15 | M90: 45 | N90: 45964 | O90: 2. Wraps & Sandwiches | P90: 2855.15 | R90: August | S90: 45870 | T90: PWC Antwerpen | U90: 236.56 | W90: February | X90: 46054 | Y90: Bon - With Love | Z90: 2072.52 | AB90: June | AC90: 46174 | AD90: 4. Warm Dishes | AE90: 6919.47
C91: 42 | D91: 45943 | E91: Kadans Droite | F91: 319.8 | H91: 38 | I91: 45915 | J91: Croc&Go | K91: 3457.44 | M91: 45 | N91: 45964 | O91: 5. Desserts | P91: 1786.25 | R91: August | S91: 45870 | T91: Engie Garden Café Heat and Eat | U91: 229.61 | W91: February | X91: 46054 | Y91: Seppe's | Z91: 4625.95 | AB91: June | AC91: 46174 | AD91: 1. Cold Dishes | AE91: 9964.8
C92: 42 | D92: 45943 | E92: PWC Antwerpen | F92: 70.32 | H92: 38 | I92: 45915 | J92: Tastyfood | K92: 272.16 | M92: 45 | N92: 45964 | O92: 1. Cold Dishes | P92: 2003.56 | R92: August | S92: 45870 | T92: Lhoist Corbais | U92: 191.37 | W92: February | X92: 46054 | Y92: The Good Food | AB92: June | AC92: 46174 | AD92: 3. Warm Dishes Jar | AE92: 880.75
C93: 42 | D93: 45943 | E93: Engie Garden Café Wrap & Roll | F93: 204.93 | H93: 38 | I93: 45915 | J93: Gaufrine | K93: 434.02 | M93: 45 | N93: 45964 | O93: 8. Breakfast | P93: 556.45 | R93: August | S93: 45870 | T93: Engie Garden Café Wrap & Roll | U93: 874.56 | W93: February | X93: 46054 | Y93: MadLab | Z93: 88 | AB93: June | AC93: 46174 | AD93: 6. Snacks | AE93: 2000.33
C94: 42 | D94: 45943 | E94: Kadans Gauche | F94: 311.19 | H94: 38 | I94: 45915 | J94: Mister cook | K94: 881.88 | M94: 45 | N94: 45964 | O94: 7. Drinks | P94: 448 | R94: August | S94: 45870 | T94: CBC | U94: 753.28 | W94: February | X94: 46054 | Y94: Full-Iz | Z94: 708.4 | AB94: June | AC94: 46174 | AD94: 10. Frozen Warm Dishes | AE94: 1440.56
C95: 42 | D95: 45943 | E95: Engie Garden Café Heat and Eat | F95: 119.74 | H95: 38 | I95: 45915 | J95: Bon - With Love | K95: 319.16 | M95: 45 | N95: 45964 | O95: 6. Snacks | P95: 685.79 | R95: August | S95: 45870 | T95: Engie Antwerpen | U95: 302.55 | W95: February | X95: 46054 | Y95: RISH | Z95: 276.61
C96: 42 | D96: 45943 | E96: Spadel Brussels | F96: 395.01 | H96: 38 | I96: 45915 | J96: MadLab | K96: 94 | M96: 45 | N96: 45964 | O96: 3. Warm Dishes Jar | P96: 123.1 | R96: August | S96: 45870 | T96: Neuhaus Sint-Pieters | U96: 1486.14 | W96: February | X96: 46054 | Y96: Gourmart | Z96: 16.9
C97: 42 | D97: 45943 | E97: Engie Antwerpen | F97: 45.7 | H97: 38 | I97: 45915 | J97: Tropbon | K97: 91.88 | M97: 34 | N97: 45887 | O97: 8. Breakfast | P97: 887.8 | R97: August | S97: 45870 | T97: Lhoist Nivelles | U97: 228.88 | W97: February | X97: 46054 | Y97: Boulangerie Louise | Z97: 25.2
C98: 42 | D98: 45943 | E98: Lhoist Corbais | F98: 54.23 | H98: 38 | I98: 45915 | J98: GENEROUS | K98: 27.6 | M98: 34 | N98: 45887 | O98: 5. Desserts | P98: 661.05 | R98: August | S98: 45870 | T98: Kadans Gauche | U98: 1244.65 | W98: February | X98: 46054 | Y98: GENEROUS | Z98: 6
C99: 42 | D99: 45943 | E99: Lhoist Nivelles | F99: 79.28 | H99: 38 | I99: 45915 | J99: RISH | K99: 63.68 | M99: 34 | N99: 45887 | O99: 6. Snacks | P99: 346.75 | R99: August | S99: 45870 | T99: Brussels Airlines Vilvoorde | U99: 346.06 | W99: March | X99: 46082 | Y99: La Cantine de Géraldine | Z99: 9696.69
C100: 42 | D100: 45943 | E100: DPG Media Antwerpen | F100: 403.51 | H100: 38 | I100: 45915 | J100: Gourmart | K100: 217.3 | M100: 34 | N100: 45887 | O100: 1. Cold Dishes | P100: 1326.85 | R100: August | S100: 45870 | T100: Kadans Droite | U100: 1223.58 | W100: March | X100: 46082 | Y100: Croc&Go | Z100: 23531.95
C101: 42 | D101: 45943 | E101: Brussels Airlines Airport | F101: 196.91 | H101: 38 | I101: 45915 | J101: Boulangerie Louise | K101: 43.2 | M101: 34 | N101: 45887 | O101: 2. Wraps & Sandwiches | P101: 2110.72 | R101: August | S101: 45870 | T101: DPG Media Antwerpen | U101: 1517.69 | W101: March | X101: 46082 | Y101: Tastyfood | Z101: 3089.19
C102: 42 | D102: 45943 | E102: PWC Diegem | F102: 722.38 | H102: 37 | I102: 45908 | J102: La Cantine de Géraldine | K102: 1299.1 | M102: 34 | N102: 45887 | O102: 3. Warm Dishes Jar | P102: 393.6 | R102: August | S102: 45870 | T102: Interparking | U102: 588.73 | W102: March | X102: 46082 | Y102: Interdrinks | Z102: 2101.94
C103: 42 | D103: 45943 | E103: Allianz Brussels | F103: 185.41 | H103: 37 | I103: 45908 | J103: Gaufrine | K103: 421.31 | M103: 34 | N103: 45887 | O103: 4. Warm Dishes | P103: 977 | R103: August | S103: 45870 | T103: DPG Media Vilvoorde | U103: 1415.57 | W103: March | X103: 46082 | Y103: Bon - With Love | Z103: 3232
C104: 42 | D104: 45943 | E104: PWC Ghent | F104: 174.66 | H104: 37 | I104: 45908 | J104: Seppe's | K104: 490.6 | M104: 34 | N104: 45887 | O104: 7. Drinks | P104: 387.14 | R104: August | S104: 45870 | T104: The Woods | U104: 1577.88 | W104: March | X104: 46082 | Y104: Tropbon | Z104: 460.44
C105: 42 | D105: 45943 | E105: CBC | F105: 235.81 | H105: 37 | I105: 45908 | J105: Tropbon | K105: 208.8 | M105: 46 | N105: 45971 | O105: 6. Snacks | P105: 498.76 | R105: August | S105: 45870 | T105: Spadel Brussels | U105: 913.68 | W105: March | X105: 46082 | Y105: Seppe's | Z105: 5288.7
C106: 42 | D106: 45943 | E106: RTBF | F106: 1146.07 | H106: 37 | I106: 45908 | J106: Croc&Go | K106: 4104.45 | M106: 46 | N106: 45971 | O106: 7. Drinks | P106: 453.93 | R106: August | S106: 45870 | T106: PWC Ghent | U106: 376.75 | W106: March | X106: 46082 | Y106: Mister cook | Z106: 2750.42
... C157: 40 | D157: 45929 | E157: Bank Degroof | F157: 144.37 | H157: 34 | I157: 45887 | J157: La Cantine de Géraldine | K157: 661.05 | M157: 51 | N157: 46006 | O157: 7. Drinks | P157: 440.45 | R157: December | S157: 45992 | T157: Engie Antwerpen | U157: 271.44 | W157: June | X157: 46174 | Y157: Greenz | Z157: 1452.12
C158: 40 | D158: 45929 | E158: PWC Diegem | F158: 591.04 | H158: 34 | I158: 45887 | J158: MadLab | K158: 64 | M158: 51 | N158: 46006 | O158: 9. Soup | R158: December | S158: 45992 | T158: Thermofisher Zaventem | U158: 159.42 | W158: June | X158: 46174 | Y158: Gourmart | Z158: 880.75
C159: 40 | D159: 45929 | E159: Lhoist Corbais | F159: 47.85 | H159: 34 | I159: 45887 | J159: Croc&Go | K159: 3130.6 | M159: 52 | N159: 46013 | O159: 5. Desserts | P159: 602.55 | R159: December | S159: 45992 | T159: Kadans Gauche | U159: 219.23 | W159: June | X159: 46174 | Y159: Tropbon | Z159: 531.6
C160: 40 | D160: 45929 | E160: Brussels Airlines Vilvoorde | F160: 107.49 | H160: 34 | I160: 45887 | J160: Bon - With Love | K160: 306.97 | M160: 52 | N160: 46013 | O160: 3. Warm Dishes Jar | P160: 383.5 | R160: December | S160: 45992 | T160: Van Mieghem Tubize | U160: 67.78 | W160: June | X160: 46174 | Y160: Colors Kitchen | Z160: 2053.49
C161: 40 | D161: 45929 | E161: Van Mieghem Tubize | F161: 112.39 | H161: 34 | I161: 45887 | J161: Gaufrine | K161: 225.47 | M161: 52 | N161: 46013 | O161: 1. Cold Dishes | P161: 874.65 | R161: December | S161: 45992 | T161: Kadans Droite | U161: 124.18 | W161: June | X161: 46174 | Y161: Betty&Albert | Z161: 342.36
C162: 40 | D162: 45929 | E162: Engie Antwerpen | F162: 68.05 | H162: 34 | I162: 45887 | J162: Gourmart | K162: 393.6 | M162: 52 | N162: 46013 | O162: 2. Wraps & Sandwiches | P162: 1404.66 | R162: December | S162: 45992 | T162: Brussels Airlines Vilvoorde | U162: 455.35 | W162: June | X162: 46174 | Y162: Delimeal | Z162: 1440.56
C163: 40 | D163: 45929 | E163: DPG Media Antwerpen | F163: 470.4 | H163: 34 | I163: 45887 | J163: Tastyfood | K163: 956.51 | M163: 52 | N163: 46013 | O163: 4. Warm Dishes | P163: 632.8 | R163: December | S163: 45992 | T163: Allianz Brussels | U163: 121.64 | W163: June | X163: 46174 | Y163: Gaufrine | Z163: 1100.37
C164: 40 | D164: 45929 | E164: DPG Media Vilvoorde | F164: 458.25 | H164: 34 | I164: 45887 | J164: Tropbon | K164: 48.88 | M164: 52 | N164: 46013 | O164: 8. Breakfast | P164: 382.45 | R164: December | S164: 45992 | T164: Engie Namur | U164: 202.2 | W164: June | X164: 46174 | Y164: MadLab | Z164: 20
C165: 40 | D165: 45929 | E165: Allianz Brussels | F165: 296.87 | H165: 34 | I165: 45887 | J165: Interdrinks | K165: 357.29 | M165: 52 | N165: 46013 | O165: 6. Snacks | P165: 259.12 | R165: December | S165: 45992 | T165: ABB Zaventem | U165: 152.32 | W165: June | X165: 46174 | Y165: Interdrinks | Z165: 8.65
C166: 40 | D166: 45929 | E166: Thermofisher | F166: 396.04 | H166: 34 | I166: 45887 | J166: GENEROUS | K166: 8.4 | M166: 52 | N166: 46013 | O166: 9. Soup | P166: 211.5 | R166: December | S166: 45992 | T166: DPG Media Antwerpen | U166: 376.06 | W166: June | X166: 46174 | Y166: GENEROUS | Z166: 6
C167: 40 | D167: 45929 | E167: Kadans Droite | F167: 331.6 | H167: 34 | I167: 45887 | J167: RISH | K167: 29.85 | M167: 52 | N167: 46013 | O167: 7. Drinks | P167: 212.55 | R167: December | S167: 45992 | T167: Lhoist Corbais | U167: 19.02 | W167: June | X167: 46174 | Y167: Mister cook | Z167: 1823.24
C168: 40 | D168: 45929 | E168: Lhoist Nivelles | F168: 97.08 | H168: 34 | I168: 45887 | J168: Mister cook | K168: 20.49 | M168: 7 | N168: 46062 | O168: 3. Warm Dishes Jar | R168: December | S168: 45992 | T168: Brussels Airlines TFC | U168: 570.52 | W168: June | X168: 46174 | Y168: Bon - With Love | Z168: 739.7
C169: 40 | D169: 45929 | E169: Kadans Gauche | F169: 312 | H169: 46 | I169: 45971 | J169: Gaufrine | K169: 300.56 | M169: 7 | N169: 46062 | O169: 6. Snacks | P169: 550.39 | R169: December | S169: 45992 | T169: PWC Ghent | U169: 113.5
C170: 40 | D170: 45929 | E170: Spadel Brussels | F170: 322.83 | H170: 46 | I170: 45971 | J170: Interdrinks | K170: 374.33 | M170: 7 | N170: 46062 | O170: 1. Cold Dishes | P170: 2415.7 | R170: December | S170: 45992 | T170: DPG Media Vilvoorde | U170: 443.5
C171: 40 | D171: 45929 | E171: Abbott Wavre | F171: 162.71 | H171: 46 | I171: 45971 | J171: La Cantine de Géraldine | K171: 1533.85 | M171: 7 | N171: 46062 | O171: 2. Wraps & Sandwiches | P171: 3343.97 | R171: December | S171: 45992 | T171: Spadel Brussels | U171: 115.95
C172: 40 | D172: 45929 | E172: PWC Ghent | F172: 116.21 | H172: 46 | I172: 45971 | J172: Croc&Go | K172: 3679.89 | M172: 7 | N172: 46062 | O172: 4. Warm Dishes | P172: 1736.06 | R172: December | S172: 45992 | T172: Bank Degroof | U172: 100.98
C173: 40 | D173: 45929 | E173: Engie Garden Café Heat and Eat | F173: 119.06 | H173: 46 | I173: 45971 | J173: Seppe's | K173: 482.5 | M173: 7 | N173: 46062 | O173: 8. Breakfast | P173: 1382.05 | R173: December | S173: 45992 | T173: CBC | U173: 203.25
C174: 40 | D174: 45929 | E174: Engie Garden Café Wrap & Roll | F174: 282.76 | H174: 46 | I174: 45971 | J174: Tropbon | K174: 103 | M174: 7 | N174: 46062 | O174: 5. Desserts | P174: 2311.98 | R174: December | S174: 45992 | T174: Lhoist Nivelles | U174: 26.52
C175: 40 | D175: 45929 | E175: The Woods | F175: 581.65 | H175: 46 | I175: 45971 | J175: The Good Food | K175: 238.875 | M175: 7 | N175: 46062 | O175: 9. Soup | R175: December | S175: 45992 | T175: Brussels Airlines Airport | U175: 466.26
C176: 40 | D176: 45929 | E176: Engie Namur | F176: 223.63 | H176: 46 | I176: 45971 | J176: Tastyfood | K176: 706.98 | M176: 7 | N176: 46062 | O176: 7. Drinks | P176: 548.15 | R176: December | S176: 45992 | T176: Zoetis LLN | U176: 2174.45
C177: 40 | D177: 45929 | E177: Interparking | F177: 206.97 | H177: 46 | I177: 45971 | J177: Bon - With Love | K177: 339.36 | M177: 8 | N177: 46069 | O177: 5. Desserts | P177: 2077.46 | R177: December | S177: 45992 | T177: RTBF | U177: 1283.67
C178: 40 | D178: 45929 | E178: CBC | F178: 249.69 | H178: 46 | I178: 45971 | J178: Colors Kitchen | K178: 343.36 | M178: 8 | N178: 46069 | O178: 4. Warm Dishes | P178: 1385.86 | R178: December | S178: 45992 | T178: Interparking | U178: 165.25
C179: 40 | D179: 45929 | E179: RTBF | F179: 18.7 | H179: 46 | I179: 45971 | J179: Mister cook | K179: 347.42 | M179: 8 | N179: 46069 | O179: 8. Breakfast | P179: 976.95 | R179: December | S179: 45992 | T179: Thermofisher Vilvoorde | U179: 85.46
C180: 39 | D180: 45922 | E180: Bia Group Overijse | F180: 440.73 | H180: 46 | I180: 45971 | J180: RISH | K180: 79.6 | M180: 8 | N180: 46069 | O180: 1. Cold Dishes | P180: 1939.7 | R180: December | S180: 45992 | T180: Brussels Airlines Be house | U180: 325.68
C181: 39 | D181: 45922 | E181: Brussels Airlines Airport | F181: 226.57 | H181: 46 | I181: 45971 | J181: MadLab | K181: 70 | M181: 8 | N181: 46069 | O181: 2. Wraps & Sandwiches | P181: 2877.01 | R181: February | S181: 46054 | T181: Bia Group Overijse | U181: 21.11
C182: 39 | D182: 45922 | E182: Van Mieghem Tubize | F182: 125.38 | H182: 46 | I182: 45971 | J182: GENEROUS | K182: 25.2 | M182: 8 | N182: 46069 | O182: 3. Warm Dishes Jar | P182: 5.7 | R182: February | S182: 46054 | T182: Van Mieghem Tubize | U182: 237.71
C183: 39 | D183: 45922 | E183: Allnex | F183: 254.29 | H183: 46 | I183: 45971 | J183: Gourmart | K183: 407.8 | M183: 8 | N183: 46069 | O183: 7. Drinks | P183: 478.03 | R183: February | S183: 46054 | T183: Allnex | U183: 401.08
C184: 39 | D184: 45922 | E184: GSV Huppertz Wilrijk | F184: 161.18 | H184: 47 | I184: 45978 | J184: Mister cook | K184: 386.28 | M184: 8 | N184: 46069 | O184: 6. Snacks | P184: 431.19 | R184: February | S184: 46054 | T184: Abbott Wavre | U184: 119.13
C185: 39 | D185: 45922 | E185: Brussels Airlines Be house | F185: 366.12 | H185: 47 | I185: 45978 | J185: Croc&Go | K185: 3996.32 | M185: 6 | N185: 46055 | O185: 4. Warm Dishes | P185: 1873.51 | R185: February | S185: 46054 | T185: Police Tubize | U185: 229.81
C186: 39 | D186: 45922 | E186: Abbott Wavre | F186: 137.51 | H186: 47 | I186: 45978 | J186: Interdrinks | K186: 333.69 | M186: 6 | N186: 46055 | O186: 2. Wraps & Sandwiches | P186: 3539.06 | R186: February | S186: 46054 | T186: The Woods
C187: 39 | D187: 45922 | E187: ABB Zaventem | F187: 279.98 | H187: 47 | I187: 45978 | J187: La Cantine de Géraldine | K187: 1939.05 | M187: 6 | N187: 46055 | O187: 6. Snacks | P187: 480.31 | R187: February | S187: 46054 | T187: Thermofisher Zaventem | U187: 535.08
C188: 39 | D188: 45922 | E188: Police Tubize | F188: 327.14 | H188: 47 | I188: 45978 | J188: Tastyfood | K188: 717.72 | M188: 6 | N188: 46055 | O188: 5. Desserts | P188: 2412.82 | R188: February | S188: 46054 | T188: Neuhaus Sint-Pieters | U188: 539.93
C189: 39 | D189: 45922 | E189: Engie Namur | F189: 214.27 | H189: 47 | I189: 45978 | J189: Seppe's | K189: 663.5 | M189: 6 | N189: 46055 | O189: 1. Cold Dishes | P189: 2677.5 | R189: February | S189: 46054 | T189: RTBF | U189: 91.25
C190: 39 | D190: 45922 | E190: Brussels Airlines Vilvoorde | F190: 82.41 | H190: 47 | I190: 45978 | J190: Bon - With Love | K190: 552.32 | M190: 6 | N190: 46055 | O190: 7. Drinks | P190: 1012.51 | R190: February | S190: 46054 | T190: ABB Zaventem | U190: 467.35
C191: 39 | D191: 45922 | E191: Velux | F191: 100.16 | H191: 47 | I191: 45978 | J191: MadLab | K191: 42 | M191: 6 | N191: 46055 | O191: 8. Breakfast | P191: 1272.5 | R191: February | S191: 46054 | T191: Zoetis LLN | U191: 146.78
C192: 39 | D192: 45922 | E192: Bank Degroof | F192: 109.87 | H192: 47 | I192: 45978 | J192: Gaufrine | K192: 420.53 | M192: 6 | N192: 46055 | O192: 9. Soup | P192: 4.4 | R192: February | S192: 46054 | T192: Brussels Airlines Be house | U192: 5.21
C193: 39 | D193: 45922 | E193: Neuhaus Sint-Pieters | F193: 388.86 | H193: 47 | I193: 45978 | J193: Colors Kitchen | K193: 1074.64 | M193: 6 | N193: 46055 | O193: 3. Warm Dishes Jar | P193: 11.4 | R193: February | S193: 46054 | T193: GSV Huppertz Wilrijk | U193: 44.05
...

Sheet Sales Data
B1: Weekly Sales Data | AH1: Monthly Sales Data
B3: Week No | C3: Week Start Date | D3: Fridge Name | E3: Total Product | F3: Sales Turnover | G3: Refund Amount | H3: FrigoLoco Discount | I3: Customer Credit | J3: Net Sale | L3: Week No | M3: Week Start Date | N3: Supplier Name | O3: Total Product | P3: Sales Turnover | Q3: FrigoLoco Discount | R3: Customer Credit | S3: Refund Amount | T3: Net Sale | V3: Week No | W3: Week Start Date | X3: Category Name | Y3: Total Product | Z3: Sales Turnover | AA3: FrigoLoco Discount | AB3: Customer Credit | AC3: Refund Amount | AD3: Net Sale | AH3: Month Name | AI3: Start Date | AJ3: Fridge Name | AK3: Total Product | AL3: Sales Turnover | AM3: Refund Amount | AN3: FrigoLoco Discount | AO3: Customer Credit | AP3: Net Sale | AR3: Month Name | AS3: Start Date | AT3: Supplier Name | AU3: Total Product | AV3: Sales Turnover | AW3: FrigoLoco Discount | AX3: Customer Credit | AY3: Refund Amount | AZ3: Net Sale | BB3: Month Name | BC3: Start Date | BD3: Category Name | BE3: Total Product | BF3: Sales Turnover | BG3: FrigoLoco Discount | BH3: Customer Credit | BI3: Refund Amount | BJ3: Net Sale
B4: 44 | C4: 45957 | D4: Brussels Airlines Airport | E4: 58 | F4: 181.27 | G4: 0 | H4: 0.97 | I4: 0 | J4: 181.27 | L4: 44 | M4: 45957 | N4: Interdrinks | O4: 274 | P4: 516.6 | Q4: 0 | R4: 0.46 | S4: 69.99 | T4: 586.59 | V4: 44 | W4: 45957 | X4: 7. Drinks | Y4: 313 | Z4: 630.4 | AA4: 0 | AB4: 0.46 | AC4: 76.39 | AD4: 706.79 | AH4: October | AI4: 45931 | AJ4: Engie Garden Café Heat and Eat | AK4: 191 | AL4: 719.96 | AM4: 0 | AN4: 0 | AO4: 8.08 | AP4: 728.04 | AR4: October | AS4: 45931 | AT4: La Cantine de Géraldine | AU4: 4076 | AV4: 10307.27 | AW4: 4.9 | AX4: 0 | AY4: 553.54 | AZ4: 10855.91 | BB4: October | BC4: 45931 | BD4: 5. Desserts | BE4: 4076 | BF4: 10307.27 | BG4: 4.9 | BH4: 0 | BI4: 553.54 | BJ4: 10855.91
B5: 44 | C5: 45957 | D5: Police Tubize | E5: 83 | F5: 364.15 | G5: 0 | H5: 10.31 | I5: 0 | J5: 364.15 | L5: 44 | M5: 45957 | N5: La Cantine de Géraldine | O5: 1025 | P5: 2645.23 | Q5: 0 | R5: 26.9 | S5: 84.14 | T5: 2729.37 | V5: 44 | W5: 45957 | X5: 5. Desserts | Y5: 1025 | Z5: 2645.23 | AA5: 0 | AB5: 26.9 | AC5: 84.14 | AD5: 2729.37 | AH5: October | AI5: 45931 | AJ5: Police Tubize | AK5: 333 | AL5: 1411.19 | AM5: 0 | AN5: 0 | AO5: 14.81 | AP5: 1426 | AR5: October | AS5: 45931 | AT5: Gaufrine | AU5: 1276 | AV5: 2394.2 | AW5: 4 | AX5: 0 | AY5: 172.3 | AZ5: 2562.5 | BB5: October | BC5: 45931 | BD5: 6. Snacks | BE5: 1749 | BF5: 3587.01 | BG5: 11.2 | BH5: 0 | BI5: 249.06 | BJ5: 3824.87
B6: 44 | C6: 45957 | D6: RTBF | E6: 477 | F6: 1936.39 | G6: 0 | H6: 0 | I6: 1.86 | J6: 1938.25 | L6: 44 | M6: 45957 | N6: Mister cook | O6: 152 | P6: 1139.42 | Q6: 0 | R6: 4.7 | S6: 163.54 | T6: 1302.96 | V6: 44 | W6: 45957 | X6: 4. Warm Dishes | Y6: 248 | Z6: 1859.2 | AA6: 0 | AB6: 8.06 | AC6: 258.14 | AD6: 2117.34 | AH6: October | AI6: 45931 | AJ6: Brussels Airlines Be house | AK6: 624 | AL6: 2451.77 | AM6: 17.5 | AN6: 0 | AO6: 70.9 | AP6: 2505.17 | AR6: October | AS6: 45931 | AT6: Interdrinks | AU6: 1323 | AV6: 2470.47 | AW6: 10.91 | AX6: 0 | AY6: 356.73 | AZ6: 2816.29 | BB6: October | BC6: 45931 | BD6: 7. Drinks | BE6: 1474 | BF6: 2918.79 | BG6: 10.91 | BH6: 0 | BI6: 390.81 | BJ6: 3298.69
B7: 44 | C7: 45957 | D7: DPG Media Antwerpen | E7: 144 | F7: 614.32 | G7: 0 | H7: 11.33 | I7: 0 | J7: 614.32 | L7: 44 | M7: 45957 | N7: Gaufrine | O7: 295 | P7: 561.6 | Q7: 0 | R7: 0.6 | S7: 31.3 | T7: 592.9 | V7: 44 | W7: 45957 | X7: 6. Snacks | Y7: 371 | Z7: 744.89 | AA7: 0 | AB7: 0.6 | AC7: 47.78 | AD7: 792.67 | AH7: October | AI7: 45931 | AJ7: ABB Zaventem | AK7: 390 | AL7: 1520.56 | AM7: 2.99 | AN7: 0 | AO7: 27.36 | AP7: 1544.93 | AR7: October | AS7: 45931 | AT7: Seppe's | AU7: 682 | AV7: 3112.14 | AW7: 0 | AX7: 0 | AY7: 304.36 | AZ7: 3416.5 | BB7: October | BC7: 45931 | BD7: 8. Breakfast | BE7: 684 | BF7: 3119.74 | BG7: 0 | BH7: 0 | BI7: 304.36 | BJ7: 3424.1
B8: 44 | C8: 45957 | D8: Allianz Brussels | E8: 71 | F8: 221.76 | G8: 0 | H8: 0 | I8: 0 | J8: 221.76 | L8: 44 | M8: 45957 | N8: Seppe's | O8: 172 | P8: 789.12 | Q8: 0 | R8: 1.56 | S8: 79.96 | T8: 869.08 | V8: 44 | W8: 45957 | X8: 8. Breakfast | Y8: 172 | Z8: 789.12 | AA8: 0 | AB8: 1.56 | AC8: 79.96 | AD8: 869.08 | AH8: October | AI8: 45931 | AJ8: The Woods | AK8: 713 | AL8: 3981.92 | AM8: 14.1 | AN8: 0 | AO8: 50.55 | AP8: 4018.37 | AR8: October | AS8: 45931 | AT8: Tropbon | AU8: 332 | AV8: 704.11 | AW8: 0 | AX8: 0 | AY8: 43.86 | AZ8: 747.97 | BB8: October | BC8: 45931 | BD8: 2. Wraps & Sandwiches | BE8: 2562 | BF8: 14153.37 | BG8: 18.19 | BH8: 0 | BI8: 1167.27 | BJ8: 15302.45
B9: 44 | C9: 45957 | D9: Bia Group Overijse | E9: 72 | F9: 348.88 | G9: 0 | H9: 10.78 | I9: 0 | J9: 348.88 | L9: 44 | M9: 45957 | N9: Tropbon | O9: 57 | P9: 113.74 | Q9: 0 | R9: 0 | S9: 15.04 | T9: 128.78 | V9: 44 | W9: 45957 | X9: 2. Wraps & Sandwiches | Y9: 589 | Z9: 3255.31 | AA9: 0 | AB9: 126.04 | AC9: 151.69 | AD9: 3407 | AH9: October | AI9: 45931 | AJ9: Allianz Brussels | AK9: 365 | AL9: 1201.64 | AM9: 0 | AN9: 0 | AO9: 6.31 | AP9: 1207.95 | AR9: October | AS9: 45931 | AT9: Croc&Go | AU9: 2846 | AV9: 18743.08 | AW9: 21.39 | AX9: 0 | AY9: 1276.81 | AZ9: 19998.5 | BB9: October | BC9: 45931 | BD9: 1. Cold Dishes | BE9: 934 | BF9: 8492.77 | BG9: 20.4 | BH9: 0 | BI9: 486.14 | BJ9: 8958.51
